Workbook

Sheet English
A1: Number | B1: Link | C1: Title | D1: Title (Hebrew) | E1: Description | F1: Description (Hebrew) | G1: published Date | H1: Event date from | I1: Event date to | J1: Platform | K1: Author | L1: Author (Hebrew) | M1: Source | N1: Reference | O1: Language | P1: Location | Q1: Location (Hebrew) | R1: Type | S1: Media | T1: Theme (tag) | U1: Places & Organizations (tag) | V1: Locations (tag) | W1: Figures (tag)
A2: 2384 | B2: https://www.undp.org/press-releases/new-un-report-impacts-war-have-set-back-development-gaza-much-69-years | C2: UNDP Report says development in Gaza went back by 69 years | D2: =VLOOKUP($A2,Hebrew!$A:$S,3,0) -> דו"ח חדש של UNDP אומר שחלה נסיגה של כ-69 שנים בהתפתחות עזה | E2: A new UN report highlights the severe impacts of war on Gaza's development, projecting a rise in poverty and a significant contraction in GDP and employment in the State of Palestine. | F2: =VLOOKUP($A2,Hebrew!$A:$S,4,0) -> דו"ח חדש מטעם ארגון הפיתוח של האו"ם קובעת שבלי הסרת המגבלות הכלכליות ואפשרות שיקום והשקעות בפיתוח, צפויה עלייה בעוני, צמצום בתמ"ג וברמת התעסוקה בכלכלה הפלסטינית | G2: October 22, 2024 | J2: UNDP (UN Development Programme) | K2: United Nations Development Programme | L2: =VLOOKUP($A2,Hebrew!$A:$S,9,0) -> תכנית הפיתוח של האו"ם (UNPD) | N2: https://www.undp.org/arab-states/publications/gaza-war-expected-socio-economic-impacts-state-palestine-october-2024 | O2: English | P2: Gaza Strip | Q2: =VLOOKUP($A2,Hebrew!$A:$S,13,0) -> רצועת עזה | R2: Official Report | S2: Text | T2: Economy, Humanitarian Aid, Blockade, Reconstruction | V2: Gaza Strip
A3: 2385 | B3: https://www.haaretz.co.il/opinions/2024-12-22/ty-article-opinion/.premium/00000193-ea47-d35c-a79f-fae7bf390000 | C3: Brigadier General Vach's Worldview is Known. Nonetheless, He was Charged with Commanding a Sensitive Area | D3: =VLOOKUP(A3,Hebrew!A:C,3,0) -> השקפת העולם של תא"ל ואך ידועה. למרות זאת הופקד על גזרה רגישה בעזה | E3: The opinion piece discusses the military actions in Gaza and the controversial decisions made by Brigadier General Yehuda Vach, despite the sensitivity of the situation. | F3: =VLOOKUP($A3,Hebrew!$A:$S,4,0) -> מאמר הדעה דן בפעילות הצבא ברצועת עזה וחילוקי הדעות סביב החלטות תא"ל וואך, למרות רגישות המצב | G3: December 22, 2024 | H3: August 7, 2024 | J3: Haaretz | K3: Yagil Levi | L3: =VLOOKUP($A3,Hebrew!$A:$S,9,0) -> יגיל לוי | N3: https://www.haaretz.co.il/news/magazine/2024-12-18/ty-article-magazine/.premium/00000193-d01a-dcf9-afbb-deff388f0000 | O3: Hebrew | P3: Netzarim Corridor | Q3: =VLOOKUP($A3,Hebrew!$A:$S,13,0) -> מסדרון נצרים | R3: Opinion | S3: Text | T3: Ethnic Cleansing, Rules of Engagement, Religious Right | U3: IDF (Israel Defense Forces) | V3: Netzarim Corridor
A4: 2386 | B4: https://reliefweb.int/report/occupied-palestinian-territory/israels-assault-foundations-international-law-must-have-consequences-un-experts | C4: UN: Israel must have consequnces for attacking humanitarian law | D4: =VLOOKUP(A4,Hebrew!A:C,3,0) -> האו"ם: על ישראל לשאת בשלכות של הפרת הדין הבינלאומי | E4: UN experts condemn Israel's violations of international law in the occupied Palestinian territory and call for accountability for crimes against humanity and war crimes. | F4: =VLOOKUP($A4,Hebrew!$A:$S,4,0) -> מומחי האו"ם מאשימים את ישראל בהפרת החוק הבינלאומי בשטחים הפלסטינים הכבושים וקוראים להכרה בפשעים נגד האנושות ופשעי מלחמה. | G4: December 30, 2024 | J4: ReliefWeb | K4: ReliefWeb | L4: =VLOOKUP($A4,Hebrew!$A:$S,9,0) -> ReliefWeb | N4: https://www.ohchr.org/en/press-releases/2024/12/israels-assault-foundations-international-law-must-have-consequences-un?sub-site=HRC | O4: English | P4: Gaza Strip | Q4: =VLOOKUP($A4,Hebrew!$A:$S,13,0) -> רצועת עזה | R4: Official Report | S4: Text | T4: Murder, Torture, Forced Displacement, Sexual Violence | V4: Kamal Adwan Hospital
A5: 2387 | B5: https://www.idi.org.il/articles/57946 | C5: Poll - 57.5% of Israeli Public Support Complete Hostage Deal in Return for End of War (Jan 2025) | D5: =VLOOKUP(A5,Hebrew!A:C,3,0) -> סקר דצמבר 2024: רוב הציבור (57.5%) תומך בעסקה כוללת לשחרור כול החטופים בתמורה לסיום המלחמה | E5: A survey conducted in December 2024 by the Israeli Democracy Institute shows public support for a comprehensive deal to release all captives in exchange for ending the war, with varying opinions across political spectrums. | F5: =VLOOKUP($A5,Hebrew!$A:$S,4,0) -> סקר שערך מכון הישראלי לדמוקרטיה מצא, בין שאר הנושאים, רוב גדול התומך בעסקה כוללת לשחרור החטיפים בתמורה לסיום המלחמה. | G5: January 15, 2025 | H5: 45658 | I5: January 8, 2025 | J5: The Israel Democracy Institute | K5: Prof. Tamar Herman, Dr. Lior Yohanani, Yaron Kaplan, Inna Orly Sapojnikov | L5: =VLOOKUP($A5,Hebrew!$A:$S,9,0) -> פרופ' תמר הרמן, ד"ר ליאור יוחנני, ירון קפלן, אינה אורלי ספוז'ניקוב | N5: https://dataisrael.idi.org.il | O5: Hebrew | P5: Israel | Q5: =VLOOKUP($A5,Hebrew!$A:$S,13,0) -> ישראל | R5: Analysis | S5: Text | T5: Hostage Deal, Ceasefire, Public Opinion, Israeli Society | U5: IDF (Israel Defense Forces) | V5: Israel
A6: 2388 | B6: https://www.mekomit.co.il/%d7%9c%d7%94%d7%a8%d7%95%d7%a1-%d7%90%d7%aa-%d7%94%d7%a9%d7%9c%d7%99%d7%97-%d7%9b%d7%9a-%d7%94%d7%97%d7%a8%d7%99%d7%91%d7%94-%d7%99%d7%a9%d7%a8%d7%90%d7%9c-%d7%90%d7%aa-%d7%9e%d7%aa%d7%a7%d7%a0%d7%99/ | C6: Israel's destruction of journalistic infrastructure in Gaza | D6: =VLOOKUP(A6,Hebrew!A:C,3,0) -> להרוס את השליח: כך החריבה ישראל את מתקני העיתונות בעזה | E6: Israel's destruction of media facilities in Gaza, as investigated by Forbidden Stories, highlights the challenges faced by journalists in reporting from the region. | F6: =VLOOKUP($A6,Hebrew!$A:$S,4,0) -> תחקיר של פורבידן סטוריז ושיחה מקומית בעקבות הפגיעה בעיתונאים ובמשרדיהם. | G6: June 26, 2024 | H6: October 7, 2023 | I6: June 25, 2024 | J6: Mekomit | K6: Léa Peruchon | L6: =VLOOKUP($A6,Hebrew!$A:$S,9,0) -> לאה פרושון | O6: Hebrew | P6: Gaza City | Q6: =VLOOKUP($A6,Hebrew!$A:$S,13,0) -> עיר עזה | R6: Journalistic report | S6: Text | T6: Media, Civilians, Air Strike, Rules of Engagement, Journalists, War Crimes | V6: Gaza City
A7: 2389 | B7: https://www.haaretz.co.il/news/magazine/2024-06-25/ty-article-magazine/.premium/00000190-4ac5-da42-a1ba-7fef27c50000 | C7: IDF reserve soldiers refusing to serve further tell their stories | D7: =VLOOKUP(A7,Hebrew!A:C,3,0) -> שלושה חיילי מילואים מספרים מדוע יסרבו לשרת בעזה גם אם ישלמו על כך | E7: Three reserve soldiers explain why they will refuse to serve in Gaza, even if they will face consequences. | F7: =VLOOKUP($A7,Hebrew!$A:$S,4,0) -> שלושה חיילי מילואים מסבירים מדוע חתמו על מכתב סירוב לשרת בעזה | G7: June 25, 2024 | H7: May 31, 2024 | J7: Haaretz | K7: Liza Rozovsky | L7: =VLOOKUP($A7,Hebrew!$A:$S,9,0) -> ליזה רוזובסקי | O7: Hebrew | P7: Gaza Strip | Q7: =VLOOKUP($A7,Hebrew!$A:$S,13,0) -> רצועת עזה | R7: Journalistic report | S7: Text | T7: War Crimes, Rules of Engagement, Ground Operation, Hostage Deal | U7: IDF (Israel Defense Forces) | V7: Gaza Strip
A8: 2390 | B8: https://zeteo.com/p/the-myth-of-human-shields-israel-gaza | C8: The Myth of Gaza's civilian population serving as human shields for Hamas | D8: =VLOOKUP(A8,Hebrew!A:C,3,0) -> המיתוס של 'מגינים אנושיים' | E8: The article debunks the 'human shields' claim used by Israel in Gaza conflicts, highlighting the impact on civilians and the misuse of the term by the Israeli military. | F8: =VLOOKUP($A8,Hebrew!$A:$S,4,0) -> המאמר חושף את השימוש לראה בטיעון 'מגינים אנושיים' בו משתמש הצבא הישראלי ברצועת עזה, וחושף את השפעתו על האוכלוסייה האזרחית | G8: September 30, 2024 | J8: Zeteo | K8: Muhammad Shehada | L8: =VLOOKUP($A8,Hebrew!$A:$S,9,0) -> מוחמד שחאדה | O8: English | P8: Gaza Strip | Q8: =VLOOKUP($A8,Hebrew!$A:$S,13,0) -> רצועת עזה | R8: Opinion | S8: Text | T8: Civilians, Rules of Engagement, Air Strike, Collective Punishment | V8: Gaza Strip
A9: 2391 | B9: https://www.gazahealthcareletters.org/usa-letter-oct-2-2024 | C9: Letter to US President Biden and Vice President Harris from 99 American physicians who volunteered in Gaza | D9: =VLOOKUP(A9,Hebrew!A:C,3,0) -> מכתב 99 רופאים שהתנדבו לשרת בעזה לנשיא ארה"ב ביידן ולסגניתו האריס | E9: American medical professionals who served in Gaza write an open letter to President Biden and Vice President Harris, urging for immediate action to prevent further catastrophe in Gaza and Israel. | F9: =VLOOKUP($A9,Hebrew!$A:$S,4,0) -> במכתב פתוח לנשיא ארה"ב ביידן ולסגניתו האריס פונים אנשי צוותי רפואה אמריקנים לפעול בדחיות למנוע המשך הקטקסטרופה בעזה ובישראל. | G9: October 2, 2024 | H9: October 7, 2023 | I9: 45566 | J9: Gaza Healthcare Letters | K9: American Medical Professionals who Served in Gaza | L9: =VLOOKUP($A9,Hebrew!$A:$S,9,0) -> צוותי רפואה אמריקנים שפעלו בעזה | O9: English | P9: Gaza Strip | Q9: =VLOOKUP($A9,Hebrew!$A:$S,13,0) -> רצועת עזה | R9: Open letter | S9: Text | T9: Civilians, Hospital, Public Health, Torture | U9: United States | V9: Gaza Strip | W9: Joe Biden, Kamala Harris
A10: 2392 | B10: https://www.haaretz.co.il/news/politics/2024-10-30/ty-article-magazine/.premium/00000192-de9d-d7b5-af97-ff9d2d0d0000 | C10: 100 dead in IDF attempt to kill a spotter | D10: =VLOOKUP(A10,Hebrew!A:C,3,0) -> איך אפשר להפציץ בניין על כל יושביו?: בבית לאהיא מחפשים ניצולים במבנה שקרס | E10: Residents and rescue workers search for survivors in a collapsed five-story building in Beit Lahia, northern Gaza Strip, following an explosion that occurred the previous morning. | F10: =VLOOKUP($A10,Hebrew!$A:$S,4,0) -> לפי הרשויות בעזה, כמאה בני אדם נהרגו ועוד עשרות נעדרים בתקיפת מבנה מגורים בן חמש קומות בבית לאהיא שאיכלס כ-200 איש. בצה"ל אומרים כי תצפיתן שהה על גג המבנה. אנשי שירותי ההצלה, המשיכו לנסות ולאתר ניצולים. | G10: October 30, 2024 | H10: October 29, 2024 | I10: October 29, 2024 | J10: Haaretz | K10: Jack Khoury | L10: =VLOOKUP($A10,Hebrew!$A:$S,9,0) -> ג'קי חורי | O10: Hebrew | P10: Beit Lahia | Q10: =VLOOKUP($A10,Hebrew!$A:$S,13,0) -> בית לאהיא | R10: Journalistic report | S10: Text | T10: Air Strike, Civilians | V10: Beit Lahiya
A11: 2393 | B11: https://www.theguardian.com/world/article/2024/jul/19/israel-gaza-war-polio-sewage-samples | C11: Polio virus found in Gaza sewage | D11: =VLOOKUP(A11,Hebrew!A:C,3,0) -> וירוס פוליו מדבק התגלה בדגימות ביוב בעזה | E11: Highly infectious poliovirus found in Gaza sewage samples, putting thousands at risk of contracting the disease due to poor sanitation and infrastructure conditions. | F11: =VLOOKUP($A11,Hebrew!$A:$S,4,0) -> וירוס פוליו מדבק התגלה בדגימות ביוב בעזה ומעמיד בסכנה אלפי תושבים בגלל תנאי היגיינה ותשתיות פגועים. | G11: July 19, 2024 | J11: The Guardian | K11: Agence France-Presse | L11: =VLOOKUP($A11,Hebrew!$A:$S,9,0) -> סוכנות הידיעות הצרפתית | O11: English | P11: Gaza Strip | Q11: =VLOOKUP($A11,Hebrew!$A:$S,13,0) -> רצועת עזה | R11: Journalistic report | S11: Text | T11: Water, Public Health | V11: Central Gaza Strip
A12: 2394 | B12: https://www.thenationalnews.com/news/mena/2024/06/21/israel-gaza-city-municipality-garage/ | C12: Israel killed water/environment engineer & municipality officials working to restore water supply in Gaza | D12: =VLOOKUP(A12,Hebrew!A:C,3,0) -> בתקיפה אווירית נהרגו מהנדסי מים ותשתיות נציגי העירייה שפעלו להחזיר לפעולה את אספקת המים | E12: An Israeli airstrike on a Gaza City municipal building kills at least five workers, including four preparing to restore drinking water wells, leading to significant destruction and impacting essential services in the war-torn enclave. | F12: =VLOOKUP($A12,Hebrew!$A:$S,4,0) -> בתקיפה אווירית ישראלית על בנין העירייה של עזה נהרגו לפחות ארבעה שעבדו על חידוש אספקת מים לבארות המים ובכך פגעו אנושות באספקת משאב חיוני בעזה הנצורה. | G12: June 21, 2024 | H12: June 21, 2024 | I12: June 21, 2024 | J12: The National | K12: Nagham Mohanna | L12: =VLOOKUP($A12,Hebrew!$A:$S,9,0) -> נאגהם מוחאנה | O12: English | P12: Gaza City | Q12: =VLOOKUP($A12,Hebrew!$A:$S,13,0) -> עיר עזה | R12: Journalistic report | S12: Text | T12: Air Strike, Civilians, Water | V12: Gaza City
A13: 2395 | B13: https://www.globaltimes.cn/page/202411/1322528.shtml | C13: Gazans boycott local markets due to exhorbitant food prices | D13: =VLOOKUP(A13,Hebrew!A:C,3,0) -> עזתים מחרימים שווקים מקומיים בשל הפקעת מחירים | E13: Markets in Gaza are empty as locals boycott due to soaring prices amid the conflict with Israel, leading to protests and accusations of price manipulation by traders. | F13: =VLOOKUP($A13,Hebrew!$A:$S,4,0) -> שווקים בעזה התרוקנו בשל חרם של העזתים במחאה על האשמת הסוחרים מחירים המופקעים | G13: November 6, 2024 | H13: November 5, 2024 | J13: Global Times | K13: Xinhua | L13: =VLOOKUP($A13,Hebrew!$A:$S,9,0) -> סוכנות הידיעות הסינית | O13: English | P13: Central Gaza; Southern Gaza | Q13: =VLOOKUP($A13,Hebrew!$A:$S,13,0) -> מרכז ודרום רצועת עזה | R13: Journalistic report | S13: Text | T13: Food, Humanitarian Aid | V13: Gaza Strip
A14: 2396 | B14: https://amp.cnn.com/cnn/2024/11/29/middleeast/gaza-bakery-crush-palestinians-killed-intl-latam | C14: 3 Palestinians crushed to death in line to get food | D14: =VLOOKUP(A14,Hebrew!A:C,3,0) -> בתור לאוכל נמחצו למוות אישה ושני ילדים פלסטינים | E14: Three Palestinians, including two children and a woman, were crushed to death outside a bakery in Gaza amid a worsening food crisis in the enclave. | F14: =VLOOKUP($A14,Hebrew!$A:$S,4,0) -> על רקע מצוקת המזון הגוברת ברצונת עזה נמחצו למוות אישה ושני ילדים פלסטינים בתור למאפיה. | G14: November 30 ,2024 | H14: November 29, 2024 | I14: November 29, 2024 | J14: CNN | K14: Abeer Salman; Mohammad Al Sawalhi; Ibrahim Dahman; Mitchell McCluskey | L14: =VLOOKUP($A14,Hebrew!$A:$S,9,0) -> אביר סלמאן, מוחמד אל-סוואלי, איברהים דמאן, מישל מק'לאסקי | O14: English | P14: Central Gaza | Q14: =VLOOKUP($A14,Hebrew!$A:$S,13,0) -> מרכז רצועת עזה | R14: Journalistic report | S14: Text | T14: Humanitarian Aid, Food, Civilians | V14: Central Gaza Strip
A15: 2397 | B15: https://thebaffler.com/latest/running-amok-turfah | C15: Dehumanizing social media posts by Israeli soldiers in Gaza | D15: =VLOOKUP(A15,Hebrew!A:C,3,0) -> דהומנציזציה של הפלסטינים מוצגת על ידי חיילים ישראלים בסרטונים במדיה החברתית | E15: The content discusses various disturbing behaviors exhibited by Israeli soldiers in Gaza, including destruction, looting, and disrespectful actions towards Palestinians. | F15: =VLOOKUP($A15,Hebrew!$A:$S,4,0) -> בסרטונים תכנים מטרידים של חיילי ישראל, כולל תיאורי הרס, ביזה והתנהגות לא מכובדת כלפי פלסטינים | G15: June 18, 2024 | J15: The Baffler | K15: Mary Turfah | L15: =VLOOKUP($A15,Hebrew!$A:$S,9,0) -> מרי טורפה | O15: English | P15: Gaza Strip | Q15: =VLOOKUP($A15,Hebrew!$A:$S,13,0) -> רצועת עזה | R15: Journalistic report | S15: Text | T15: Vandalism | U15: IDF (Israel Defense Forces) | V15: Gaza Strip
A16: 2398 | B16: https://www.haaretz.com/israel-news/2024-09-03/ty-article/.premium/israeli-army-reservists-assault-gazan-truck-drivers-working-for-aid-organizations/00000191-b71d-d13c-a39b-bf9d24710000 | C16: Israeli army reservist assault Gazan truck drivers working for aid organizations | D16: =VLOOKUP(A16,Hebrew!A:C,3,0) -> חיילי מילואים תוקפים נהגי משאיות עזתים העובדים עבור ארגוני סיוע | E16: Israeli army reservists assaulted Gazan truck drivers working for aid organizations, despite being cleared by Israel's security services. | F16: =VLOOKUP($A16,Hebrew!$A:$S,4,0) -> חיילי מילואים תוקפים נהגי משאיות עזתים העובדים עבור ארגוני סיוע למרות שיש להם אישור מכוחות הביטחון | G16: September 3, 2024 | H16: 45505 | J16: Haaretz | K16: Yaniv Kubovich | L16: =VLOOKUP($A16,Hebrew!$A:$S,9,0) -> יניב קובוביץ | O16: English | P16: Kerem Shalom Crossing | Q16: =VLOOKUP($A16,Hebrew!$A:$S,13,0) -> מעבר כרם שלום | R16: Journalistic report | S16: Text | T16: Humanitarian Aid, Civilians | U16: IDF (Israel Defense Forces) | V16: Kerem Shalom Crossing
A17: 2399 | B17: https://www.themarker.com/news/education/2024-09-30/ty-article/00000192-41e6-d07b-aff3-57e6401a0000 | C17: Israeli Ministry of Education Directorate of Religious Education calls for schools to celebrate killing of Hezbollah leader Hassan Nasrallah | D17: =VLOOKUP(A17,Hebrew!A:C,3,0) -> משרד החינוך קרא לבתי הספר לערוך הרקדות ומשלוחי מנות לתלמידים עקב חיסול נסראללה | E17: The Ministry of Education instructed religious state schools to hold dances and send food packages to students following the killing of Hezbollah leader Hassan Nasrallah, sparking debates within the religious community. | F17: =VLOOKUP($A17,Hebrew!$A:$S,4,0) -> מינהל החינוך הדתי במשרד החינוך, האחראי על הפיקוח על רבני בתי הספר הממלכתיים־דתיים, הנחה בתי ספר לערוך חגיגות לציון הרג מנהיג חיזבאללה. היו גורמים במשרד שמתחו ביקורת על המהלך | G17: September 30, 2024 | H17: September 29, 2024 | I17: September 29, 2024 | J17: The Marker | K17: Lior Dattel | L17: =VLOOKUP($A17,Hebrew!$A:$S,9,0) -> ליאור דטל | O17: Hebrew | P17: Israel | Q17: =VLOOKUP($A17,Hebrew!$A:$S,13,0) -> ישראל | R17: Journalistic report | S17: Text | T17: Israeli Society | V17: Israel | W17: Hassan Nasrallah
A18: 2400 | B18: https://www.haaretz.co.il/news/law/2024-09-23/ty-article/.premium/00000192-1b6b-d342-ab9f-df6b2b790000 | C18: Deputy Mayor of Jerusalem interrogated under suspicion of inciting to violence and terrorism | D18: =VLOOKUP(A18,Hebrew!A:C,3,0) -> סגן ראש העיר ירושלים נחקר בחשד להסתה לטרור לאחר שפרסם פוסטים נגד אונר"א | E18: Jerusalem's Deputy Mayor, Aryeh King, is under investigation for incitement to violence and terrorism after posting against the UN - Law and Crime | F18: =VLOOKUP($A18,Hebrew!$A:$S,4,0) -> סגן ראש העיר ירושלים נחקר בחשד להסתה לאלימות והסתה לטרור לאחר שפרסם פוסטים נגד אונר"א ועידוד לשריפת מבני אונר"א | G18: September 23, 2024 | H18: September 23, 2024 | J18: Haaretz | K18: Yael Freidson | L18: =VLOOKUP($A18,Hebrew!$A:$S,9,0) -> יעל פרידסון | O18: Hebrew | P18: Israel | Q18: =VLOOKUP($A18,Hebrew!$A:$S,13,0) -> ישראל | R18: Journalistic report | S18: Text | T18: Terrorism | U18: Israeli Police, UNRWA (The UN Relief and Works Agency for Palestine Refugees) | V18: Jerusalem
A19: 2401 | B19: https://www.nytimes.com/2024/10/14/world/middleeast/israel-gaza-military-human-shields.html | C19: Israeli Army uses Palestinian civilians as human shields in Gaza | D19: =VLOOKUP(A19,Hebrew!A:C,3,0) -> צה"ל משתמש באזרחים פלסטינים כמגינים חיים בעזה. | E19: Israeli soldiers have been accused of using Palestinians as human shields in Gaza, forcing them to carry out dangerous tasks, as reported by The New York Times. | F19: =VLOOKUP($A19,Hebrew!$A:$S,4,0) -> חיילי צה"ל לפי דיווח בניו יורק טיימס מאלצים אזרחים פלסטינים לשמש כמגינים חיים ולבצע משימות מסכנות חיים. | G19: October 14, 2024 | J19: The New York Times | K19: Natan Odenheimer; Bilal Shbair; Patrick Kingsley | L19: =VLOOKUP($A19,Hebrew!$A:$S,9,0) -> נתן אודנהיימר, בילאל שבאר, פטריק קינגסלי | O19: English | P19: Gaza Strip | Q19: =VLOOKUP($A19,Hebrew!$A:$S,13,0) -> רצועת עזה | R19: Journalistic report | S19: Text | T19: Ground Operation, Civilians | U19: IDF (Israel Defense Forces) | V19: Gaza Strip
A20: 2402 | B20: https://www.haaretz.co.il/news/magazine/2024-06-28/ty-article-magazine/.premium/00000190-5aa7-de5e-abd0-fbf704260000 | C20: A night with an IDF ghost unit that has been fighting in the Gaza Strip for eight months | D20: =VLOOKUP(A20,Hebrew!A:C,3,0) -> לילה עם יחידת רפאים של צה"ל, שנלחמת ברצועה כבר שמונה חודשים | E20: An article about a night with the IDF's Re'phaim unit, which has been fighting in the Gaza Strip for eight months. | F20: =VLOOKUP($A20,Hebrew!$A:$S,4,0) -> לילה עם יחידת רפאים של צה"ל, שמכונה גם היחידה הרב-ממדית, שתפקידה לאתר ולפגוע במחבלים בעומק שטח הלחימה באמצעות יכולות טכנולוגיות מתקדמות | G20: June 28,2024 | H20: June 21, 2024 | J20: Haaretz | K20: Yaniv Kubovich | L20: =VLOOKUP($A20,Hebrew!$A:$S,9,0) -> יניב קובוביץ | O20: Hebrew | P20: Gaza Strip | Q20: =VLOOKUP($A20,Hebrew!$A:$S,13,0) -> רצועת עזה | R20: Journalistic report | S20: Text | T20: Hostages | U20: IDF (Israel Defense Forces) | V20: Gaza Strip
A21: 2403 | B21: https://www.haaretz.co.il/news/politics/2024-10-16/ty-article/.premium/00000192-94aa-d9c2-a7f3-9cae337a0000 | C21: An invitation from Likud for an event in the Gaza border area was distributed under the title 'Preparing to settle in the Gaza region | D21: =VLOOKUP(A21,Hebrew!A:C,3,0) -> הזמנה מטעם הליכוד לאירוע בעוטף הופצה תחת הכותרת "נערכים להתיישב בחבל עזה" | E21: The Likud party has issued an invitation for an event in the Gaza envelope titled 'Preparing to settle in the Gaza Strip' with the participation of several Likud Knesset members. | F21: =VLOOKUP($A21,Hebrew!$A:$S,4,0) -> לפי ההזמנה, הליכוד יקים סוכה כחלק מ"עיר סוכות" בעוטף עזה של תנועת "נחלה", שפועלת להקמת מאחזים בלתי חוקיים בגדה. בהזמנה נכתב כי ח"כים מהליכוד צפויים להגיע | G21: October 16,2024 | J21: Haaretz | K21: Noa Spigel | L21: =VLOOKUP($A21,Hebrew!$A:$S,9,0) -> נועה שפיגל | O21: Hebrew | P21: Western Negev (Otef) | Q21: =VLOOKUP($A21,Hebrew!$A:$S,13,0) -> עוטף עזה | R21: Journalistic report | S21: Text | T21: Israeli Society, Settlements | V21: Western Negev (Otef) | W21: Benny Gantz, Benjamin Netanyahu
A22: 2404 | B22: https://www.mekomit.co.il/ps/141796/ | C22: The children of Gaza have started the school year amid destruction, loss, and uncertainty | D22: =VLOOKUP(A22,Hebrew!A:C,3,0) -> ילדי עזה החלו את שנת הלימודים בתוך חורבן, אובדן ואי ודאות | E22: Children in Gaza begin the school year amidst destruction and uncertainty, facing challenges in accessing education due to ongoing attacks and war aftermath. | F22: =VLOOKUP($A22,Hebrew!$A:$S,4,0) -> מורים ואנשי חינוך בעזה החרבה מנסים לספק לילדים תוכניות חינוכיות בכיתות, באוהלים או במבנים הרוסים, אך ספק אם התוכניות האלה ישרדו תחת ההתקפות המתמשכות והחורף המתקרב | G22: October 31, 2024 | J22: Mekomit | K22: Rawida Kamal Amar;Ivtisam Mahdi | L22: =VLOOKUP($A22,Hebrew!$A:$S,9,0) -> רווידה כמאל עמאר ואיבתיסאם מהדי | N22: https://www.ochaopt.org/content/reported-impact-snapshot-gaza-strip-29-october-2024 | O22: Hebrew | P22: Gaza Strip | Q22: =VLOOKUP($A22,Hebrew!$A:$S,13,0) -> רצועת עזה | R22: Journalistic report | S22: Text | T22: Scholasticide | V22: Gaza Strip
A23: 2405 | B23: https://www.kan.org.il/content/kan-news/defense/827036/ | C23: With the help of soldiers: This is how the right-wing activist managed to enter Netzarim | D23: =VLOOKUP(A23,Hebrew!A:C,3,0) -> תחקיר זמן אמת: בסיוע חיילים הצליחה פעילת הימין להיכנס לנצרים | E23: Israeli Right-wing settler activist Daniella Weiss enlisted the help of military forces stationed in and around the Gaza Strip to enter the territory despite it being declared a closed military zone. Weiss did so in preparation for establishing Jewish settlements in the Gaza Strip. | F23: =VLOOKUP($A23,Hebrew!$A:$S,4,0) -> רכב צבאי הסיע את דניאלה וייס, ממייסדות תנועת ההתיישבות, לתוך שטח צבאי סגור ברצועת עזה. שלטונות הצבא היו מודעים לכך. | G23: November 21, 2024 | H23: November 13, 2024 | J23: Kan 11 | K23: Avi Amit | L23: =VLOOKUP($A23,Hebrew!$A:$S,9,0) -> אבי עמית | O23: Hebrew | P23: Gaza Strip | Q23: =VLOOKUP($A23,Hebrew!$A:$S,13,0) -> רצועת עזה | R23: Journalistic report | S23: Text | T23: Religious Right, Settlements | U23: IDF (Israel Defense Forces) | V23: Gaza Strip
A24: 2406 | B24: https://www.haaretz.co.il/news/politics/2025-01-18/ty-article/00000194-784f-d739-a9b6-78ff31ab0000 | C24: Israel has committed to allowing reconstruction work in the Gaza Strip at the beginning of the first phase of the deal | D24: =VLOOKUP(A24,Hebrew!A:C,3,0) -> ישראל התחייבה לאפשר קיום עבודות לשיקום הרצועה בתחילת השלב הראשון של העסקה | E24: Israel committed to allowing infrastructure rehabilitation works in the Gaza Strip at the beginning of the first stage of the agreement, amidst the release of captives and ceasefire negotiations. | F24: =VLOOKUP($A24,Hebrew!$A:$S,4,0) -> במסגרת ההסכם יוקמו ערי קראוונים לתושבי הרצועה במימון בינלאומי. לאחר שהממשלה אישרה הלילה את העסקה, הודיע דובר משרד החוץ הקטארי כי הפסקת האש תיכנס לתוקף מחר ב-8:30. חמאס מחויב לשלוח לישראל היום את שמות שלוש החטופות הראשונות שישוחררו | G24: January 18, 2025 | J24: Haaretz | K24: Yaniv Kubovich, Yehonatan Lis | L24: =VLOOKUP($A24,Hebrew!$A:$S,9,0) -> יניב קובוביץ ויהונתן ליס | O24: Hebrew | P24: North Gaza Strip | Q24: =VLOOKUP($A24,Hebrew!$A:$S,13,0) -> צפון רצועת עזה | R24: Journalistic report | S24: Text | T24: Hostage Deal, Reconstruction, Ceasefire | U24: Qatar | V24: North Gaza
A25: 2407 | B25: https://www.nytimes.com/2024/11/19/world/middleeast/israel-5-million-dollars-hostage.html | C25: Netanyahu Offers $5 Million for Each Hostage Freed in Gaza | D25: =VLOOKUP(A25,Hebrew!A:C,3,0) -> נתניהו מציע 5 מיליון דולר עבור כל חטוף שישוחרר | E25: Israeli Prime Minister Netanyahu offers $5 million for each hostage freed in Gaza as part of efforts to secure their release amidst stalled cease-fire talks. | F25: =VLOOKUP($A25,Hebrew!$A:$S,4,0) -> נתניהו מציע פרס כספי עבור שחרור חטופים תוך שהוא דוחה הצעה להפסקת אש ומאיים להעניש מי שיפגע בחטופים. | G25: November 19, 2024 | J25: The New York Times | K25: Efrat Livni | L25: =VLOOKUP($A25,Hebrew!$A:$S,9,0) -> אפרת ליבני | O25: English | Q25: =VLOOKUP($A25,Hebrew!$A:$S,13,0) -> 0 | R25: Journalistic report | S25: Text | T25: Hostage Deal, Hostages | W25: Benjamin Netanyahu, Yoav Gallant
A26: 2408 | B26: https://www.ha-makom.co.il/idf-droppings/ | C26: Silent and suppressed refusal: Active-duty soldiers are no longer willing to keep fighting | D26: =VLOOKUP(A26,Hebrew!A:C,3,0) -> סרבנות שקטה ומושתקת: לוחמים בסדיר לא מוכנים יותר להמשיך להילחם | E26: Israeli soldiers in the Nahal Brigade express reluctance to continue fighting in Gaza due to mental and emotional strain, leading to a phenomenon of quiet refusal to engage in combat. | F26: =VLOOKUP($A26,Hebrew!$A:$S,4,0) -> מנח״ל ועד חטיבת הקומנדו, מגבעתי ועד הצנחנים - יותר ויותר לוחמים, מכלל יחידות החי״ר, מעידים שהשחיקה והאטימות של צה"ל לא הותירה להם ברירה אלא לסרב | G26: October 15, 2024 | J26: Ha-Makom | K26: Revital Hovel | L26: =VLOOKUP($A26,Hebrew!$A:$S,9,0) -> רביטל חובל | O26: Hebrew | Q26: =VLOOKUP($A26,Hebrew!$A:$S,13,0) -> 0 | R26: Journalistic report | S26: Text | T26: Israeli Society | U26: IDF (Israel Defense Forces)
A27: 2409 | B27: https://www.haaretz.co.il/news/politics/2024-08-02/ty-article/.premium/00000191-1442-db7e-a99d-1edabb590000 | C27: Senior negotiator: Security officials believe that Netanyahu is not interested in advancing a deal | D27: =VLOOKUP(A27,Hebrew!A:C,3,0) -> בכיר בצוות המו"מ: ראשי מערכת הביטחון מעריכים שנתניהו לא מעוניין לקדם עסקה | E27: Senior member of the negotiation team states that security system heads believe Netanyahu is not interested in advancing a deal. | F27: =VLOOKUP($A27,Hebrew!$A:$S,4,0) -> ידיעות על משבר ביחסים בין נתניהו למערכת הביטחון. במערכת הביטחון, וכן בארה"ב בקטאר ובמצרים, מעריכים כבר חודשים ארוכים כי נתניהו אינו מעוניין בעסקה. זאת, בין היתר כדי לשמור על שרידות הממשלה שלו. | G27: August 02, 2024 | J27: Haaretz | K27: Michael Houzertov, Yehonatan Lis, Bar Peleg | L27: =VLOOKUP($A27,Hebrew!$A:$S,9,0) -> מיכאל האוזר טוב, יהונתן ליס ובר פלג | O27: Hebrew | P27: Gaza Strip | Q27: =VLOOKUP($A27,Hebrew!$A:$S,13,0) -> רצועת עזה | R27: Journalistic report | S27: Text | T27: Hostage Deal | U27: Shin Bet | V27: Netzarim Corridor, Philadelphi Corridor | W27: Ronen Bar, Benjamin Netanyahu
A28: 2410 | B28: https://www.haaretz.co.il/news/politics/2025-01-19/ty-article/.premium/00000194-7d23-de1b-a9bd-7d67f9790000 | C28: The IDF and Shin Bet retrieved from the Gaza Strip the body of soldier Oron Shaul, who was killed in Operation Protective Edge in 2014 | D28: =VLOOKUP(A28,Hebrew!A:C,3,0) -> צה"ל ושב"כ חילצו מרצועת עזה את גופתו של החייל אורון שאול שנהרג במבצע צוק איתן ב-2014 | E28: IDF and Shin Bet extracted the body of soldier Oron Shaul, who was killed in Operation Protective Edge in 2014, from the Gaza Strip. | F28: =VLOOKUP($A28,Hebrew!$A:$S,4,0) -> גופתו של שאול נחטפה למנהרה בשג'אעייה לאחר שטיל RPG נורה על הנגמ"ש שבו היה עם חבריו. כוחות מיוחדים, בהם לוחמי שייטת 13, השתתפו בהשבתו לישראל. צה"ל: מחויבים להשיב גם את הדר גולדין ושאר החטופים | G28: January 19, 2025 | J28: Haaretz | K28: Michael Houzertov, Adi Hashmonai, Bar Peleg | L28: =VLOOKUP($A28,Hebrew!$A:$S,9,0) -> יניב קובוביץ, עדי חשמונאי ובר פלג | O28: Hebrew | Q28: =VLOOKUP($A28,Hebrew!$A:$S,13,0) -> 0 | R28: Journalistic report | S28: Text | T28: Hostages | U28: IDF (Israel Defense Forces)
A29: 2411 | B29: https://www.haaretz.co.il/gallery/media/2024-08-19/ty-article/.premium/00000191-69da-d12a-a3b5-7dff33f80000 | C29: The Srugim website published an article supporting Jewish terrorism against Palestinians | D29: =VLOOKUP(A29,Hebrew!A:C,3,0) -> אתר "סרוגים" פירסם מאמר שתומך בטרור יהודי נגד פלסטינים | E29: The news website Srugim published an article expressing support for Jewish terrorism against Palestinians. | F29: =VLOOKUP($A29,Hebrew!$A:$S,4,0) -> בתגובה למהומות המתנחלים בג'ית שבהן נורה פלסטיני למוות, פרסם סמנכ"ל "חוננו" לשעבר, אורי קירשנבום, באתר החדשות הדתי־לאומי "סרוגים", טור תחת הכותרת "דין ג'ית כדין רפיח": "שמישהו יסביר לי למה מה שנכון בעזה לא נכון בג'נין, בחברון ובשכם" | G29: August 19 2024 | J29: Haaretz | K29: Ido David Cohen | L29: =VLOOKUP($A29,Hebrew!$A:$S,9,0) -> עדו דוד כהן | O29: Hebrew | P29: West Bank | Q29: =VLOOKUP($A29,Hebrew!$A:$S,13,0) -> הגדה המערבית | R29: Journalistic report | S29: Text | T29: Religious Right | V29: West Bank, Zaytun Neighborhood
A30: 2412 | B30: https://www.haaretz.co.il/magazine/2024-10-10/ty-article-magazine/.highlight/00000192-70ab-d292-a392-78bfa8210000?utm_source=App_Share&utm_medium=Android_Native&utm_campaign=Share | C30: Netanyahu's government is not just allowing Jewish terrorism in the West Bank—it is funding it. Investigation | D30: =VLOOKUP(A30,Hebrew!A:C,3,0) -> ממשלת נתניהו לא סתם מאפשרת את הטרור היהודי בגדה. היא מממנת אותו. תחקיר | E30: An investigation into the funding of Jewish terrorism in the West Bank by the Netanyahu government. | F30: =VLOOKUP($A30,Hebrew!$A:$S,4,0) -> המתנחלים מדברים על זה במונחים של מהפכה: במקום התנחלויות מגודרות על הגבעות, הוקמו בתוך שבע שנים יותר מ–60 חוות שהשתלטו על מאות אלפי דונם בגדה. הפרויקט הנוסק הזה, שמתבסס על כוח עבודה של בני נוער שנפלטו ממסגרות, הפך למחולל המרכזי של אלימות נגד פלסטינים. והוא ממומן בעשרות מיליונים בידי המדינה | G30: October 10, 2024 | J30: Haaretz | K30: Hilo Glazer, Hafar Sheizaf | L30: =VLOOKUP($A30,Hebrew!$A:$S,9,0) -> הילו גלזר, הגר שיזף | O30: Hebrew | P30: West Bank | Q30: =VLOOKUP($A30,Hebrew!$A:$S,13,0) -> הגדה המערבית | R30: Journalistic report | S30: Text | T30: Religious Right, Settlements | U30: Israeli Government | V30: West Bank
A31: 2413 | B31: https://www.ynet.co.il/news/article/bkldluke1e#autoplay | C31: During a visit to the Civil Administration, Smotrich said he is working to shut it down: 'I spoke with Netanyahu' | D31: =VLOOKUP(A31,Hebrew!A:C,3,0) -> בביקור במנהל האזרחי אמר סמוטריץ' כי הוא פועל לסגור אותו: "דיברתי עם נתניהו | E31: Bezalel Smotrich, Minister of Treasury and Minister of Security, is working towards closing the Israeli Civil Administration in the West Bank, as part of a move to annex the territory to Israel de-facto. | F31: =VLOOKUP($A31,Hebrew!$A:$S,4,0) -> שר האוצר רוצה לנצל את מומנטום כניסת ממשל טראמפ, ולקדם את סיפוח יהודה ושומרון והחלת ריבונות על השטח. הכתבה מרחיבה על המשמעויות הדרמטיות של צעד כזה | G31: December 5, 2024 | J31: Ynet | K31: Elisha Ben-kimon | L31: =VLOOKUP($A31,Hebrew!$A:$S,9,0) -> אלישע בן קימון | O31: Hebrew | P31: West Bank | Q31: =VLOOKUP($A31,Hebrew!$A:$S,13,0) -> הגדה המערבית | R31: Journalistic report | S31: Text | T31: Religious Right, Annexation | U31: Israeli Government | V31: West Bank | W31: Bezalel Smotritch
A32: 2414 | B32: https://www.haaretz.co.il/news/politics/2025-01-09/ty-article/.premium/00000194-45b1-db19-abdd-6db7c86d0000 | C32: Ben Gvir demands that the police prioritize the demolition of illegal buildings that house families | D32: =VLOOKUP(A32,Hebrew!A:C,3,0) -> בן גביר דורש מהמשטרה לתעדף הריסת מבנים לא חוקיים שמאכלסים משפחות | E32: Minister Itamar Ben Gvir intervenes in the police enforcement policy regarding the demolition of illegal buildings housing families. | F32: =VLOOKUP($A32,Hebrew!$A:$S,4,0) -> השר לביטחון לאומי איתמר בן גביר התערב במדיניות האכיפה של המשטרה בהריסת מבנים לא חוקיים, והורה לבכירים בארגון לתעדף הריסת בתים המאוכלסים על ידי משפחות על אף שאין לו הסמכות לקבוע את מדיניות ההריסה | G32: January 9, 2025 | J32: Haaretz | K32: Josh Breiner | L32: =VLOOKUP($A32,Hebrew!$A:$S,9,0) -> יהושע (ג'וש) בריינר | O32: Hebrew | P32: Negev | Q32: =VLOOKUP($A32,Hebrew!$A:$S,13,0) -> נגב | R32: Journalistic report | S32: Text | T32: Religious Right | U32: Israeli Police | V32: Negev | W32: Itamar Ben-Gvir
A33: 2415 | B33: https://www.haaretz.co.il/news/politics/2024-10-30/ty-article/.premium/00000192-d9c2-d605-a3b2-dfc702430000 | C33: In the Shuafat refugee camp, residents do not believe that the authorities will take over UNRWA's role | D33: =VLOOKUP(A33,Hebrew!A:C,3,0) -> במחנה הפליטים שועפט לא מאמינים שהרשויות ייכנסו לנעלי אונר"א | E33: The article discusses the living conditions in the Shuafat refugee camp, managed by the UN agency UNRWA, and the potential legal implications of a recent law passed in the Knesset. | F33: =VLOOKUP($A33,Hebrew!$A:$S,4,0) -> כמו בהחלטות רבות שנוגעות לירושלים מאז 1967, גם החוק לסילוק אונר"א לא הגיע על רקע רצון לפתור בעיה כלשהי, להקל על תושבי ירושלים או לקדם עתיד טוב יותר. גם אם יש בעיות בסוכנות, לא מדובר בארגון טרור, אלא בארגון שמספק שירותים חיוניים למאות אלפי בני אדם | G33: October 30, 2024 | J33: Haaretz | K33: Nir Hasson | L33: =VLOOKUP($A33,Hebrew!$A:$S,9,0) -> ניר חסון | O33: Hebrew | P33: East Jerusalem | Q33: =VLOOKUP($A33,Hebrew!$A:$S,13,0) -> מזרח ירושלים | R33: Opinion | S33: Text | U33: UN (United Nations) | V33: Jerusalem
A34: 2416 | B34: https://www.haaretz.co.il/news/politi/2024-11-13/ty-article/.premium/00000193-24ee-d76b-afd7-a7ff70930000 | C34: Approved in a preliminary vote: The police will be able to access a computer or personal phone without the owner's knowledge | D34: =VLOOKUP(A34,Hebrew!A:C,3,0) -> אושר בטרומית: המשטרה תוכל לחדור למחשב או לטלפון אישי בלא ידיעת בעליו | E34: The Knesset approved a controversial bill allowing police officers to access personal computers or phones without the owner's knowledge, sparking opposition concerns about the legality of the process. | F34: =VLOOKUP($A34,Hebrew!$A:$S,4,0) -> מליאת הכנסת אישרה בקריאה טרומית הצעה, לפיה קצין בדרגת ניצב־משנה ומעלה יוכל לבקש אישור מנשיא בית המשפט המחוזי או מסגנו לחדור למחשבים אישיים ולהעתיק מהם חומרים, אם שוכנע שהפעולה נדרשת למניעת "פשע חמור". החוק לא יחול על עבירות שחיתות כגון שוחד, מרמה והפרת אמונים | G34: November 13, 2024 | J34: Haaretz | K34: Noa Shpigel | L34: =VLOOKUP($A34,Hebrew!$A:$S,9,0) -> נעה שפיגל | O34: Hebrew | P34: Israel | Q34: =VLOOKUP($A34,Hebrew!$A:$S,13,0) -> ישראל | R34: Journalistic report | S34: Text | T34: Civilians | U34: Israeli Police | V34: Israel
A35: 2417 | B35: https://www.lemonde.fr/en/les-decodeurs/article/2024/10/13/why-the-gaza-health-ministry-s-death-count-is-considered-reliable_6729264_8.html | C35: Study on MoH death toll being accurate | D35: =VLOOKUP(A35,Hebrew!A:C,3,0) -> מדוע נחשבים הנתונים שמספק משרד הבריאות הפלסטיני בעזה לגבי מספר המתים אמינים? | E35: The article discusses the reliability of the death count provided by the Gaza Health Ministry during the Israel-Gaza conflict, detailing the methodology used and the challenges faced in accurately reporting casualties. | F35: =VLOOKUP($A35,Hebrew!$A:$S,4,0) -> המאמר סוקר את חילוקי הדעות לגבי נתונים שמספק משרד הבריאות בעזה. במאמר נטען שהנתונים אמינים ומקובלים. | G35: October 13, 2024 | J35: Le Monde | K35: Assma Maad | L35: =VLOOKUP($A35,Hebrew!$A:$S,9,0) -> אסמה אעד | O35: English | P35: Gaza Strip | Q35: =VLOOKUP($A35,Hebrew!$A:$S,13,0) -> רצועת עזה | R35: Analysis | S35: Text | T35: Civilians | U35: Hamas, Gaza Health Ministry, IDF (Israel Defense Forces) | V35: Gaza Strip
A36: 2418 | B36: https://www.haaretz.co.il/news/law/2024-12-17/ty-article/00000193-d466-d4ec-a5d3-f57f62f00000 | C36: Israeli activists detained for painting a road in Jerusalem a year and a half ago | D36: =VLOOKUP(A36,Hebrew!A:C,3,0) -> פעילים ישראלים נעצרו על צביעת כביש בירושלים לפני שנה וחצי | E36: Two activists were detained for investigation on suspicion of painting a road in Jerusalem in protest over police brutality over a year ago. | F36: =VLOOKUP($A36,Hebrew!$A:$S,4,0) -> שני פעילים נעצרו לחקירה בחשד ששלפני יותר משנה צבעו כביש בירושלים במחאה נגד המהפכה המשטרית. | G36: December 17, 2024 | J36: Haaretz | K36: Bar Peleg | L36: =VLOOKUP($A36,Hebrew!$A:$S,9,0) -> בר פלג | O36: Hebrew | P36: Jerusalem | Q36: =VLOOKUP($A36,Hebrew!$A:$S,13,0) -> ירושלים | R36: Journalistic report | S36: Text | T36: Israeli Society, Vandalism, Protest (Israel) | V36: Jerusalem
A37: 2419 | B37: https://www.nytimes.com/2024/07/25/us/politics/harris-biden-netanyahu-meeting-israel.html?campaign_id=9&emc=edit_nn_20240726&instance_id=129819&nl=the-morning&regi_id=70279552&segment_id=173210&smid=url-share&te=1&user_id=2e28080c4831073bd853a843a6df3aec | C37: Harris Offers Support for Israel but Calls Out Palestinians’ Plight After Talk With Netanyahu | D37: =VLOOKUP(A37,Hebrew!A:C,3,0) -> הריס מציעה תמיכה לישראל אך מדגישה את מצוקתם של הפלסטינים לאחר שיחה עם נתניהו | E37: Vice President Kamala Harris expresses support for Israel's right to defend itself but also highlights the suffering of Palestinians during a meeting with Prime Minister Benjamin Netanyahu. | F37: =VLOOKUP($A37,Hebrew!$A:$S,4,0) -> סגנית הנשיא קמלה האריס מביעה תמיכה בזכותה של ישראל להגן על עצמה, אך גם מדגישה את הסבל של הפלסטינים במהלך פגישה עם ראש הממשלה בנימין נתניהו. | G37: July 25, 2024 | J37: The New York Times | K37: Peter Baker | L37: =VLOOKUP($A37,Hebrew!$A:$S,9,0) -> פיטר בייקר | O37: English | Q37: =VLOOKUP($A37,Hebrew!$A:$S,13,0) -> 0 | R37: Journalistic report | S37: Text | T37: Civilians, Hostages, Forced Displacement, Starvation | W37: Benjamin Netanyahu, Kamala Harris, Joe Biden
A38: 2420 | B38: https://www.wsj.com/world/middle-east/once-hamass-sworn-enemy-mohammed-dahlan-rises-as-a-postwar-strongman-f64676b1?ref=forever-wars.com | C38: Some U.S., Israeli and Arab officials see Palestinian Mohammed Dahlan as a viable leader of an interim security force | D38: =VLOOKUP(A38,Hebrew!A:C,3,0) -> כמה פקידים אמריקאים, ישראלים וערבים רואים את מוחמד דחלאן הפלסטיני כמנהיג אפשרי של כוח ביטחון זמני אחרי המלחמה. | E38: As part of discussions on the so-called "day after" in Gaza, U.S., Arab, and Israeli officials have proposed that Mohammed Dahlan, formerly head of the Palestinian Authority's security forces, be charged with security in the Gaza Strip, once the war is over. | F38: =VLOOKUP($A38,Hebrew!$A:$S,4,0) -> כחלק מהדיונים על מה שמכונה "היום שאחרי" בעזה, פקידים אמריקאים, ערבים וישראלים הציעו שמוחמד דחלאן, שהיה בעבר ראש כוחות הביטחון של הרשות הפלסטינית וחי כיום באבו דאבי, ימונה לאחראי על הביטחון ברצועת עזה, לאחר שהמלחמה תסתיים. | G38: July 25, 2024 | J38: The Wall Street Journal | K38: Summer Said, Fatima AbdulKarim, and Stephen Kalin | L38: =VLOOKUP($A38,Hebrew!$A:$S,9,0) -> סאמר סייד, פאטימה עבדולכרים, וסטיבן קלין | O38: English | Q38: =VLOOKUP($A38,Hebrew!$A:$S,13,0) -> רצועת עזה | R38: Journalistic report | S38: Text | U38: Hamas, United States
A39: 2421 | B39: https://time.com/7008717/benjamin-netanyahu-interview/ | C39: Bibi at war: Benjamin Netanyahu on Israel's historic crisis and his own | D39: =VLOOKUP(A39,Hebrew!A:C,3,0) -> ביבי במלחמה: בנימין נתניהו על המשבר ההיסטורי של ישראל ועל מדיניתו | E39: Benjamin Netanyahu's leadership during a time of conflict and criticism, with a focus on Israel's security challenges and international relations. | F39: =VLOOKUP($A39,Hebrew!$A:$S,4,0) -> הנהגת בנימין נתניהו בתקופה של סכסוך וביקורת, עם דגש על אתגרי הביטחון של ישראל ויחסים בינלאומיים. | G39: August 8, 2024 | J39: Time | K39: Eric Cortellessa | L39: =VLOOKUP($A39,Hebrew!$A:$S,9,0) -> אריק קורטלסה | O39: English | Q39: =VLOOKUP($A39,Hebrew!$A:$S,13,0) -> 0 | R39: Journalistic report | S39: Text | T39: Israeli Society, Hostages, Ground Operation, Ceasefire, Protest (International), Protest (Israel) | U39: Hamas, IDF (Israel Defense Forces) | W39: Benjamin Netanyahu, Antony Blinken
A40: 2422 | B40: https://www.theatlantic.com/international/archive/2024/09/israel-gaza-war-biden-netanyahu-peace-negotiations/679581/ | C40: Inside the year-long American effort to release the hostages, end the fighting in Gaza, and bring peace to the Middle East | D40: =VLOOKUP(A40,Hebrew!A:C,3,0) -> שנה של מאמץ אמריקאי לשחרר את בני הערובה, לסיים את הלחימה בעזה ולהביא שלום למזרח התיכון | E40: The article discusses the American effort to broker peace in the Middle East, focusing on the Biden administration's involvement during a conflict between Israel and Hamas. | F40: =VLOOKUP($A40,Hebrew!$A:$S,4,0) -> המאמר מספק תיאור כרונולוגי של המאמצים האמריקאיים לתווך שלום במזרח התיכון, תוך התמקדות במעורבות של ממשלת ביידן במהלך הסכסוך בין ישראל לחמאס. | G40: September 25, 2024 | J40: The Atlantic | K40: Franklin Foer | L40: =VLOOKUP($A40,Hebrew!$A:$S,9,0) -> פרנקלין פויר | O40: English | P40: North Gaza | Q40: =VLOOKUP($A40,Hebrew!$A:$S,13,0) -> צפון רצועת עזה | R40: Journalistic report | S40: Text | T40: Hostages, Iron Dome, Air Strike | U40: IDF (Israel Defense Forces) | V40: North Gaza | W40: Benny Gantz, Benjamin Netanyahu, Antony Blinken, Joe Biden, Yoav Gallant, Hassan Nasrallah, Yahya Al-Sinwar, Mohammed bin Salman Al Saud
A41: 2423 | B41: https://www.mekomit.co.il/ps/143011/ | C41: In the besieged Beit Lahia, rotting bodies are scattered among the ruins | D41: =VLOOKUP(A41,Hebrew!A:C,3,0) -> בבית לאחיא הנצורה, גופות מרקיבות מפוזרות בין ההריסות | E41: The article describes the dire situation in Beit Lahia, Gaza, where residents face continuous Israeli bombardment, food and water shortages, and deteriorating living conditions. | F41: =VLOOKUP($A41,Hebrew!$A:$S,4,0) -> המאמר מתאר את המצב הקשה בבית לאהיא, עזה, שבו התושבים מתמודדים עם הפצצות ישראליות מתמשכות, מחסור במזון ובמים, ותנאי חיים מתדרדרים. | G41: December 1, 2024 | J41: Mekomit | K41: Ibrahim Mohammad | L41: =VLOOKUP($A41,Hebrew!$A:$S,9,0) -> איברהים מוחמד | O41: Hebrew | P41: Beit Lahiya | Q41: =VLOOKUP($A41,Hebrew!$A:$S,13,0) -> בית לאהיא | R41: Journalistic report | S41: Text | T41: Urbicide, Hospital, Forced Displacement, Air Strike | U41: IDF (Israel Defense Forces) | V41: Beit Lahiya
A42: 2424 | B42: https://www.dropsitenews.com/p/death-march-from-beit-lahia | C42: Death march from Beit Lahia | D42: =VLOOKUP(A42,Hebrew!A:C,3,0) -> מצעד המוות מבית לאהיא | E42: Hossam Shabat reports on Israel's mass expulsion campaign in Beit Lahia, Gaza, forcing thousands of Palestinians to flee under heavy artillery shelling and gunfire. | F42: =VLOOKUP($A42,Hebrew!$A:$S,4,0) -> חוסאם שבת מדווח על הגירוש ההמוני מבית לאהיא, עזה, תחת הפגזות ארטילריה כבדות וירי. | G42: December 5, 2024 | J42: Drop Site News | K42: Hossam Shabat | L42: =VLOOKUP($A42,Hebrew!$A:$S,9,0) -> חוסאם שבת | O42: English | P42: Beit Lahiya | Q42: =VLOOKUP($A42,Hebrew!$A:$S,13,0) -> בית לאהיא | R42: Journalistic report | S42: Text | T42: Civilians, Journalists, Forced Displacement, Blockade, Ground Operation, Air Strike | U42: IDF (Israel Defense Forces) | V42: North Gaza, Kamal Adwan Hospital , The Indonesian Hospital, Jabaliya, Beit Lahiya
A43: 2425 | B43: https://www.haaretz.co.il/news/politics/2024-12-24/ty-article/00000193-f900-d10a-a797-fb6bab660000 | C43: IDF attacks on hospitals late Dec | D43: =VLOOKUP(A43,Hebrew!A:C,3,0) -> דיווחים פלסטיניים: צה"ל מגביר את התקיפות על בתי חולים בצפון הרצועה ומפנה בכוח מטופלים | E43: Reports from Palestinian sources indicate that the Israeli military is intensifying attacks on hospitals in the northern Gaza Strip, forcibly evacuating patients and causing damage. | F43: =VLOOKUP($A43,Hebrew!$A:$S,4,0) -> דיווחים פלסטיניים מצביעים על כך שהצבא הישראלי מגביר את התקפותיו על בתי חולים בצפון רצועת עזה, מפנה בכוח מטופלים וגורם נזק. | G43: December 24, 2024 | J43: Haaretz | K43: Rawan Suleiman, Jack Khoury | L43: =VLOOKUP($A43,Hebrew!$A:$S,9,0) -> רואן סלימאן, ג'קי חורי | O43: Hebrew | P43: North Gaza | Q43: =VLOOKUP($A43,Hebrew!$A:$S,13,0) -> צפון רצועת עזה | R43: Journalistic report | S43: Text | T43: Hospital, Air Strike | U43: Hamas, IDF (Israel Defense Forces) | V43: Kamal Adwan Hospital, The Indonesian Hospital, Gaza City
A44: 2426 | B44: https://www.israelhayom.com/2025/01/02/knesset-committee-pushes-for-controversial-generals-plan-in-gaza/ | C44: Controversial 'Generals' Plan' in northern Gaza picks up steam | D44: =VLOOKUP(A44,Hebrew!A:C,3,0) -> תוכנית ה'גנרלים' השנויה במחלוקת בצפון עזה צוברת תאוצה | E44: Members of the Knesset Foreign Affairs and Defense Committee demand that the Israeli Ministry of Defence implement the so-called "Generals' Plan," which includes the forced evacuation of civilians and the deprivation of energy, food, and water, in northern Gaza. | F44: =VLOOKUP($A44,Hebrew!$A:$S,4,0) -> חברי ועדת החוץ והביטחון של הכנסת דורשים ממשרד הביטחון הישראלי ליישם את מה שמכונה "תוכנית הגנרלים", הכוללת פינוי כפוי של אזרחים ושלילת אנרגיה, מזון ומים בצפון עזה. | G44: January 2, 2025 | J44: Israel Hayom | K44: Shirit Avitan Cohen | L44: =VLOOKUP($A44,Hebrew!$A:$S,9,0) -> שירית אביטן כהן | O44: English | P44: North Gaza | Q44: =VLOOKUP($A44,Hebrew!$A:$S,13,0) -> צפון רצועת עזה | R44: Journalistic report | S44: Text | T44: Civilians, Food, Forced Displacement, Water | U44: Hamas, IDF (Israel Defense Forces) | V44: North Gaza
A45: 2427 | B45: https://www.ynet.co.il/news/article/bkcljlrdyx#autoplay | C45: Harvard and antisemitism - recompensation | D45: =VLOOKUP(A45,Hebrew!A:C,3,0) -> פשרת הרווארד ואנטישמיות - פיצוי | E45: Harvard University has reached a settlement with Jewish students and the Brandeis Center for Human Rights over allegations of failing to address campus antisemitism. The agreement includes compensation, adopting IHRA's antisemitism definition, and establishing partnerships with Israeli universities. | F45: =VLOOKUP($A45,Hebrew!$A:$S,4,0) -> אוניברסיטת הרווארד הגיעה להסכם עם סטודנטים יהודים ומרכז ברנדייס לזכויות האדם בעקבות האשמות על כך שלא טיפלה באנטישמיות בקמפוס. ההסכם כולל פיצוי, אימוץ ההגדרה של IHRA לאנטישמיות, והקמת שותפויות עם אוניברסיטאות ישראליות. | G45: January 22, 2025 | J45: Ynet | K45: Daniel Adelson | L45: =VLOOKUP($A45,Hebrew!$A:$S,9,0) -> דניאל אדלסון | O45: Hebrew | P45: United States | Q45: =VLOOKUP($A45,Hebrew!$A:$S,13,0) -> ארה"ב | R45: Journalistic report | S45: Text | T45: Antisemitism, Academia | U45: United States | V45: USA
A46: 2428 | B46: https://www.nytimes.com/2024/12/22/us/gaza-war-campuses-middle-ground.html?unlocked_article_code=1.jU4.Vrl4.tuL9laa9sjOB | C46: College students and faculty members are seeking space for nuanced perspectives on the Israel-Hamas war on deeply divided campuses | D46: =VLOOKUP(A46,Hebrew!A:C,3,0) -> סטודנטים ואנשי סגל במכללות מחפשים מרחב לדעות מורכבות על מלחמת ישראל-חמאס בקמפוסים המפולגים עמוקות. | E46: The article discusses efforts by college students and faculty to create space for nuanced perspectives on the Israel-Hamas war amidst campus divisions. | F46: =VLOOKUP($A46,Hebrew!$A:$S,4,0) -> המאמר דן במאמצים של סטודנטים ואנשי סגל במכללות ליצור מרחב לדעות מורכבות על מלחמת ישראל-חמאס על רקע הפיצולים בקמפוסים. | G46: December 22, 2024 | J46: The New York Times | K46: Sharon Otterman | L46: =VLOOKUP($A46,Hebrew!$A:$S,9,0) -> שרון אוטרמן | O46: English | P46: United States | Q46: =VLOOKUP($A46,Hebrew!$A:$S,13,0) -> ארה"ב | R46: Journalistic report | S46: Text | T46: Public Opinion, Academia, Protest (International) | V46: USA
A47: 2429 | B47: https://www.makorrishon.co.il/news/808697/ | C47: Professor from Tel Aviv University accused Israel of war crimes | D47: =VLOOKUP(A47,Hebrew!A:C,3,0) -> פרופסור מאוניברסיטת תל אביב האשים את ישראל בפשעי מלחמה | E47: CAMERA On Campus, an organization monitoring speech on university campuses in the US and Israel, clandestinely recorded a student-organized conversation about the situation in Gaza with Israeli Professor Idan Landau at Tel Aviv University and provided the right-wing newspaper Makor Rishon with the recordings, claiming that Prof. Landau baselessly accused Israel of war crimes in Gaza. | F47: =VLOOKUP($A47,Hebrew!$A:$S,4,0) -> CAMERA בקמפוס, ארגון המנטר את השיח בקמפוסים אוניברסיטאיים בארצות הברית ובישראל, הקליט בסתר שיחה מאורגנת על ידי סטודנטים על המצב בעזה עם הפרופסור הישראלי עידן לנדו באוניברסיטת תל אביב וסיפק לעיתון הימני "מקור ראשון" את ההקלטות, וטען כי פרופ' לנדו האשים את ישראל ללא בסיס בפשעי מלחמה בעזה. | G47: January 14, 2025 | H47: December 19, 2024 | I47: December 19, 2024 | J47: Makor Rishon | K47: Avigail Zait | L47: =VLOOKUP($A47,Hebrew!$A:$S,9,0) -> אביגיל זית | O47: Hebrew | Q47: =VLOOKUP($A47,Hebrew!$A:$S,13,0) -> 0 | R47: Journalistic report | S47: Text | T47: Crimes Against Humanity, Academia | U47: Hamas, IDF (Israel Defense Forces)
A48: 2430 | B48: https://13tv.co.il/item/news/domestic/crime-and-justice/c8nmb-904430163/ | C48: 70 people admitted they pretended to be October 7 victims | D48: =VLOOKUP(A48,Hebrew!A:C,3,0) -> 70 אנשים הודו שהם העמידו פנים שהם קורבנות של ה-7 באוקטובר | E48: Dozens of suspects are being investigated for falsely claiming to be victims of a massacre at the 'Supernova Sukkot Gathering' (Nova) festival near Kibbutz Re'im and Gaza border communities on October 7th. Investigators suspect fraudulent claims of trauma and are considering filing charges against them. | F48: =VLOOKUP($A48,Hebrew!$A:$S,4,0) -> עשרות חשודים נמצאים בחקירה על כך שטוענים שהם קורבנות הטבח במפגש 'סופרנובה סוכות' (נובה) ליד קיבוץ רעים וקהילות בגבול עזה ב-7 באוקטובר. החוקרים חושדים בטענות שקריות על טראומה כדי לקבל מענק מביטוח לאומי ושוקלים להגיש נגדם כתבי אישום. | G48: January 22, 2025 | J48: Reshet 13 | K48: Eli Senior, Aviad Glickman | L48: =VLOOKUP($A48,Hebrew!$A:$S,9,0) -> אלי סניור, אביעד גליקמן | O48: Hebrew | Q48: =VLOOKUP($A48,Hebrew!$A:$S,13,0) -> 0 | R48: Journalistic report | S48: Text | T48: Israeli Society | U48: Israeli Police
A49: 2431 | B49: https://www.insidehighered.com/news/faculty-issues/academic-freedom/2025/01/05/aha-convention-attendees-oppose-scholasticide-gaza | C49: Historians Condemn ‘Scholasticide’ in Gaza at Conference | D49: =VLOOKUP(A49,Hebrew!A:C,3,0) -> כנס היסטוריונים מגנה את השמדת הידע והחינוך בעזה | E49: American Historical Association members at the annual conference vote to oppose 'scholasticide' in Gaza and U.S. funding of Israel's war, calling for a permanent ceasefire and support for Gaza's educational infrastructure. | F49: =VLOOKUP($A49,Hebrew!$A:$S,4,0) -> חברי האגודה ההיסטורית האמריקאית בכנס השנתי הצביעו נהשמדת הידע והחינוך בעזה ומימון המלחמה של ישראל על ידי ארצות הברית, וקוראים להפסקת אש קבועה ולתמיכה בתשתית החינוכית של עזה. | G49: January 5, 2025 | J49: Inside Higher Ed | K49: Ryan Quinn | L49: =VLOOKUP($A49,Hebrew!$A:$S,9,0) -> ראיין קווין | O49: English | Q49: =VLOOKUP($A49,Hebrew!$A:$S,13,0) -> 0 | R49: Journalistic report | S49: Text | T49: Scholasticide, Academia, Education, Schools | U49: UN (United Nations), IDF (Israel Defense Forces)
A50: 2432 | B50: https://www.haaretz.co.il/news/magazine/2024-12-17/ty-article-magazine/.premium/00000193-cf48-dcad-adfb-efeac1eb0000 | C50: An ally of Ben Gvir and a criminal suspect: It turns out that the dominant figure in the police is the Commissioner of the Israel Prison Service | D50: =VLOOKUP(A50,Hebrew!A:C,3,0) -> בן גביר וחשוד בפשע: מתברר שהדמות הדומיננטית במשטרה היא המפקח על שירות בתי הסוהר הישראלי קובי יעקבי. | E50: A drama unfolds in the office of the Minister of National Security, Itamar Ben Gvir, involving a refusal by a police commander to accompany him to the Temple Mount, revealing power struggles within the police force. | F50: =VLOOKUP($A50,Hebrew!$A:$S,4,0) -> דרמה במשרדו של שר הביטחון הלאומי, איתמר בן גביר, עם סירובו של מפקד משטרה ללוות אותו להר הבית, חושפת מאבקים על סמכויות בתוך כוחות המשטרה. | G50: December 17, 2024 | J50: Haaretz | K50: Josh Breiner | L50: =VLOOKUP($A50,Hebrew!$A:$S,9,0) -> יהושע (ג'וש) בריינר | O50: Hebrew | P50: Jerusalem | Q50: =VLOOKUP($A50,Hebrew!$A:$S,13,0) -> ירושלים | R50: Journalistic report | S50: Text | U50: Israeli Police, Israeli Prison | V50: Jerusalem | W50: Kobi Yaakobi
A51: 354 | B51: https://x.com/IamIbrahim21/status/1797521016702550496 | C51: Family forced by conditions to move from tent and seek refuge in rental apartment | D51: =VLOOKUP(A51,Hebrew!A:C,3,0) -> משפחה שנאלצה בעקבות הנסיבות לעזוב את האוהל ולחפש מקלט בדירה שכורה | E51: Family forced to seek accommodation in a burned rental unit after displacement for 1200 NIS ($330), since they cannot tolerate the conditions in the so-called safe areas. | F51: =VLOOKUP($A51,Hebrew!$A:$S,4,0) -> משפחה נאלצה לעזוב את האוהל ולחפש מגורים בשכירות בדירה שרופה ב-1200 ש"ח (330$), בגלל התנאים הקשים באזורים המוגדרים בטוחים. | G51: June 3, 2024 | H51: June 3, 2024 | I51: June 3, 2024 | J51: X | K51: Ibrahim Massri (@IamIbrahim21) | L51: =VLOOKUP($A51,Hebrew!$A:$S,9,0) -> Ibrahim Massri (@IamIbrahim21) | O51: English | P51: Khan Younis | Q51: =VLOOKUP($A51,Hebrew!$A:$S,13,0) -> חאן יונס | R51: Post | S51: Text, Photo | T51: Forced Displacement, Disease, Testimony | V51: Khan Younis
A52: 355 | B52: https://x.com/JalalAK_jojo/status/1797296916763418747 | C52: Footage of IDF drone attack on Gaza | D52: =VLOOKUP(A52,Hebrew!A:C,3,0) -> תיעוד של מתקפת רחפן של צה"ל על עזה | E52: Drone attack on Gaza recorded by IDF soldiers. The drone was downed and its footage was broadcast on Al Jazeera | F52: =VLOOKUP($A52,Hebrew!$A:$S,4,0) -> התקפת רחפן על עזה תועדה על ידי חיילי צה"ל. הרחפן הופל והצילומים שלו שודרו על ידי אל ג'זירה. | G52: June 2, 2024 | H52: May 27, 2024 | I52: May 27, 2024 | J52: X | K52: Jalal (@JalalAK_jojo) | L52: =VLOOKUP($A52,Hebrew!$A:$S,9,0) -> Jalal (@JalalAK_jojo) | O52: English | P52: Gaza Strip | Q52: =VLOOKUP($A52,Hebrew!$A:$S,13,0) -> רצועת עזה | R52: Post | S52: Video, Text | T52: Bombing, Air Strike, Drone / Quadcopter | U52: IDF (Israel Defense Forces) | V52: Gaza Strip
A53: 356 | B53: https://x.com/KhaledYousry22/status/1798729352412319874 | C53: Itamar Ben-Gvir declares intent to resettle Gaza and clear it of Palestinians | D53: =VLOOKUP(A53,Hebrew!A:C,3,0) -> איתמר בן-גביר מכריז על כוונה ליישב מחדש את עזה ולפנות אותה מפלסטינים | E53: Itamar Ben-Gvir declares intent to clear Gaza of Palestinians, in order to occupy it and establish settlements. | F53: =VLOOKUP($A53,Hebrew!$A:$S,4,0) -> איתמר בן גביר מכריז על כוונה לפנות את עזה מפלסטינים, במטרה לכבוש אותה ולהקים בה יישובים. | G53: June 6, 2024 | H53: June 6, 2024 | I53: June 6, 2024 | J53: X | K53: Khaled Yousry (@KhaledYousry22) | L53: =VLOOKUP($A53,Hebrew!$A:$S,9,0) -> Khaled Yousry (@KhaledYousry22) | O53: English, Arabic | P53: Israel | Q53: =VLOOKUP($A53,Hebrew!$A:$S,13,0) -> ישראל | R53: Post | S53: Text, Video | T53: Ethnic Cleansing, Incitement to Genocide, Annexation, Forced Displacement, Settlements | U53: Israeli Government | V53: Israel | W53: Itamar Ben-Gvir
A54: 357 | B54: https://x.com/N12News/status/1798769743119167566 | C54: Bezalel Smotrich calls for return to Gush Katif | D54: =VLOOKUP(A54,Hebrew!A:C,3,0) -> בצלאל סמוטריץ' קורא לשוב לגוש קטיף | E54: Bezalel Smotrich calls for return to Gush Katif in a ceremony at Merkaz HaTora veHaAretz. | F54: =VLOOKUP($A54,Hebrew!$A:$S,4,0) -> בצלאל סמוטריץ' קורא לשוב לגוש קטיף בטקס במרכז התורה והארץ. | G54: June 6, 2024 | H54: June 6, 2024 | I54: June 6, 2024 | J54: X | K54: N12 news (@N12News) | L54: =VLOOKUP($A54,Hebrew!$A:$S,9,0) -> N12 חדשות (@N12News) | O54: Hebrew | P54: Israel | Q54: =VLOOKUP($A54,Hebrew!$A:$S,13,0) -> ישראל | R54: Post | S54: Video, Text | T54: Religious Right, Ethnic Cleansing, Forced Displacement, Settlements, Annexation | U54: Israeli Government, IDF (Israel Defense Forces) | V54: Israel | W54: Bezalel Smotritch
A55: 358 | B55: https://x.com/YehudaShaul/status/1737112308672016760 | C55: Incitement to racism at events for IDF soldiers | D55: =VLOOKUP(A55,Hebrew!A:C,3,0) -> אמנים המופיעים בפני חיילי צה"ל מחזקים מגמות של הסתה, גזענות ופוליטיקה קיצועית | E55: A 19-tweet thread that includes several cases of artists appearing before IDF troops strengthen existing trends of racism and extremism. Increased calls for restablishment of settlements in Gaza. The thread also includes additional examples of racism and dehumanizaiton, as well as hoping to hit innocent people in Gaza. | F55: =VLOOKUP($A55,Hebrew!$A:$S,4,0) -> שרשור של 19 ציוצים שכולל מספר מקרים של אמנים המופיעים בפני חיילי צה"ל ומחזקים מגמות קיימות של גזענות וקיצוניות וקריאות לשוב ולהקים התנחלויות בעזה. השרשור כולל דוגמאות נוספות לגזענות ולדה-הומניזציה, כמו גם תקוות לפגוע באנשים חפים מפשע בעזה. | G55: December 19, 2023 | J55: X | K55: Yehuda Shaul (@YehudaShaul) | L55: =VLOOKUP($A55,Hebrew!$A:$S,9,0) -> יהודה שאול (@YehudaShaul) | O55: English, Hebrew | P55: Gaza Strip | Q55: =VLOOKUP($A55,Hebrew!$A:$S,13,0) -> רצועת עזה | R55: Post | S55: Text, Video | T55: Annexation, Incitement to Genocide, Racism, Abuse, Humiliation, Israeli Soldier Movies, Jewish Settlements in Gaza | U55: IDF (Israel Defense Forces) | V55: Gaza Strip
A56: 359 | B56: https://x.com/abierkhatib/status/1793720981607071831 | C56: IDF soldier filmed vandalizing school property in Gaza | D56: =VLOOKUP(A56,Hebrew!A:C,3,0) -> חייל צה"ל תועד משחית רכוש בית ספר בעזה | E56: Israeli soldier filming himself in an elementary school smashing certificates honouring talented students in Gaza, while also declaring the intention to return to Gush Katif and resettle Gaza. | F56: =VLOOKUP($A56,Hebrew!$A:$S,4,0) -> חייל ישראלי מצלם את עצמו בבית ספר יסודי כשהוא הורס תעודות המוקירות תלמידים מוכשרים בעזה, תוך כדי שהוא מכריז על כוונתו לחזור לגוש קטיף וליישב מחדש את עזה. | G56: May 23, 2024 | J56: X | K56: Abier (@abierkhatib) | L56: =VLOOKUP($A56,Hebrew!$A:$S,9,0) -> Abier (@abierkhatib) | O56: English, Hebrew | P56: Gaza Strip | Q56: =VLOOKUP($A56,Hebrew!$A:$S,13,0) -> רצועת עזה | R56: Post | S56: Video, Text | T56: Education, Abuse, Scholasticide, Children, Israeli Soldier Movies, Vandalism, Schools, Jewish Settlements in Gaza | U56: IDF (Israel Defense Forces) | V56: Gaza Strip
A57: 361 | B57: https://x.com/marcowenjones/status/1795063041513402446 | C57: Confusion regarding IDF's messaging on safe zones in Gaza | D57: =VLOOKUP(A57,Hebrew!A:C,3,0) -> חוסר בהירות לגבי המסרים של צה"ל על אזורי בטיחות בעזה | E57: IDF maps of "safe zones" in Gaza are imprecise, with animations expanding areas and creating confusion for civilians. Marc Owen Jones highlights inconsistencies and unclear boundaries. | F57: =VLOOKUP($A57,Hebrew!$A:$S,4,0) -> מפות צה"ל של "אזורי בטיחות" בעזה אינן מדויקות, עם אנימציות שמרחיבות אזורים ויוצרות בלבול אצל אזרחים. מארק אוון ג'ונס מדגיש חוסר עקביות וגבולות לא ברורים. | G57: May 22, 2024 | H57: May 22, 2024 | I57: May 22, 2024 | J57: X | K57: Marc Owen Jones (@marcowenjones) | L57: =VLOOKUP($A57,Hebrew!$A:$S,9,0) -> Marc Owen Jones (@marcowenjones) | O57: English, Arabic | P57: Rafah | Q57: =VLOOKUP($A57,Hebrew!$A:$S,13,0) -> רפיח | R57: Post | S57: Video, Text | T57: Forced Displacement, Air Strike, Warning | U57: IDF (Israel Defense Forces) | V57: Rafah | W57: Avichay Adraee
A58: 362 | B58: https://x.com/moshebs11/status/1766830282219372906 | C58: Bringing a torah scroll to Nezarim Corridor | D58: =VLOOKUP(A58,Hebrew!A:C,3,0) -> הבאת מגילת תורה למעבר נצרים | E58: IDF soldiers singing and dancing as they bring a Torah scroll to Nezarim Corridor, Gaza. | F58: =VLOOKUP($A58,Hebrew!$A:$S,4,0) -> חיילי צה"ל שרים ורוקדים כשהם מביאים ספר תורה למעבר נצרים, עזה. | G58: March 10, 2024 | J58: X | K58: Moshe ben Shitrit (@moshebs11) | L58: =VLOOKUP($A58,Hebrew!$A:$S,9,0) -> משה בן שטרית (@moshebs11) | O58: Hebrew | P58: Netzarim Corridor | Q58: =VLOOKUP($A58,Hebrew!$A:$S,13,0) -> מסדרון נצרים | R58: Post | S58: Text, Video | T58: Religious Right, Israeli Soldier Movies | U58: IDF (Israel Defense Forces) | V58: Netzarim Corridor
A59: 363 | B59: https://x.com/ytirawi/status/1794113236708573451 | C59: IDF soldier details destruction of Khuza'a (Khirbat Akhzaya) as revenge, as a part of "Oz and Nir" Operation | D59: =VLOOKUP(A59,Hebrew!A:C,3,0) -> חייל צה"ל מפרט את הריסת ח'וּזַ֫אעַה (חִ֫'רְבֶּת אֶחְ'זַ֫אעַה) כנקמה, כחלק ממבצע "עוז וניר" | E59: IDF soldier describes his part in destroying the village of Khuza'a (Khirbat Akhzaya) in Gaza, as a revenge for Oct. 7. The post claims to expose genocidal operation "Oz and Nir". | F59: =VLOOKUP($A59,Hebrew!$A:$S,4,0) -> חייל צה"ל מתאר את חלקו בהריסת הכפר ח'וּזַ֫אעַה (חִ֫'רְבֶּת אֶחְ'זַ֫אעַה) בעזה, כנקמה על ה-7 באוקטובר. הפוסט טוען לחשוף את מבצע רצח עם "עוז וניר". | G59: May 25, 2024 | H59: January 8, 2024 | I59: January 8, 2024 | J59: X | K59: Younis Tirawi (@ytirawi) | L59: =VLOOKUP($A59,Hebrew!$A:$S,9,0) -> Younis Tirawi (@ytirawi) | O59: Hebrew | P59: Khuza'a | Q59: =VLOOKUP($A59,Hebrew!$A:$S,13,0) -> ח'וזעה | R59: Post | S59: Photo, Text | T59: Collective Punishment, Domicide, Incitement to Genocide, Urbicide, Genocide, Bombing, Israeli Soldier Testimonies, Destruction | U59: IDF (Israel Defense Forces) | V59: Gaza Strip, Khuza'a
A60: 364 | B60: https://x.com/ytirawi/status/1795129920902873557 | C60: IDF using hospital as mililtary base | D60: =VLOOKUP(A60,Hebrew!A:C,3,0) -> צה"ל משתמש בבית חולים בתור בסיס צבאי | E60: IDF soldiers relax on hospital beds at Noura Kaabi Dialysis Hospital in the Jabalia Refugee camp. Smiles and good cheer abound. | F60: =VLOOKUP($A60,Hebrew!$A:$S,4,0) -> חיילי צה"ל נחים על מיטות בבית החולים לדיאליזה נורה קאבי במחנה הפליטים ג'באליה. חיוכים ואווירה טובה שוררים. | G60: May 27, 2024 | J60: X | K60: Younis Tirawi (@ytirawi) | L60: =VLOOKUP($A60,Hebrew!$A:$S,9,0) -> Younis Tirawi (@ytirawi) | O60: English | P60: Jabaliya | Q60: =VLOOKUP($A60,Hebrew!$A:$S,13,0) -> ג'באליה | R60: Post | S60: Photo, Text | T60: Hospital, Israeli Soldier Photos | U60: IDF (Israel Defense Forces) | V60: Jabaliya
A61: 368 | B61: https://twitter.com/Bar_ShemUr/status/1757852992215056477 | C61: Likud spokesman warns hostage families against calling for elections | D61: =VLOOKUP(A61,Hebrew!A:C,3,0) -> דובר הליכוד מזהיר את משפחות החטופים מפני קריאה לבחירות | E61: Likud spokesman Guy Levi met with families of Israeli hostages, urging them to oppose new elections and warning that the political fallout would be far worse than before October 7. Several attendees described his remarks as a direct threat. | F61: =VLOOKUP($A61,Hebrew!$A:$S,4,0) -> דובר הליכוד גיא לוי נפגש עם משפחות של חטופים ישראלים ודחק בהן להתנגד לבחירות חדשות והזהיר שההשלכות הפוליטיות יהיו הרבה יותר גרועות מלפני ה-7 באוקטובר. כמה מהנוכחים תיארו את דבריו כאיום ישיר. | G61: February 14, 2024 | H61: January 30, 2024 | I61: January 30, 2024 | J61: X | K61: Bar Shem-Ur (@Bar_ShemUr) | L61: =VLOOKUP($A61,Hebrew!$A:$S,9,0) -> בר שם-אור (@Bar_ShemUr) | M61: Hatzinor | N61: https://x.com/Bar_ShemUr/status/1757863600578777418 | O61: Hebrew | Q61: =VLOOKUP($A61,Hebrew!$A:$S,13,0) -> 0 | R61: Post | S61: Text, Photo | T61: Abuse, Hostages, Hostage Deal, Journalistic Report | U61: Israeli Government, Hostages and Missing Families Forum
A62: 369 | B62: https://twitter.com/Uvda_tweet/status/1778496650798833931 | C62: Testimonies from negotiators on the condition of hostages | D62: =VLOOKUP(A62,Hebrew!A:C,3,0) -> עדויות של מנהלי משא ומתן על מצב חטופים | E62: A television documentary presenting accounts from individuals involved in recent negotiations for the return of Israeli hostages. The testimonies provide insight into the deteriorating conditions of the hostages and the urgency surrounding the negotiations. | F62: =VLOOKUP($A62,Hebrew!$A:$S,4,0) -> סרט תיעודי טלוויזיוני מציג דיווחים מאנשים מעורבים לאחרונה במשא ומתן להחזרת החטופים הישראלים. העדויות מספקות תובנה על התנאים המידרדרים של החטופים ועל דחיפות המו"מ. | G62: April 11, 2024 | J62: X | K62: Uvda with Ilana Dayan (@Uvda_tweet) | L62: =VLOOKUP($A62,Hebrew!$A:$S,9,0) -> עובדה עם אילנה דיין (@Uvda_tweet) | O62: Hebrew | Q62: =VLOOKUP($A62,Hebrew!$A:$S,13,0) -> 0 | R62: Post | S62: Video, Text | T62: Captivity Conditions, Civilians, Hostage Deal, Hostages, Journalistic Report, Interview, Israeli Negotiation Team | U62: Hamas, Shin Bet, Mossad
A63: 370 | B63: https://twitter.com/_selftitled_/status/1784272179817041951 | C63: Interview with adviser to Qatari Prime Minister: Hostage deal repeatedly blocked at final stages | D63: =VLOOKUP(A63,Hebrew!A:C,3,0) -> ראיון עם יועץ לראש ממשלת קטאר: עסקת בני הערובה נחסמה שוב ושוב בשלבים הסופיים | E63: Qatari official stated that "every time a [hostage] deal was near, it was blocked." | F63: =VLOOKUP($A63,Hebrew!$A:$S,4,0) -> בכיר קטארי הצהיר כי "כל פעם שעסקה [חטופים] הייתה קרובה, היא נחסמה" | G63: April 27, 2024 | H63: April 27, 2024 | I63: April 27, 2024 | J63: X | K63: Sof (@selftitled) | L63: =VLOOKUP($A63,Hebrew!$A:$S,9,0) -> Sof (@selftitled) | M63: Haaretz | O63: Hebrew | Q63: =VLOOKUP($A63,Hebrew!$A:$S,13,0) -> 0 | R63: Post | S63: Photo, Text | T63: Captivity Conditions, Ceasefire | U63: Mossad, Qatar, Shin Bet, Israeli Government
A64: 360 | B64: https://x.com/ireallyhateyou/status/1802435990251848148 | C64: Moshe Feiglin's statement on the need to conquer Gaza | D64: =VLOOKUP(A64,Hebrew!A:C,3,0) -> הצהרת משה פייגלין על הצורך לכבוש את עזה | E64: Moshe Feiglin asserts that Israel cannot tolerate the existence of a single "Islamo-Nazi" if it is to survive. "It's us or them" with explicit reference to Hitler's declaration against the Jews. | F64: =VLOOKUP($A64,Hebrew!$A:$S,4,0) -> משה פייגלין טוען שישראל לא יכולה לסבול את קיומו של "איסלאמו-נאצי" אחד, אם היא רוצה לשרוד. "זה אנחנו או הם" עם התייחסות מפורשת להצהרתו של היטלר נגד היהודים. | G64: June 16, 2024 | J64: X | K64: B.M. (@ireallyhateyou) | L64: =VLOOKUP($A64,Hebrew!$A:$S,9,0) -> B.M. (@ireallyhateyou) | M64: Keshet 12 | O64: Hebrew, English | P64: Israel | Q64: =VLOOKUP($A64,Hebrew!$A:$S,13,0) -> ישראל | R64: Post | S64: Video, Text | T64: Religious Right, Incitement to Genocide, Collective Punishment, Interview, Jewish Settlements in Gaza | V64: Israel | W64: Moshe Feiglin
A65: 365 | B65: https://x.com/ytirawi/status/1798462630736396472 | C65: IDF soldier speaks on "Oz and Nir" Operation in Khuza'a (Khirbat Akhzaya) | D65: =VLOOKUP(A65,Hebrew!A:C,3,0) -> חייל צה"ל מדבר על מבצע "עוז וניר" בח'וּזַ֫אעַה (חִ֫'רְבֶּת אֶחְ'זַ֫אעַה) | E65: Interview with IDF soldier regarding the destruction of Khuza'a (Khirbat Akhzaya), as a part of "Oz and Nir" Operation. The town of 13,000 Palestinians was completely destroyed. | F65: =VLOOKUP($A65,Hebrew!$A:$S,4,0) -> ראיון עם חייל צה"ל בנוגע להריסת ח'וּזַ֫אעַה (חִ֫'רְבֶּת אֶחְ'זַ֫אעַה), כחלק ממבצע "עוז וניר". העיירה של 13,000 פלסטינים נהרסה לחלוטין. | G65: June 6, 2024 | J65: X | K65: Younis Tirawi (@ytirawi) | L65: =VLOOKUP($A65,Hebrew!$A:$S,9,0) -> Younis Tirawi (@ytirawi) | N65: https://x.com/ytirawi | O65: English | P65: Khuza'a | Q65: =VLOOKUP($A65,Hebrew!$A:$S,13,0) -> ח'וזעה | R65: Post | S65: Text, Audio | T65: Forced Displacement, Domicide, Journalistic Report, Israeli Soldier Testimonies, Urbicide, Interview | U65: IDF (Israel Defense Forces) | V65: Gaza Strip, Khan Younis, Khuza'a
A66: 371 | B66: https://twitter.com/tomashinyu3/status/1747651031737979233 | C66: Confusion regarding cause of death of hostages Sherman, Beizer and Toledano | D66: =VLOOKUP(A66,Hebrew!A:C,3,0) -> חוסר בהירות לגבי סיבת המוות של בני הערובה שרמן, בייזר וטולדנו | E66: Survey of possible causes of death of three hostages-soldiers following IDF Spokesperson statement that they may have been suffocated or poisoned. The writer speculates whether the IDF may have intentionally killed the hostages and states as part of a policy of abandoning or killing the remaining hostages and if so, what the implications will be for Israel society. | F66: =VLOOKUP($A66,Hebrew!$A:$S,4,0) -> סקר של סיבות אפשריות למותם של שלושה חיילים-חטופים בעקבות הצהרת דובר צה"ל כי ייתכן שהם נחנקו או הורעלו. הכותב מעלה שאלה האם צה"ל הרג בכוונה את בני הערובה ומציין כחלק ממדיניות של נטישה או הרג של החטופים הנותרים ואם כן, מה יהיו ההשלכות על החברה הישראלית. | G66: January 17, 2024 | H66: January 17, 2024 | I66: January 17, 2024 | J66: X | K66: Tomer Sharon (@tomashinyu3) | L66: =VLOOKUP($A66,Hebrew!$A:$S,9,0) -> תומר שרון (@tomashinyu3) | O66: Hebrew | P66: Gaza Strip | Q66: =VLOOKUP($A66,Hebrew!$A:$S,13,0) -> רצועת עזה | R66: Post | S66: Text | T66: Hostages, Hostage Deal, Hannibal Directive | U66: Israeli Government, Hamas, IDF (Israel Defense Forces) | V66: Gaza Strip
A67: 1450 | B67: https://twitter.com/josh_hammer/status/1711185635229282605 | C67: The events of Saturday, October 7 are indescribable | D67: =VLOOKUP(A67,Hebrew!A:C,3,0) -> אין מילים כדי לתאר את אירועי שבת, 7 באוקטובר | E67: The author, Senior Editor-at-large of Newsweek at the time, describes his views about the causes of October 7 essentially arguing that there can be no peaceful solution. Prescribing instead a forced removal of "identifiable" civilian population from Gaza to Egypt, razing of infrastructure, Eradication of all Hamas members and infrastructure, re-annexation, installment of puppet regime. Blaming democratic US administrations and officials. | F67: =VLOOKUP($A67,Hebrew!$A:$S,4,0) -> המחבר, עורך בכיר של ניוזוויק באותה תקופה, מתאר את דעותיו לגבי הסיבות ל-7 באוקטובר, וטוען בעצם שאין פתרון של שלום. הוא ממליץ במקום זאת על גירוש בכוח של אוכלוסייה אזרחית "ניתנת לזיהוי" מעזה למצרים, הריסת תשתיות, חיסול כל חברי חמאס ותשתיותיהם, חזרה לסיפוח רצועת עזה והקמת משטר בובות בה. הוא מאשים את הממשלות והפקידים הדמוקרטיים בארצות הברית. | G67: October 9, 2023 | H67: October 9, 2024 | I67: October 9, 2024 | J67: X | K67: Josh Hammer (@josh_hammer) | L67: =VLOOKUP($A67,Hebrew!$A:$S,9,0) -> Josh Hammer (@josh_hammer) | O67: English | Q67: =VLOOKUP($A67,Hebrew!$A:$S,13,0) -> 0 | R67: Post | S67: Text | T67: Ethnic Cleansing, Religious Right, Annexation, Forced Displacement, Civilians, Collective Punishment, Incitement to Genocide, Hostages, Opinion, Demolition, Infrastructure, Conspiracy theories | U67: Egypt, Mossad, Hamas, Iran, Shin Bet, Hezbollah, United States, Qatar, IDF (Israel Defense Forces) | W67: Joe Biden, Benjamin Netanyahu, Almog Boker
A68: 1451 | B68: https://twitter.com/kann_news/status/1770492431990956343 | C68: Is there starvation in Gaza as claimed by WFO? | D68: =VLOOKUP(A68,Hebrew!A:C,3,0) -> האם יש רעב בעזה כפי שטוענת ה-WFO? | E68: Shaul Amsterdamsky in interview with Nurit Yohanan, Palestinian affairs correspondent at Kan who analyzes World Food Organization figures regarding starvation/malnutrition figures in Gaza following the publication of the World Food Programme's Integrated Food Security Phase Classification report. Yohanan judges the WFP figures to be largely accurate. | F68: =VLOOKUP($A68,Hebrew!$A:$S,4,0) -> שאול אמסטרדמסקי בראיון עם נורית יוחנן, כתבת לענייני פלסטינים ב"כאן", שמנתחת את הנתונים של ארגון המזון העולמי לגבי רעב/תת תזונה בעזה בעקבות פרסום דוח סיווג שלב הביטחון התזונתי של תוכנית המזון העולמית. יוחנן מעריכה שהנתונים של WFP מדויקים ברובם. | G68: March 20,2024 | H68: March 18, 2024 | I68: March 18, 2024 | J68: X | K68: Kann News (@kann_news) | L68: =VLOOKUP($A68,Hebrew!$A:$S,9,0) -> חדשות כאן(@kann_news) | N68: https://www.wfp.org/news/famine-imminent-northern-gaza-new-report-warns | O68: Hebrew | P68: Gaza Strip | Q68: =VLOOKUP($A68,Hebrew!$A:$S,13,0) -> רצועת עזה | R68: Post | S68: Video, Text | T68: Starvation, Analysis, Food | U68: World Food Programme, UN (United Nations), UNRWA (The UN Relief and Works Agency for Palestine Refugees) | V68: Gaza Strip
A69: 1453 | B69: https://twitter.com/ofercass/status/1783896320933036133 | C69: Police invade Hadash party HQ in Nazareth before the 1 May demonstration | D69: =VLOOKUP(A69,Hebrew!A:C,3,0) -> המשטרה פלשה למטה מפלגת חד"ש בנצרת לפני הפגנת 1 במאי | E69: Police search and vandalize artwork for the May 1st parade in Hadash party's club in Nazareth. Two people detained. | F69: =VLOOKUP($A69,Hebrew!$A:$S,4,0) -> המשטרה עשתה חיפוש במועדון מפלגת חד"ש בנצרת והשחיתה יצירות אמנות לקראת מצעד ה-1 במאי . שני אנשים נעצרו. | G69: April 26, 2024 | H69: April 26, 2024 | I69: April 26, 2024 | J69: X | K69: Ofer Cassif (@ofercass) | L69: =VLOOKUP($A69,Hebrew!$A:$S,9,0) -> עופר כסיף (@ofercass) | O69: Hebrew, English | Q69: =VLOOKUP($A69,Hebrew!$A:$S,13,0) -> 0 | R69: Post | S69: Video, Text | T69: Abuse, Palestinian Citizens of Israel, Vandalism, Limiting Free Speech | U69: Israeli Police
A70: 1454 | B70: https://twitter.com/petersavodnik/status/1778620648551829969 | C70: Pro-Israel campaign to discredit the Gaza Health Ministry's data | D70: =VLOOKUP(A70,Hebrew!A:C,3,0) -> קמפיין פרו-ישראלי להפרכת נתוני משרד הבריאות בעזה | E70: A report attempting to cast doubt on the Ministry of Health's claim, arguing that that Israel has killed "only" 22,000 and not 30,000 Gazans by April 2024. Allegedly this would put the ratio of combatants to non-combatants at 1:1. | F70: =VLOOKUP($A70,Hebrew!$A:$S,4,0) -> דו"ח המנסה לערער על טענת משרד הבריאות בעזה, וטוען כי ישראל הרגה "רק" 22,000 ולא 30,000 פלסטינים בעזה עד אפריל 2024. לכאורה, זה היה מציב את היחס בין לוחמים לאזרחים לא מעורבים על 1:1. | G70: April 11, 2024 | H70: April 6, 2024 | I70: April 6, 2024 | J70: X | K70: Peter Savodnik (@petersavodnik) | L70: =VLOOKUP($A70,Hebrew!$A:$S,9,0) -> Peter Savodnik (@petersavodnik) | N70: https://www.fdd.org/analysis/2024/04/09/hamas-run-gaza-health-ministry-admits-to-flaws-in-casualty-data/ | O70: English | P70: Gaza Strip | Q70: =VLOOKUP($A70,Hebrew!$A:$S,13,0) -> רצועת עזה | R70: Post | S70: Photo, Text | T70: Journalistic report, Civilians, Genocide, Doubting the Gaza death toll, Gaza death toll | U70: Gaza Health Ministry, Hamas, Foundation for the Defense of Democracies, IDF (Israel Defense Forces) | V70: Gaza Strip
A71: 428 | B71: https://twitter.com/CensoredMen/status/1765773664325075354 | C71: Popular Israeli Telegram channel mocks Palestinian child who died of starvation. | D71: =VLOOKUP(A71,Hebrew!A:C,3,0) -> ערוץ טלגרם ישראלי פופולרי לועג לילד פלסטיני שמת מרעב. | E71: An Israeli Telegram account published a mocking poster, presenting the deceased Palestinian child with cerebral palsy, Yazan al-Kafarneh, as an alien. | F71: =VLOOKUP($A71,Hebrew!$A:$S,4,0) -> חשבון טלגרם ישראלי פרסם פוסטר לועג, המציג את הילד הפלסטיני המנוח עם שיתוק מוחין, יזן אל-כפרנה, כאילו היה חייזר. | G71: March 7, 2024 | H71: March 4, 2024 | I71: March 7, 2024 | J71: X | K71: Censored Men (@CensoredMen) | L71: =VLOOKUP($A71,Hebrew!$A:$S,9,0) -> גברים מצונזרים (@CensoredMen) | O71: English, Hebrew | Q71: =VLOOKUP($A71,Hebrew!$A:$S,13,0) -> 0 | R71: Post | S71: Text, Photo | T71: Dehumanization, Humiliation, Children, Starvation, Social Media
A72: 429 | B72: https://twitter.com/EmilioMorenatti/status/1759669676810904020 | C72: IDF soldiers smile as they take a selfie against a backdrop of the ruins of Gaza. | D72: =VLOOKUP(A72,Hebrew!A:C,3,0) -> חיילות צה"ל מחייכות תוך צילום סלפי על רקע חורבות עזה. | E72: IDF female soldiers posed and smiled for a selfie photo among the ruins of destroyed Gazan homes. | F72: =VLOOKUP($A72,Hebrew!$A:$S,4,0) -> חיילות צה"ל מחייכות תוך כדי צילום סלפי על רקע חורבות הבתים ההרוסים בעזה. | G72: February 19, 2024 | J72: X | K72: Emilio Morenatti (@EmilioMorenatti) | L72: =VLOOKUP($A72,Hebrew!$A:$S,9,0) -> Emilio Morenatti (@EmilioMorenatti) | O72: English | P72: Gaza Strip | Q72: =VLOOKUP($A72,Hebrew!$A:$S,13,0) -> רצועת עזה | R72: Post | S72: Text, Photo | T72: Israeli Society, Abuse, Destruction, Dehumanization | U72: IDF (Israel Defense Forces) | V72: Gaza Strip
A73: 430 | B73: https://twitter.com/GLZRadio/status/1773260052683469178 | C73: Ex-IDF official calls to resettle Gaza on Israeli radio. | D73: =VLOOKUP(A73,Hebrew!A:C,3,0) -> ראש אכ"א לשעבר לאילנה דיין בגל"צ קורא להתיישבות מחדש בחבל עזה. | E73: Mordechai (Moti) Almoz, former IDF general and head of the Israeli Civil Administration, advocates resettling Gaza, accusing Palestinians of constant aggression and labeling them as "human animals." | F73: =VLOOKUP($A73,Hebrew!$A:$S,4,0) -> מרדכי (מוטי) אלמוז, ראש א"כ לשעבר, תומך בהתיישבות מחדש בעזה, ומאשים את הפלסטינים בתוקפנות מתמדת ומכנה אותם "חיות אדם." | G73: March 28, 2024 | H73: March 28, 2024 | I73: March 28, 2024 | J73: X | K73: GLZRadio (@GLZRadio) | L73: =VLOOKUP($A73,Hebrew!$A:$S,9,0) -> גל"צ (@GLZRadio) | O73: Hebrew | Q73: =VLOOKUP($A73,Hebrew!$A:$S,13,0) -> 0 | R73: Post | S73: Text, Photo | T73: Settlements, War Crimes, Religious Right, Dehumanization, Disengagement (2005) | U73: IDF (Israel Defense Forces)
A74: 431 | B74: https://twitter.com/GLZRadio/status/1779764062433284213 | C74: Smotrich describes Gazan civilians as Nazis and calls for imposing military rule in Gaza. | D74: =VLOOKUP(A74,Hebrew!A:C,3,0) -> סמוטריץ' מתאר את אזרחי עזה כנאצים וקורא להטיל שלטון צבאי בעזה. | E74: Finance Minister Bezalel Smotrich asserts that all Gazan civilians ("2 million people") are Nazis "who want to butcher, rape and kill any Jew", arguing that Israel should govern Gaza rather than any local civilian authority. | F74: =VLOOKUP($A74,Hebrew!$A:$S,4,0) -> שר האוצר בצלאל סמוטריץ' טוען שכל האזרחים בעזה ("2 מיליון אנשים") הם נאצים "שרוצים לשחוט, לאנוס ולרצוח כל יהודי", וטוען שישראל צריכה לשלוט בעזה עד שתימצא אזרחית מקומית מתונה. | G74: April 15, 2024 | H74: April 15, 2024 | I74: April 15, 2024 | J74: X | K74: GLZRadio (@GLZRadio) | L74: =VLOOKUP($A74,Hebrew!$A:$S,9,0) -> גל"צ (@GLZRadio) | O74: Hebrew | P74: Israel | Q74: =VLOOKUP($A74,Hebrew!$A:$S,13,0) -> ישראל | R74: Post | S74: Text, Photo | T74: Dehumanization, Annexation, Religious Right | U74: Israeli Government | V74: Israel | W74: Bezalel Smotritch
A75: 438 | B75: https://twitter.com/LensVeritatis/status/1774998396501373207 | C75: Soldiers, mostly shirtless, dance while mocking Gazan detainees and ridiculing Palestinian Dabke. | D75: =VLOOKUP(A75,Hebrew!A:C,3,0) -> חיילים, רובם ללא חולצות, רוקדים תוך כדי לעג לעצורים מעזה ולעג לדבקה הפלסטינית. | E75: Dozens of IDF soldiers staged a mocking display, with one standing atop a bulldozer bucket dressed in white overalls as worn by Gazan detainees, while others joined in by imitating and ridiculing the traditional Palestinian Dabke dance. | F75: =VLOOKUP($A75,Hebrew!$A:$S,4,0) -> עשרות חיילי צה"ל ערכו מופע לגלוג, כאשר אחד מהם עמד על דלי של דחפור לבוש במדי עבודה לבנים כמו אלו של עצורים מעזה, בעוד אחרים הצטרפו בחיקוי ולגלוג לריקוד הדבקה המסורתי הפלסטיני. | G75: April 2, 2024 | J75: X | K75: Dr Lens Veritatis (@LensVeritatis) | L75: =VLOOKUP($A75,Hebrew!$A:$S,9,0) -> Dr Lens Veritatis (@LensVeritatis) | O75: English | Q75: =VLOOKUP($A75,Hebrew!$A:$S,13,0) -> 0 | R75: Post | S75: Text, Video | T75: Israeli Society, Humiliation, Dehumanization, Destruction | U75: IDF (Israel Defense Forces)
A76: 440 | B76: https://twitter.com/MacaesBruno/status/1787573947690819907 | C76: Senior Likud official calls for indiscriminate killing of civilians in Rafah. | D76: =VLOOKUP(A76,Hebrew!A:C,3,0) -> בכיר בליכוד קורא להרג חסר הבחנה של אזרחים ברפיח. | E76: Shimon Boker, Deputy Chairman of the World Likud, in an interview to Ofira Asayag and Chaim Levinson, Channel 12: "We need to crack down on them(...) We should have entered Rafah already yesterday(...) There are no uninvolved people there. We need to go in and kill, and kill, and kill." | F76: =VLOOKUP($A76,Hebrew!$A:$S,4,0) -> שמעון בוקר, סגן יושב ראש הליכוד העולמי, בראיון לאופירה אסייג וחיים לוינסון, ערוץ 12: "אנחנו צריכים להכות בהם(...) היינו צריכים להיכנס לרפיח כבר אתמול(...) אין שם אנשים לא מעורבים. אנחנו צריכים להיכנס ולقتل, ולقتل, ולقتل." | G76: May 6,2024 | J76: X | K76: Bruno Macaes (@MacaesBruno) | L76: =VLOOKUP($A76,Hebrew!$A:$S,9,0) -> Bruno Macaes (@MacaesBruno) | M76: Keshet 12 | O76: English, Hebrew | P76: Israel | Q76: =VLOOKUP($A76,Hebrew!$A:$S,13,0) -> ישראל | R76: Post | S76: Text, Video | T76: Civilians, Collective Punishment, Dehumanization, Ethnic Cleansing, Incitement to Genocide, Israeli Society, Media | U76: Israeli Government | V76: Rafah, Israel | W76: Shimon Boker
A77: 1455 | B77: https://twitter.com/ytirawi/status/1774836624280473643 | C77: A defamation attempt against Palestinian journalist Younis Tirawi | D77: =VLOOKUP(A77,Hebrew!A:C,3,0) -> ניסיון הכפשה נגד העיתונאי הפלסטיני יוניס טיראווי. | E77: Tirawi was approached by a journallist from 13 News claiming that he, Tirawi, does not meet journalistic standards in his posts about IDF soldiers in Gaza. | F77: =VLOOKUP($A77,Hebrew!$A:$S,4,0) -> טיראווי: פנה אליו עיתונאי מחדשות-13 שטוען שהוא, טיראווי, לא עומד בסטנדרטים עיתונאיים בפוסטים שלו על חיילי צה"ל בעזה. | G77: April 1, 2024 | H77: April 1, 2024 | I77: April 1, 2024 | J77: X | K77: Younis Tirawi (@ytirawi) | L77: =VLOOKUP($A77,Hebrew!$A:$S,9,0) -> Younis Tirawi (@ytirawi) | O77: English | P77: Gaza Strip | Q77: =VLOOKUP($A77,Hebrew!$A:$S,13,0) -> רצועת עזה | R77: Post | S77: Text | T77: Journalistic Report, Journalists, Limiting Free Speech, Social Media | U77: IDF (Israel Defense Forces) | V77: Gaza Strip
A78: 1662 | B78: https://x.com/AssalRad/status/1799543857539108962 | C78: World coverage of Israel's rescue of four live hostages does not refer to hundreds of Palestinians killed in the event | D78: =VLOOKUP(A78,Hebrew!A:C,3,0) -> הכיסוי העולמי של חילוץ ארבעת חטופים חיים אינו מתייחס למאות הפלסטינים שנהרגו במהלך האירוע. | E78: Quoted reports regarding IDF operation to rescue 4 live hostages; none note the 200+ Palestinians killed during that event. | F78: =VLOOKUP($A78,Hebrew!$A:$S,4,0) -> דיווחים מצוטטים לגבי מבצע צה"ל לשחרור 4 חטופים חיים לא מציינים את 200+ הפלסטינים שנהרגו במהלך האירוע הזה. | G78: June 8, 2024 | H78: June 8, 2024 | I78: June 8, 2024 | J78: X | K78: Assal Rad (@AssalRad) | L78: =VLOOKUP($A78,Hebrew!$A:$S,9,0) -> Assal Rad (@AssalRad) | O78: English | P78: Gaza Strip | Q78: =VLOOKUP($A78,Hebrew!$A:$S,13,0) -> רצועת עזה | R78: Post | S78: Text, Photo | T78: Hostages, Civilians, Ground Operation, Media, Media bias | U78: Hamas, IDF (Israel Defense Forces) | V78: Gaza Strip
A79: 1663 | B79: https://x.com/Morpheus1099/status/1799407973791645979 | C79: Channel 13 journalist: Order exists to withhold Gaza bombing footage from Israeli public | D79: =VLOOKUP(A79,Hebrew!A:C,3,0) -> עיתונאית ערוץ 13: ישנה הוראה לא להראות לציבור בישראל צילומי תוצאות ההפצצות בעזה | E79: Hila Elroi on Channel 13 news admits that there exists an order not to expose Israelis to the results of Israel's bombing of Gaza. | F79: =VLOOKUP($A79,Hebrew!$A:$S,4,0) -> הילה אלרואי בחדשות ערוץ 13 מודה שיש הוראה לא לחשוף את הישראלים לתוצאות ההפצצות של ישראל על עזה. | G79: June 8, 2024 | H79: June 8, 2024 | I79: June 8, 2024 | J79: X | K79: Facism has won 2024 (@morpheus1099) | L79: =VLOOKUP($A79,Hebrew!$A:$S,9,0) -> Stop the Genocide (@morpheus1099) | M79: Reshet 13 | O79: Hebrew | P79: Gaza Strip | Q79: =VLOOKUP($A79,Hebrew!$A:$S,13,0) -> רצועת עזה | R79: Post | S79: Text, Video | T79: Media, Communication Blackout, Destruction, Propaganda, Censorship, Limiting Free Speech | U79: Hamas, IDF (Israel Defense Forces) | V79: Gaza Strip
A80: 1666 | B80: https://x.com/rafaelshimunov/status/1795813951940202938 | C80: Arrest of Palestinian Citizen in Israel after social media post expressing solidarity and sorrow following Rafah strike | D80: =VLOOKUP(A80,Hebrew!A:C,3,0) -> מעצר של אזרחית פלסטינית בישראל לאחר פוסט ברשתות החברתיות המביע סולידריות ועצב בעקבות הטבח ברפיח | E80: A Palestinian citizen of Israel was arrested following a social media post expressing solidarity with civilians in Gaza after the Rafah tent camp strike. Footage shows police arresting the woman, tying her hands with a ziptie, blindfolding her, and leading her from the police vehicle. | F80: =VLOOKUP($A80,Hebrew!$A:$S,4,0) -> מעצר אזרחית פלסטינית ישראלית בעקבות פוסט ברשתות החברתיות שמביע סולידריות עם אזרחים בעזה לאחר הטבח במחנה האוהלים ברפיח. צילומים מראים את המשטרה עוצרת את האישה, קושרת את ידיה עם אזיקון, מכסה את עיניה ומובילה אותה לרכב המשטרתי. | G80: May 29 2024 | H80: May 29, 2024 | I80: May 29, 2024 | J80: X | K80: Rafael Shimunov (@rafaelshimunov) | L80: =VLOOKUP($A80,Hebrew!$A:$S,9,0) -> רפאל שימונוב (@rafaelshimunov) | O80: Hebrew, Arabic | P80: Majd al-Krum | Q80: =VLOOKUP($A80,Hebrew!$A:$S,13,0) -> מג'ד אל-כרום | R80: Post | S80: Text, Video | T80: Palestinian Citizens of Israel, Social Media, Civilians, Limiting Free Speech, Abuse | U80: Israeli Police | V80: Israel
A81: 2109 | B81: https://x.com/AMokhallalati/status/1849082736402632878 | C81: Testimony from Kamal Adwan Hospital amid heavy bombardment | D81: =VLOOKUP(A81,Hebrew!A:C,3,0) -> עדות מבית החולים קמאל אדואן תחת הפצצות כבדות | E81: Orthopedic surgeon Dr. Mohammed Obeid, working with Doctors Without Borders, describes the dire humanitarian and medical crisis at Kamal Adwan Hospital in northern Gaza in a recorded testimony from October 22. He details the ongoing bombardment, overwhelmed facilities, and inability to treat many of the injured. (Dr. Obeid was later arrested by the IDF.) | F81: =VLOOKUP($A81,Hebrew!$A:$S,4,0) -> המנתח האורתופדי ד"ר מוחמד עבאיד, העובד עם רופאים ללא גבולות, מתאר את המשבר ההומניטרי והרפואי החמור בבית החולים קמאל עדואן בצפון עזה בעדות מוקלטת מ-22 באוקטובר. הוא מתאר הפצצות מתמשכות, משאבים מועטים, וחוסר היכולת לטפל בהרבה מהפצועים. (ד"ר עבאיד נעצר מאוחר יותר על ידי צה"ל.) | G81: October 23, 2024 | H81: October 22, 2024 | I81: October 22, 2024 | J81: X | K81: Ahmed El Mokhallati (@AMokhallalati) | L81: =VLOOKUP($A81,Hebrew!$A:$S,9,0) -> Ahmed El Mokhallati (@AMokhallalati) | N81: https://www.youtube.com/watch?v=qEp2wv7wNdU | O81: English | P81: Kamal Adwan Hospital | Q81: =VLOOKUP($A81,Hebrew!$A:$S,13,0) -> בית החולים כמאל עדואן | R81: Post | S81: Photo, Text | T81: Public Health, Healthcare Workers, Hospital, Bombing, Testimony, Air Strike, Blockade | U81: IDF (Israel Defense Forces), MSF - Médecins Sans Frontières (Doctors Without Borders) | V81: Kamal Adwan Hospital, North Gaza, Beit Lahiya | W81: Shimon Boker
A82: 2121 | B82: https://x.com/AbujomaaGaza/status/1846483876014703073 | C82: IDF detonates buildings in Jabaliya camp | D82: =VLOOKUP(A82,Hebrew!A:C,3,0) -> צה"ל מפוצץ בניינים במחנה ג'בליה | E82: IDF plants explosives in heart of Jabalyia camp, destroying tens of homes, many of them inhabited. | F82: =VLOOKUP($A82,Hebrew!$A:$S,4,0) -> צה"ל מטמין חומרי נפץ בלב מחנה ג'באליה, הורס עשרות בתים, רבים מהם מאוכלסים. | G82: October 16, 2024 | H82: October 16, 2024 | I82: October 16, 2024 | J82: X | K82: Motasem Dalloul (@abujoummaaGaza) | L82: =VLOOKUP($A82,Hebrew!$A:$S,9,0) -> Motasem Dalloul (@abujoummaaGaza) | O82: English | P82: Jabaliya | Q82: =VLOOKUP($A82,Hebrew!$A:$S,13,0) -> ג'באליה | R82: Post | S82: Text, Video | T82: Civilians, Destruction, Demolition, Explosives | U82: IDF (Israel Defense Forces) | V82: North Gaza, Gaza Strip, Jabaliya
A83: 2122 | B83: https://x.com/AbujomaaGaza/status/1849732808333287510 | C83: Updates on IDF attacks on Gaza October 25, 2024 | D83: =VLOOKUP(A83,Hebrew!A:C,3,0) -> עדכונים על התקפות צה"ל על עזה 25 באוקטובר 2024 | E83: Update on attacks throughout Gaza resulting in over 200 deaths of civilians. Paramedics and civil defence personnel required to surrender to IDF. Israeli forces reportedly surrounded Kamal Adwan Hospital and struck its oxygen plant leading to the deaths of patients in critical condition. | F83: =VLOOKUP($A83,Hebrew!$A:$S,4,0) -> עדכון על התקפות ברחבי עזה שגרמו ליותר מ-200 הרוגים אזרחיים. נדרשים פרמדיקים ואנשי הגנה אזרחית להיכנע לצה"ל. כוחות ישראליים דיווחו על כך שהקיפו את בית החולים קמאל אדואן ופגעו במפעל החמצן שלו, מה שהוביל למותם של מטופלים במצב קריטי. | G83: October 25, 2024 | H83: October 24, 2024 | I83: October 25, 2024 | J83: X | K83: Motasem Dalloul (@abujoummaaGaza) | L83: =VLOOKUP($A83,Hebrew!$A:$S,9,0) -> Motasem Dalloul (@abujoummaaGaza) | O83: English | P83: Kamal Adwan Hospital, Beit Lahiya, Jabalia, Khan Yunis | Q83: =VLOOKUP($A83,Hebrew!$A:$S,13,0) -> בית החולים כמאל עדואן, בית לאהיא, ג'באליה, חאן יונס | R83: Post | S83: Text | T83: Hospital, Forced Displacement, Children, Journalistic Report, Air Strike, Public Health, Bombing, Ground Operation | U83: Gaza Health Ministry, IDF (Israel Defense Forces) | V83: North Gaza, Khan Younis, The Indonesian Hospital, Kamal Adwan Hospital, Beit Lahiya, Jabaliya | W83: Dr Hussam Abu Safiya
A84: 2123 | B84: https://x.com/AbujomaaGaza/status/1853847622236418257 | C84: 61 killed in IDF attacks on Gaza since morning | D84: =VLOOKUP(A84,Hebrew!A:C,3,0) -> 61 נהרגו בהתקפות צה"ל על עזה מאז הבוקר | E84: Medical sources report that 61 killed in IDF attacks - 46 of them in Jabaliya, Beit Hanoun, and Beit Lahiya in northern Gaza. | F84: =VLOOKUP($A84,Hebrew!$A:$S,4,0) -> מקורות רפואיים מדווחים על 61 הרוגים בהתקפות צה"ל - 46 מהם בג'באליה, בית חנון ובית לאהיה בצפון עזה. | G84: November 5, 2024 | H84: November 5, 2024 | I84: November 5, 2024 | J84: X | K84: Motasem Dalloul (@abujoummaaGaza) | L84: =VLOOKUP($A84,Hebrew!$A:$S,9,0) -> Motasem Dalloul (@abujoummaaGaza) | O84: English | P84: Jabaliya, Beit Hamoun, Beit Lahiya | Q84: =VLOOKUP($A84,Hebrew!$A:$S,13,0) -> ג'באליה, בית חאנון, בית לאהיא | R84: Post | S84: Text, Photo | T84: Air Strike, Bombing, Civilians, Journalistic Report | U84: Gaza Health Ministry, IDF (Israel Defense Forces) | V84: North Gaza, Beit Lahiya, Khan Younis, Jabaliya
A85: 2124 | B85: https://x.com/AbujomaaGaza/status/1854253562190090316 | C85: A Gazan journalist describes how he is living | D85: =VLOOKUP(A85,Hebrew!A:C,3,0) -> עיתונאי מעזה מתאר כיצד הוא חי | E85: This the fifth location where the writer has taken shelter with his family and remaining siblings in dire conditions | F85: =VLOOKUP($A85,Hebrew!$A:$S,4,0) -> זה המקום החמישי שבו הסופר מצא מקלט עם משפחתו ואחיו הנותרים בתנאים קשים. | G85: November 6, 2024 | J85: X | K85: Motasem Dalloul (@abujoummaaGaza) | L85: =VLOOKUP($A85,Hebrew!$A:$S,9,0) -> Motasem Dalloul (@abujoummaaGaza) | O85: English | P85: Gaza Strip | Q85: =VLOOKUP($A85,Hebrew!$A:$S,13,0) -> רצועת עזה | R85: Post | S85: Text | T85: Children, Civilians, Water, Food, Forced Displacement, Sanitation, Genocide, Electricity, Humanitarian Crisis, Testimony, Destruction | V85: Gaza Strip
A86: 2126 | B86: https://x.com/AbujomaaGaza/status/1855212378335391870 | C86: Crisis at Kamal Adwan Hospital during the late 2024 military operation in North Gaza | D86: =VLOOKUP(A86,Hebrew!A:C,3,0) -> משבר בבית החולים כמאל עדואן במהלך מבצע צבאי בסוף 2024 בצפון עזה | E86: Dr Hussam abu Safieh reports on desperate medical crisis at Kamal Adwan hospital in wake of IDF incursion | F86: =VLOOKUP($A86,Hebrew!$A:$S,4,0) -> ד"ר חוסאם אבו ספיה מדווח על משבר רפואי נואש בבית החולים כמאל עדואן בעקבות חדירת צה"ל | G86: November 9, 2024 | H86: November 9, 2024 | I86: November 9, 2024 | J86: X | K86: Motasem Dalloul (@abujoummaaGaza) | L86: =VLOOKUP($A86,Hebrew!$A:$S,9,0) -> Motasem Dalloul (@abujoummaaGaza) | O86: Arabic | P86: Kamal Adwan Hospital | Q86: =VLOOKUP($A86,Hebrew!$A:$S,13,0) -> בית החולים כמאל עדואן | R86: Post | S86: Video, Text | T86: Civilians, Disease, Public Health, Healthcare Workers, Hospital, Medicine, Testimony | U86: Gaza Health Ministry, IDF (Israel Defense Forces) | V86: Kamal Adwan Hospital | W86: Dr Hussam Abu Safiya
A87: 2127 | B87: https://x.com/AbujomaaGaza/status/1859190079702405379 | C87: Report from Dr Hussam abu Safieh re deaths at Kamal Adwan hospital | D87: =VLOOKUP(A87,Hebrew!A:C,3,0) -> דוח מד"ר חוסאם אבו ספיה על מקרי המוות בבית החולים כמאל עדואן | E87: Dr Hussam abu Safieh reports that during the 24 hours between November 19-20 one person died of dehydration and the hospital received 17 cases of dehydration and malnutrition among children. | F87: =VLOOKUP($A87,Hebrew!$A:$S,4,0) -> ד"ר חוסאם אבו ספיה מדווח שבמהלך 24 השעות בין ה-19 ל-20 בנובמבר, אדם אחד מת מהתייבשות ובית החולים קיבל 17 מקרים של התייבשות ותת תזונה בקרב ילדים. | G87: November 20, 2024 | H87: November 19, 2024 | I87: November 20, 2024 | J87: X | K87: Motasem Dalloul (@abujoummaaGaza) | L87: =VLOOKUP($A87,Hebrew!$A:$S,9,0) -> Motasem Dalloul (@abujoummaaGaza) | O87: English | P87: Kamal Adwan Hospital | Q87: =VLOOKUP($A87,Hebrew!$A:$S,13,0) -> בית החולים כמאל עדואן | R87: Post | S87: Text, Video | T87: Public Health, Healthcare Workers, Journalistic report, Children, Civilians, Testimony, Malnutrition, Water | U87: Gaza Health Ministry | V87: Kamal Adwan Hospital, North Gaza | W87: Dr Hussam Abu Safiya
A88: 464 | B88: https://twitter.com/RamAbdu/status/1749971465422745729 | C88: Footage shows Israeli forces killing a Palestinian carrying a white flag. | D88: =VLOOKUP(A88,Hebrew!A:C,3,0) -> הצילומים מראים כוחות ישראליים הורגים פלסטיני שנושא דגל לבן. | E88: A Palestinian journalist documented the killing of 51-year-old Ramzi Abu Sahlool in the Mawasi area, on January 22, 2024. The incident occurred after residents were forced to flee from a zone previously declared safe by the Israeli military. Abu Sahlool, holding a white flag, was attempting to evacuate his family when he was shot and killed by Israeli forces. | F88: =VLOOKUP($A88,Hebrew!$A:$S,4,0) -> עיתונאי פלסטיני תיעד את הריגתו של רמזי אבו סהלול בן ה-51 באזור המוואסי, ב-22 בינואר 2024. האירוע התרחש לאחר שהתושבים נאלצו לברוח מאזור שהוכרז קודם לכן כבטוח על ידי הצבא הישראלי. אבו סהלול, שהחזיק בדגל לבן, ניסה לפנות את משפחתו כאשר נורה ונורה למוות על ידי כוחות ישראליים. | G88: January 24, 2024 | H88: January 22, 2024 | I88: January 22, 2024 | J88: X | K88: Ramy Abdu (@RamAbdu) | L88: =VLOOKUP($A88,Hebrew!$A:$S,9,0) -> Ramy Abdu (@RamAbdu) | M88: ITV News | O88: English, Arabic | P88: Al Mawasi | Q88: =VLOOKUP($A88,Hebrew!$A:$S,13,0) -> אל-מוואסי | R88: Post | S88: Text, Video | T88: Civilians, Murder, Rules of Engagement, War Crimes, Journalistic Report, Shooting | U88: IDF (Israel Defense Forces) | V88: Gaza Strip, Al Mawasi
A89: 465 | B89: https://twitter.com/RamAbdu/status/1764759225241129162 | C89: IDF soldiers mock blindfolded Palestinian detainees | D89: =VLOOKUP(A89,Hebrew!A:C,3,0) -> חיילי צה"ל לועגים למעוכבים פלסטינים עם כיסוי עיניים | E89: Female IDF soldiers shared a video showing blindfolded Palestinian detainees kneeling, while mocking them and accusing them of being "Islamic Jihad" or "Nukhba" members. They also ridiculed a detainee who urinated in his pants. | F89: =VLOOKUP($A89,Hebrew!$A:$S,4,0) -> חיילות צה"ל שיתפו סרטון המראה עצורים פלסטינים עם כיסוי עיניים, על ברכיהם, תוך כדי שחיילי צה"ל לועגים להם ומאשימים אותם בכך שהם חברים ב"ג'יהאד האסלאמי" או ב"נוחבה". הן גם לגלגו על עצור שהשתין במכנסיו. | G89: March 4, 2024 | J89: X | K89: Ramy Abdu (@RamAbdu) | L89: =VLOOKUP($A89,Hebrew!$A:$S,9,0) -> Ramy Abdu (@RamAbdu) | O89: English, Hebrew | Q89: =VLOOKUP($A89,Hebrew!$A:$S,13,0) -> 0 | R89: Post | S89: Text, Video | T89: Abuse, Captivity Conditions, Civilians, Collective Punishment, Dehumanization, Humiliation, Israeli Society, Torture, Social Media, Detention Center, Detainees | U89: IDF (Israel Defense Forces)
A90: 468 | B90: https://twitter.com/RamAbdu/status/1780281723424547297 | C90: Palestinian child tortured in IDF detention | D90: =VLOOKUP(A90,Hebrew!A:C,3,0) -> ילד פלסטיני עונה במעצר של צה"ל | E90: A Palestinian child, recently released from Israeli detention, testifies that he has been beaten with iron bars, stripped naked, subjected to relentless torture, and denied sleep. | F90: =VLOOKUP($A90,Hebrew!$A:$S,4,0) -> ילד פלסטיני, ששוחרר לאחרונה ממעצר ישראלי, מעיד כי הוכה עם מוטות ברזל, הופשט, עונה ללא רחמים, ונמנעה ממנו שינה. | G90: April 16, 2024 | J90: X | K90: Ramy Abdu (@RamAbdu) | L90: =VLOOKUP($A90,Hebrew!$A:$S,9,0) -> Ramy Abdu (@RamAbdu) | O90: English, Arabic | Q90: =VLOOKUP($A90,Hebrew!$A:$S,13,0) -> 0 | R90: Post | S90: Text, Video | T90: Abuse, Captivity Conditions, Children, Civilians, Collective Punishment, Humiliation, Torture, Testimony, Detention Center, War Crimes, Detainees | U90: Israeli Prison
A91: 469 | B91: https://twitter.com/RamAbdu/status/1781018819961454697 | C91: Two Palestinians die in detention; thousands forcibly disappeared. | D91: =VLOOKUP(A91,Hebrew!A:C,3,0) -> שניים פלסטינים מתים במעצר; אלפים נלקחו בכוח ונעלמו. | E91: Two detainees from Gaza have died in Israeli detention centers while being interrogated. Thousands of Palestinians have been forcibly disappeared with their fate unknown, amid frequent reports of dozens being killed inside Israeli prisons. | F91: =VLOOKUP($A91,Hebrew!$A:$S,4,0) -> שני עצורים מעזה מתו במרכזי מעצר ישראליים במהלך חקירתם. אלפי פלסטינים נלקחו בכוח ונעלמו, גורלם לא ידוע, על רקע דיווחים תכופים על עשרות שנרצחו בתוך בתי הכלא הישראלים. | G91: April 18, 2024 | J91: X | K91: Ramy Abdu (@RamAbdu) | L91: =VLOOKUP($A91,Hebrew!$A:$S,9,0) -> Ramy Abdu (@RamAbdu) | M91: Kan 11 | N91: https://www.kan.org.il/content/kan-news/defense/739774/#:~:text=%D7%A9%D7%A0%D7%99%20%D7%A2%D7%A6%D7%95%D7%A8%D7%99%D7%9D%20%D7%A2%D7%96%D7%AA%D7%99%D7%9D%20%D7%9E%D7%AA%D7%95%20%D7%91%D7%93%D7%A8%D7%9A%20%D7%9C%D7%9E%D7%AA%D7%A7%D7%9F%20%D7%9B%D7%9C%D7%99%D7%90%D7%94%20%D7%91%D7%99%D7%A9%D7%A8%D7%90%D7%9C%3B%20%D7%9C%D7%95%D7%97%D7%9E%D7%99%D7%9D%20%D7%9E%D7%99%D7%97%D7%99%D7%93%D7%94%20%D7%9E%D7%99%D7%95%D7%97%D7%93%D7%AA%20%D7%A0%D7%97%D7%A7%D7%A8%D7%95,-%D7%A9%D7%A0%D7%99%20%D7%A2%D7%A6%D7%95%D7%A8%D7%99%D7%9D%20%D7%A2%D7%96%D7%AA%D7%99%D7%9D&text=%D7%94%D7%9E%D7%A9%D7%98%D7%A8%D7%94%20%D7%94%D7%A6%D7%91%D7%90%D7%99%D7%AA%20%D7%94%D7%97%D7%95%D7%A7%D7%A8%D7%AA%20%D7%94%D7%97%D7%9C%D7%94%20%D7%91%D7%99%D7%9E%D7%99%D7%9D,%D7%97%D7%9E%D7%99%D7%A9%D7%99)%20%D7%91%D7%97%D7%93%D7%A9%D7%95%D7%AA%20%D7%94%D7%A2%D7%A8%D7%91%20%D7%91%D7%9B%D7%90%D7%9F%2011. | O91: English, Hebrew | Q91: =VLOOKUP($A91,Hebrew!$A:$S,13,0) -> 0 | R91: Post | S91: Text | T91: Captivity Conditions, Detention Center, Detainees | U91: IDF (Israel Defense Forces)
A92: 470 | B92: https://twitter.com/RamAbdu/status/1785074198844453223 | C92: Israeli soldiers take photographs while wearing Palestinian women's clothes in Gaza home | D92: =VLOOKUP(A92,Hebrew!A:C,3,0) -> חיילי צה"ל מצטלמים בזמן שהם לובשים בגדי נשים פלסטיניות בבית בעזה | E92: While over 10,000 women are reported killed, IDF soldiers dress in displaced Palestinian women's clothing and take photos. | F92: =VLOOKUP($A92,Hebrew!$A:$S,4,0) -> בעת שדווח על הריגת יותר מ-10,000 נשים, חיילי צה"ל מתלבשים בבגדי נשים פלסטיניות עקורות ומצלמים תמונות. | G92: April 30, 2024 | J92: X | K92: Ramy Abdu (@RamAbdu) | L92: =VLOOKUP($A92,Hebrew!$A:$S,9,0) -> Ramy Abdu (@RamAbdu) | O92: English | P92: Gaza Strip | Q92: =VLOOKUP($A92,Hebrew!$A:$S,13,0) -> רצועת עזה | R92: Post | S92: Text, Photo | T92: Women, War Crimes, Social Media, Sexual Violence, Humiliation, Civilians | U92: IDF (Israel Defense Forces) | V92: Gaza Strip
A93: 471 | B93: https://twitter.com/RamAbdu/status/1785941575157067916 | C93: Palestinian detainee recounts physical and mental abuse by IDF | D93: =VLOOKUP(A93,Hebrew!A:C,3,0) -> עציר פלסטיני מתאר התעללות פיזית ונפשית על ידי צה"ל | E93: Jamal al-Eissawi, a Palestinian recently released from IDF detention, recounts enduring relentless abuse, including humiliation, the stripping of dignity, beatings with iron rods, dog attacks, and various other forms of extreme torture and harassment. | F93: =VLOOKUP($A93,Hebrew!$A:$S,4,0) -> ג'מאל אל-עיסאווי, פלסטיני ששוחרר לאחרונה ממעצר צה"ל, מתאר חוויות של התעללות מתמשכת, כולל השפלה, שלילת כבוד, מכות עם מוטות ברזל, התקפות כלבים וצורות אחרות של עינויים והטרדות קשות. | G93: May 2, 2024 | J93: X | K93: Ramy Abdu (@RamAbdu) | L93: =VLOOKUP($A93,Hebrew!$A:$S,9,0) -> Ramy Abdu (@RamAbdu) | O93: English, Arabic | Q93: =VLOOKUP($A93,Hebrew!$A:$S,13,0) -> 0 | R93: Post | S93: Text, Video | T93: Abuse, Captivity Conditions, Civilians, Humiliation, Torture, Testimony, Detention Center, Detainees | U93: IDF (Israel Defense Forces)
A94: 425 | B94: https://twitter.com/AlonLeeGreen/status/1787892635186712737 | C94: IDF tank drives into Gaza signs and fires indiscriminately at the Rafah Crossing to Egypt | D94: =VLOOKUP(A94,Hebrew!A:C,3,0) -> טנק של צה"ל נכנס לרצועת עזה, חוצה את מעבר רפיח למצרים ויורה באקראי. | E94: IDF soldiers drive a tank into the Gaza sign near the arrivals building in the Rafah Crossing from Egypt, drive into a "I ❤️ Gaza" sign nearby, and record themselves firing indiscriminately from a tank at civilian structures in Gaza City. | F94: =VLOOKUP($A94,Hebrew!$A:$S,4,0) -> חיילי צה"ל נוהגים טנק לעבר שלט "עזה" ליד בניין ההגעה במעבר רפיח ממצרים, פוגעים בשלט "אני ❤️ עזה" הסמוך, ומקליטים את עצמם יורים באקראי מטנק לעבר מבנים אזרחיים בעיר עזה. | G94: March 7, 2024 | J94: X | K94: Alon-Lee Green (@AlonLeeGreen) | L94: =VLOOKUP($A94,Hebrew!$A:$S,9,0) -> אלון-לי גרין (@AlonLeeGreen) | O94: Hebrew | P94: Rafah | Q94: =VLOOKUP($A94,Hebrew!$A:$S,13,0) -> רפיח | R94: Post | S94: Text, Video | T94: Collective Punishment, Vandalism, Abuse, Infrastructure, Indiscriminate Shooting, Destruction, Israeli Soldier Movies | U94: IDF (Israel Defense Forces) | V94: Rafah
A95: 522 | B95: https://twitter.com/ireallyhateyou/status/1780222143445205191 | C95: A man wears a "May your village burn" t-shirt in Mishmar HaSharon | D95: =VLOOKUP(A95,Hebrew!A:C,3,0) -> גבר לובש חולצת טי עם הכיתוב "שיישרף לכם הכפר" במושב משמר השרון | E95: A picture taken by Haaretz journalist Niv Hadas documents a young man wearing a t-shirt bearing the slogan "may your village burn" in Mishmar HaSharon, at a place where many Arabs work. The man appears to belong to the religious right. | F95: =VLOOKUP($A95,Hebrew!$A:$S,4,0) -> תמונה שצולמה על ידי העיתונאי ניב הדס מהארץ מתעדת צעיר שלובש חולצה עם הסלוגן "שישרף לכם הכפר" במושב משמר השרון, במקום שבו עובדים רבים ערבים. נראה כי האיש שייך לזרם הדתי-ימני. | G95: April 16, 2024 | H95: April 16, 2024 | I95: April 16, 2024 | J95: X | K95: B.M. (@ireallyhateyou) | L95: =VLOOKUP($A95,Hebrew!$A:$S,9,0) -> B.M. (@ireallyhateyou) | N95: https://x.com/NivHadas/status/1780156825351905721 | O95: Hebrew, English | P95: Mishmar HaSharon | Q95: =VLOOKUP($A95,Hebrew!$A:$S,13,0) -> משמר השרון | R95: Post | S95: Photo | T95: Israeli Society, Incitement to Violence, Religious Right | V95: Israel
A96: 523 | B96: https://twitter.com/ireallyhateyou/status/1781995666593456397 | C96: Israel's Finance Minister Bezalel Smotrich interviews on Galatz stating that all Gazans are Nazis | D96: =VLOOKUP(A96,Hebrew!A:C,3,0) -> שר האוצר של ישראל, בצלאל סמוטריץ', מתראיין בגלצ ואומר שכל תושבי עזה נאצים. | E96: Israel's Finance Minister Bezalel Smotrich claims that all 2 million Gazans are Nazis "who want to slaughter, rape and murder every Jew". He adds that Israel must occupy Gaza until Hamas is defeated and replaced. | F96: =VLOOKUP($A96,Hebrew!$A:$S,4,0) -> שר האוצר של ישראל, בצלאל סמוטריץ', טוען שכל 2 מיליון תושבי עזה הם נאצים "שרוצים לשחוט, לאנוס ולרצוח כל יהודי". הוא מוסיף שישראל חייבת לכבוש את עזה עד שחמאס יובס ויוחלף. | G96: April 21, 2024 | H96: April 21, 2024 | I96: April 21, 2024 | J96: X | K96: B.M. (@ireallyhateyou) | L96: =VLOOKUP($A96,Hebrew!$A:$S,9,0) -> B.M. (@ireallyhateyou) | M96: Galey Tzahal | O96: Hebrew, English | P96: Israel | Q96: =VLOOKUP($A96,Hebrew!$A:$S,13,0) -> ישראל | R96: Post | S96: Audio | T96: Interview, Opinion, Collective Punishment, Dehumanization, Media | U96: Israeli Government | V96: Gaza Strip, Israel | W96: Bezalel Smotritch
A97: 883 | B97: https://twitter.com/tparsi/status/1774872023098888465 | C97: A survey of Israel's systematic violations of international humanitarian law | D97: =VLOOKUP(A97,Hebrew!A:C,3,0) -> סקר על ההפרות השיטתיות של ישראל את החוק ההומניטרי הבינלאומי | E97: Israel is breaking long-standing rules of war by attacking protected places like embassies and hospitals, blocking aid deliveries, and allegedly using starvation as a weapon - actions that may count as war crimes. These aren't accidental violations, but seem to be part of a deliberate attempt to ignore or change international laws, which is also backed by the US government. | F97: =VLOOKUP($A97,Hebrew!$A:$S,4,0) -> ישראל מפרה חוקי מלחמה ארוכי שנים על ידי תקיפת מקומות מוגנים כמו שגרירויות ובתי חולים, חסימת משלוחי סיוע, וככל הנראה שימוש ברעב כנשק - פעולות שעשויות להיחשב כפשעי מלחמה. אלו לא הפרות מקריות, אלא נראות כחלק מניסיון מכוון להתעלם או לשנות חוקים בינלאומיים, דבר שגם נתמך על ידי ממשלת ארצות הברית. | G97: April 1, 2024 | J97: X | K97: Trita Parsi (@tparsi) | L97: =VLOOKUP($A97,Hebrew!$A:$S,9,0) -> Trita Parsi (@tparsi) | O97: English | Q97: =VLOOKUP($A97,Hebrew!$A:$S,13,0) -> 0 | R97: Post | S97: Text, Photo | T97: Humanitarian Law, War Crimes, Analysis | U97: United States, Israeli Government | W97: Joe Biden, Benjamin Netanyahu
A98: 1020 | B98: https://x.com/AssalRad/status/1850360530730709105 | C98: Different UN officials warn of Gaza's annihilation but U.S. looks away | D98: =VLOOKUP(A98,Hebrew!A:C,3,0) -> פקידים שונים באומות המאוחדות מזהירים מפני השמדת עזה, אך ארצות הברית מסיטה את מבטה. | E98: UN agencies warn of catastrophic humanitarian crisis in Gaza, with reports of mass starvation, indiscriminate attacks, and potential ethnic erasure—while the U.S. ignores their pleas, undermining its own claims to uphold international law. | F98: =VLOOKUP($A98,Hebrew!$A:$S,4,0) -> סוכנויות האומות המאוחדות מזהירות על משבר הומניטרי קטסטרופלי בעזה, עם דיווחים על רעב המוני, התקפות אקראיות ופוטנציאל למחיקה אתנית—בעוד שהארצות הברית מתעלמת מהפניות שלהן, ומערערת את טענתה שהיא שומרת על החוק הבינלאומי. | G98: October 27, 2024 | J98: X | K98: Assal Rad (@AssalRad) | L98: =VLOOKUP($A98,Hebrew!$A:$S,9,0) -> Assal Rad (@AssalRad) | O98: English | P98: Gaza Strip | Q98: =VLOOKUP($A98,Hebrew!$A:$S,13,0) -> רצועת עזה | R98: Post | S98: Text | T98: Ceasefire, Humanitarian Law, War Crimes | U98: United States, Israeli Government, UN (United Nations), UNICEF (United Nations Children's Fund), OCHA (UN Office for the Coordination of Humanitarian Affairs) | V98: Gaza Strip
A99: 446 | B99: https://twitter.com/N12News/status/1780977153166688378 | C99: IDF drops fake bills depicting Sinwar as a mouse | D99: =VLOOKUP(A99,Hebrew!A:C,3,0) -> צה"ל מפיץ שטרות מזויפים שבהם סינוואר מאוייר כעכבר | E99: Palestinian sources state that the IDF distributed fake 20-shekel notes in Deir al-Balah, central Gaza, portraying Yahya Sinwar as a mouse and bearing the message, "Your money is with Sinwar." | F99: =VLOOKUP($A99,Hebrew!$A:$S,4,0) -> מקורות פלסטיניים מדווחים כי צה"ל הפיץ שטרות מזויפים של 20 שקלים בדיר אל-בלאח, במרכז עזה, בהם יחיא סינוואר מאויר כעכבר, ואשר נושאים את המסר: "הכסף שלכם אצל סינוואר." | G99: April 18, 2024 | J99: X | K99: N12 news (@N12News) | L99: =VLOOKUP($A99,Hebrew!$A:$S,9,0) -> N12 חדשות (@N12News) | O99: Hebrew | P99: Deir al-Balah | Q99: =VLOOKUP($A99,Hebrew!$A:$S,13,0) -> דיר אל-בלח | R99: Post | S99: Text, Photo | T99: Public Opinion, Occupied territories, Humiliation, Starvation, Dehumanization, Propaganda | U99: IDF (Israel Defense Forces) | V99: Deir al Balah | W99: Yahya Al-Sinwar
A100: 447 | B100: https://twitter.com/NABEELRAJAB/status/1750228266193969448 | C100: IDF soldiers celebrate demolishing Palestinian homes. | D100: =VLOOKUP(A100,Hebrew!A:C,3,0) -> חיילי צה"ל חוגגים הריסת בתים פלסטיניים. | E100: A video showing IDF soldiers enthusiastically celebrate as they demolish a large portion of Palestinian residential buildings. | F100: =VLOOKUP($A100,Hebrew!$A:$S,4,0) -> וידאו המראה חיילי צה"ל חוגגים בהתלהבות כאשר הם הורסים חלק נרחב מבנייני מגורים פלסטיניים. | G100: January 24, 2024 | J100: X | K100: Nabeel Rajab @NABEELRAJAB | L100: =VLOOKUP($A100,Hebrew!$A:$S,9,0) -> Nabeel Rajab @NABEELRAJAB | O100: English, Hebrew | P100: Gaza Strip | Q100: =VLOOKUP($A100,Hebrew!$A:$S,13,0) -> רצועת עזה | R100: Post | S100: Text, Video | T100: Infrastructure, Domicide, Abuse, Collective Punishment, Destruction, Dehumanization, Israeli Soldier Movies | U100: IDF (Israel Defense Forces) | V100: Gaza Strip
...

Sheet For_Fine_Tune
A1: Number | B1: Link | C1: Title | D1: Title (Hebrew) | E1: Description | F1: Description (Hebrew) | G1: published Date | H1: Event date from | I1: Event date to | J1: Platform | K1: Author | L1: Author (Hebrew) | M1: Source | N1: Reference | O1: Language | P1: Location | Q1: Location (Hebrew) | R1: Type | S1: Media | T1: Theme (tag) | U1: Places & Organizations (tag) | V1: Locations (tag) | W1: Figures (tag)
A2: 2384 | B2: https://www.undp.org/press-releases/new-un-report-impacts-war-have-set-back-development-gaza-much-69-years | C2: UNDP Report says development in Gaza went back by 69 years | D2: דו"ח חדש של UNDP אומר שחלה נסיגה של כ-69 שנים בהתפתחות עזה | E2: A new UN report highlights the severe impacts of war on Gaza's development, projecting a rise in poverty and a significant contraction in GDP and employment in the State of Palestine. | F2: דו"ח חדש מטעם ארגון הפיתוח של האו"ם קובעת שבלי הסרת המגבלות הכלכליות ואפשרות שיקום והשקעות בפיתוח, צפויה עלייה בעוני, צמצום בתמ"ג וברמת התעסוקה בכלכלה הפלסטינית | G2: October 22, 2024 | J2: UNDP (UN Development Programme) | K2: United Nations Development Programme | L2: תכנית הפיתוח של האו"ם (UNPD) | N2: https://www.undp.org/arab-states/publications/gaza-war-expected-socio-economic-impacts-state-palestine-october-2024 | O2: English | P2: Gaza Strip | Q2: רצועת עזה | R2: Official Report | S2: Text | T2: Economy, Humanitarian Aid, Blockade, Reconstruction | V2: Gaza Strip
A3: 2385 | B3: https://www.haaretz.co.il/opinions/2024-12-22/ty-article-opinion/.premium/00000193-ea47-d35c-a79f-fae7bf390000 | C3: Brigadier General Vach's Worldview is Known. Nonetheless, He was Charged with Commanding a Sensitive Area | D3: השקפת העולם של תא"ל ואך ידועה. למרות זאת הופקד על גזרה רגישה בעזה | E3: The opinion piece discusses the military actions in Gaza and the controversial decisions made by Brigadier General Yehuda Vach, despite the sensitivity of the situation. | F3: מאמר הדעה דן בפעילות הצבא ברצועת עזה וחילוקי הדעות סביב החלטות תא"ל וואך, למרות רגישות המצב | G3: December 22, 2024 | H3: August 7, 2024 | J3: Haaretz | K3: Yagil Levi | L3: יגיל לוי | N3: https://www.haaretz.co.il/news/magazine/2024-12-18/ty-article-magazine/.premium/00000193-d01a-dcf9-afbb-deff388f0000 | O3: Hebrew | P3: Netzarim Corridor | Q3: מסדרון נצרים | R3: Opinion | S3: Text | T3: Ethnic Cleansing, Rules of Engagement, Religious Right | U3: IDF (Israel Defense Forces) | V3: Netzarim Corridor
A4: 2386 | B4: https://reliefweb.int/report/occupied-palestinian-territory/israels-assault-foundations-international-law-must-have-consequences-un-experts | C4: UN: Israel must have consequnces for attacking humanitarian law | D4: האו"ם: על ישראל לשאת בשלכות של הפרת הדין הבינלאומי | E4: UN experts condemn Israel's violations of international law in the occupied Palestinian territory and call for accountability for crimes against humanity and war crimes. | F4: מומחי האו"ם מאשימים את ישראל בהפרת החוק הבינלאומי בשטחים הפלסטינים הכבושים וקוראים להכרה בפשעים נגד האנושות ופשעי מלחמה. | G4: December 30, 2024 | J4: ReliefWeb | K4: ReliefWeb | L4: ReliefWeb | N4: https://www.ohchr.org/en/press-releases/2024/12/israels-assault-foundations-international-law-must-have-consequences-un?sub-site=HRC | O4: English | P4: Gaza Strip | Q4: רצועת עזה | R4: Official Report | S4: Text | T4: Murder, Torture, Forced Displacement, Sexual Violence | V4: Kamal Adwan Hospital
A5: 2387 | B5: https://www.idi.org.il/articles/57946 | C5: Poll - 57.5% of Israeli Public Support Complete Hostage Deal in Return for End of War (Jan 2025) | D5: סקר דצמבר 2024: רוב הציבור (57.5%) תומך בעסקה כוללת לשחרור כול החטופים בתמורה לסיום המלחמה | E5: A survey conducted in December 2024 by the Israeli Democracy Institute shows public support for a comprehensive deal to release all captives in exchange for ending the war, with varying opinions across political spectrums. | F5: סקר שערך מכון הישראלי לדמוקרטיה מצא, בין שאר הנושאים, רוב גדול התומך בעסקה כוללת לשחרור החטיפים בתמורה לסיום המלחמה. | G5: January 15, 2025 | H5: 45658 | I5: January 8, 2025 | J5: The Israel Democracy Institute | K5: Prof. Tamar Herman, Dr. Lior Yohanani, Yaron Kaplan, Inna Orly Sapojnikov | L5: פרופ' תמר הרמן, ד"ר ליאור יוחנני, ירון קפלן, אינה אורלי ספוז'ניקוב | N5: https://dataisrael.idi.org.il | O5: Hebrew | P5: Israel | Q5: ישראל | R5: Analysis | S5: Text | T5: Hostage Deal, Ceasefire, Public Opinion, Israeli Society | U5: IDF (Israel Defense Forces) | V5: Israel
A6: 2388 | B6: https://www.mekomit.co.il/%d7%9c%d7%94%d7%a8%d7%95%d7%a1-%d7%90%d7%aa-%d7%94%d7%a9%d7%9c%d7%99%d7%97-%d7%9b%d7%9a-%d7%94%d7%97%d7%a8%d7%99%d7%91%d7%94-%d7%99%d7%a9%d7%a8%d7%90%d7%9c-%d7%90%d7%aa-%d7%9e%d7%aa%d7%a7%d7%a0%d7%99/ | C6: Israel's destruction of journalistic infrastructure in Gaza | D6: להרוס את השליח: כך החריבה ישראל את מתקני העיתונות בעזה | E6: Israel's destruction of media facilities in Gaza, as investigated by Forbidden Stories, highlights the challenges faced by journalists in reporting from the region. | F6: תחקיר של פורבידן סטוריז ושיחה מקומית בעקבות הפגיעה בעיתונאים ובמשרדיהם. | G6: June 26, 2024 | H6: October 7, 2023 | I6: June 25, 2024 | J6: Mekomit | K6: Léa Peruchon | L6: לאה פרושון | O6: Hebrew | P6: Gaza City | Q6: עיר עזה | R6: Journalistic report | S6: Text | T6: Media, Civilians, Air Strike, Rules of Engagement, Journalists, War Crimes | V6: Gaza City
A7: 2389 | B7: https://www.haaretz.co.il/news/magazine/2024-06-25/ty-article-magazine/.premium/00000190-4ac5-da42-a1ba-7fef27c50000 | C7: IDF reserve soldiers refusing to serve further tell their stories | D7: שלושה חיילי מילואים מספרים מדוע יסרבו לשרת בעזה גם אם ישלמו על כך | E7: Three reserve soldiers explain why they will refuse to serve in Gaza, even if they will face consequences. | F7: שלושה חיילי מילואים מסבירים מדוע חתמו על מכתב סירוב לשרת בעזה | G7: June 25, 2024 | H7: May 31, 2024 | J7: Haaretz | K7: Liza Rozovsky | L7: ליזה רוזובסקי | O7: Hebrew | P7: Gaza Strip | Q7: רצועת עזה | R7: Journalistic report | S7: Text | T7: War Crimes, Rules of Engagement, Ground Operation, Hostage Deal | U7: IDF (Israel Defense Forces) | V7: Gaza Strip
A8: 2390 | B8: https://zeteo.com/p/the-myth-of-human-shields-israel-gaza | C8: The Myth of Gaza's civilian population serving as human shields for Hamas | D8: המיתוס של 'מגינים אנושיים' | E8: The article debunks the 'human shields' claim used by Israel in Gaza conflicts, highlighting the impact on civilians and the misuse of the term by the Israeli military. | F8: המאמר חושף את השימוש לראה בטיעון 'מגינים אנושיים' בו משתמש הצבא הישראלי ברצועת עזה, וחושף את השפעתו על האוכלוסייה האזרחית | G8: September 30, 2024 | J8: Zeteo | K8: Muhammad Shehada | L8: מוחמד שחאדה | O8: English | P8: Gaza Strip | Q8: רצועת עזה | R8: Opinion | S8: Text | T8: Civilians, Rules of Engagement, Air Strike, Collective Punishment | V8: Gaza Strip
A9: 2391 | B9: https://www.gazahealthcareletters.org/usa-letter-oct-2-2024 | C9: Letter to US President Biden and Vice President Harris from 99 American physicians who volunteered in Gaza | D9: מכתב 99 רופאים שהתנדבו לשרת בעזה לנשיא ארה"ב ביידן ולסגניתו האריס | E9: American medical professionals who served in Gaza write an open letter to President Biden and Vice President Harris, urging for immediate action to prevent further catastrophe in Gaza and Israel. | F9: במכתב פתוח לנשיא ארה"ב ביידן ולסגניתו האריס פונים אנשי צוותי רפואה אמריקנים לפעול בדחיות למנוע המשך הקטקסטרופה בעזה ובישראל. | G9: October 2, 2024 | H9: October 7, 2023 | I9: 45566 | J9: Gaza Healthcare Letters | K9: American Medical Professionals who Served in Gaza | L9: צוותי רפואה אמריקנים שפעלו בעזה | O9: English | P9: Gaza Strip | Q9: רצועת עזה | R9: Open letter | S9: Text | T9: Civilians, Hospital, Public Health, Torture | U9: United States | V9: Gaza Strip | W9: Joe Biden, Kamala Harris
A10: 2392 | B10: https://www.haaretz.co.il/news/politics/2024-10-30/ty-article-magazine/.premium/00000192-de9d-d7b5-af97-ff9d2d0d0000 | C10: 100 dead in IDF attempt to kill a spotter | D10: איך אפשר להפציץ בניין על כל יושביו?: בבית לאהיא מחפשים ניצולים במבנה שקרס | E10: Residents and rescue workers search for survivors in a collapsed five-story building in Beit Lahia, northern Gaza Strip, following an explosion that occurred the previous morning. | F10: לפי הרשויות בעזה, כמאה בני אדם נהרגו ועוד עשרות נעדרים בתקיפת מבנה מגורים בן חמש קומות בבית לאהיא שאיכלס כ-200 איש. בצה"ל אומרים כי תצפיתן שהה על גג המבנה. אנשי שירותי ההצלה, המשיכו לנסות ולאתר ניצולים. | G10: October 30, 2024 | H10: October 29, 2024 | I10: October 29, 2024 | J10: Haaretz | K10: Jack Khoury | L10: ג'קי חורי | O10: Hebrew | P10: Beit Lahia | Q10: בית לאהיא | R10: Journalistic report | S10: Text | T10: Air Strike, Civilians | V10: Beit Lahiya
A11: 2393 | B11: https://www.theguardian.com/world/article/2024/jul/19/israel-gaza-war-polio-sewage-samples | C11: Polio virus found in Gaza sewage | D11: וירוס פוליו מדבק התגלה בדגימות ביוב בעזה | E11: Highly infectious poliovirus found in Gaza sewage samples, putting thousands at risk of contracting the disease due to poor sanitation and infrastructure conditions. | F11: וירוס פוליו מדבק התגלה בדגימות ביוב בעזה ומעמיד בסכנה אלפי תושבים בגלל תנאי היגיינה ותשתיות פגועים. | G11: July 19, 2024 | J11: The Guardian | K11: Agence France-Presse | L11: סוכנות הידיעות הצרפתית | O11: English | P11: Gaza Strip | Q11: רצועת עזה | R11: Journalistic report | S11: Text | T11: Water, Public Health | V11: Central Gaza Strip
A12: 2394 | B12: https://www.thenationalnews.com/news/mena/2024/06/21/israel-gaza-city-municipality-garage/ | C12: Israel killed water/environment engineer & municipality officials working to restore water supply in Gaza | D12: בתקיפה אווירית נהרגו מהנדסי מים ותשתיות נציגי העירייה שפעלו להחזיר לפעולה את אספקת המים | E12: An Israeli airstrike on a Gaza City municipal building kills at least five workers, including four preparing to restore drinking water wells, leading to significant destruction and impacting essential services in the war-torn enclave. | F12: בתקיפה אווירית ישראלית על בנין העירייה של עזה נהרגו לפחות ארבעה שעבדו על חידוש אספקת מים לבארות המים ובכך פגעו אנושות באספקת משאב חיוני בעזה הנצורה. | G12: June 21, 2024 | H12: June 21, 2024 | I12: June 21, 2024 | J12: The National | K12: Nagham Mohanna | L12: נאגהם מוחאנה | O12: English | P12: Gaza City | Q12: עיר עזה | R12: Journalistic report | S12: Text | T12: Air Strike, Civilians, Water | V12: Gaza City
A13: 2395 | B13: https://www.globaltimes.cn/page/202411/1322528.shtml | C13: Gazans boycott local markets due to exhorbitant food prices | D13: עזתים מחרימים שווקים מקומיים בשל הפקעת מחירים | E13: Markets in Gaza are empty as locals boycott due to soaring prices amid the conflict with Israel, leading to protests and accusations of price manipulation by traders. | F13: שווקים בעזה התרוקנו בשל חרם של העזתים במחאה על האשמת הסוחרים מחירים המופקעים | G13: November 6, 2024 | H13: November 5, 2024 | J13: Global Times | K13: Xinhua | L13: סוכנות הידיעות הסינית | O13: English | P13: Central Gaza; Southern Gaza | Q13: מרכז ודרום רצועת עזה | R13: Journalistic report | S13: Text | T13: Food, Humanitarian Aid | V13: Gaza Strip
A14: 2396 | B14: https://amp.cnn.com/cnn/2024/11/29/middleeast/gaza-bakery-crush-palestinians-killed-intl-latam | C14: 3 Palestinians crushed to death in line to get food | D14: בתור לאוכל נמחצו למוות אישה ושני ילדים פלסטינים | E14: Three Palestinians, including two children and a woman, were crushed to death outside a bakery in Gaza amid a worsening food crisis in the enclave. | F14: על רקע מצוקת המזון הגוברת ברצונת עזה נמחצו למוות אישה ושני ילדים פלסטינים בתור למאפיה. | G14: November 30 ,2024 | H14: November 29, 2024 | I14: November 29, 2024 | J14: CNN | K14: Abeer Salman; Mohammad Al Sawalhi; Ibrahim Dahman; Mitchell McCluskey | L14: אביר סלמאן, מוחמד אל-סוואלי, איברהים דמאן, מישל מק'לאסקי | O14: English | P14: Central Gaza | Q14: מרכז רצועת עזה | R14: Journalistic report | S14: Text | T14: Humanitarian Aid, Food, Civilians | V14: Central Gaza Strip
A15: 2397 | B15: https://thebaffler.com/latest/running-amok-turfah | C15: Dehumanizing social media posts by Israeli soldiers in Gaza | D15: דהומנציזציה של הפלסטינים מוצגת על ידי חיילים ישראלים בסרטונים במדיה החברתית | E15: The content discusses various disturbing behaviors exhibited by Israeli soldiers in Gaza, including destruction, looting, and disrespectful actions towards Palestinians. | F15: בסרטונים תכנים מטרידים של חיילי ישראל, כולל תיאורי הרס, ביזה והתנהגות לא מכובדת כלפי פלסטינים | G15: June 18, 2024 | J15: The Baffler | K15: Mary Turfah | L15: מרי טורפה | O15: English | P15: Gaza Strip | Q15: רצועת עזה | R15: Journalistic report | S15: Text | T15: Vandalism | U15: IDF (Israel Defense Forces) | V15: Gaza Strip
A16: 2398 | B16: https://www.haaretz.com/israel-news/2024-09-03/ty-article/.premium/israeli-army-reservists-assault-gazan-truck-drivers-working-for-aid-organizations/00000191-b71d-d13c-a39b-bf9d24710000 | C16: Israeli army reservist assault Gazan truck drivers working for aid organizations | D16: חיילי מילואים תוקפים נהגי משאיות עזתים העובדים עבור ארגוני סיוע | E16: Israeli army reservists assaulted Gazan truck drivers working for aid organizations, despite being cleared by Israel's security services. | F16: חיילי מילואים תוקפים נהגי משאיות עזתים העובדים עבור ארגוני סיוע למרות שיש להם אישור מכוחות הביטחון | G16: September 3, 2024 | H16: 45505 | J16: Haaretz | K16: Yaniv Kubovich | L16: יניב קובוביץ | O16: English | P16: Kerem Shalom Crossing | Q16: מעבר כרם שלום | R16: Journalistic report | S16: Text | T16: Humanitarian Aid, Civilians | U16: IDF (Israel Defense Forces) | V16: Kerem Shalom Crossing
A17: 2399 | B17: https://www.themarker.com/news/education/2024-09-30/ty-article/00000192-41e6-d07b-aff3-57e6401a0000 | C17: Israeli Ministry of Education Directorate of Religious Education calls for schools to celebrate killing of Hezbollah leader Hassan Nasrallah | D17: משרד החינוך קרא לבתי הספר לערוך הרקדות ומשלוחי מנות לתלמידים עקב חיסול נסראללה | E17: The Ministry of Education instructed religious state schools to hold dances and send food packages to students following the killing of Hezbollah leader Hassan Nasrallah, sparking debates within the religious community. | F17: מינהל החינוך הדתי במשרד החינוך, האחראי על הפיקוח על רבני בתי הספר הממלכתיים־דתיים, הנחה בתי ספר לערוך חגיגות לציון הרג מנהיג חיזבאללה. היו גורמים במשרד שמתחו ביקורת על המהלך | G17: September 30, 2024 | H17: September 29, 2024 | I17: September 29, 2024 | J17: The Marker | K17: Lior Dattel | L17: ליאור דטל | O17: Hebrew | P17: Israel | Q17: ישראל | R17: Journalistic report | S17: Text | T17: Israeli Society | V17: Israel | W17: Hassan Nasrallah
A18: 2400 | B18: https://www.haaretz.co.il/news/law/2024-09-23/ty-article/.premium/00000192-1b6b-d342-ab9f-df6b2b790000 | C18: Deputy Mayor of Jerusalem interrogated under suspicion of inciting to violence and terrorism | D18: סגן ראש העיר ירושלים נחקר בחשד להסתה לטרור לאחר שפרסם פוסטים נגד אונר"א | E18: Jerusalem's Deputy Mayor, Aryeh King, is under investigation for incitement to violence and terrorism after posting against the UN - Law and Crime | F18: סגן ראש העיר ירושלים נחקר בחשד להסתה לאלימות והסתה לטרור לאחר שפרסם פוסטים נגד אונר"א ועידוד לשריפת מבני אונר"א | G18: September 23, 2024 | H18: September 23, 2024 | J18: Haaretz | K18: Yael Freidson | L18: יעל פרידסון | O18: Hebrew | P18: Israel | Q18: ישראל | R18: Journalistic report | S18: Text | T18: Terrorism | U18: Israeli Police, UNRWA (The UN Relief and Works Agency for Palestine Refugees) | V18: Jerusalem
A19: 2401 | B19: https://www.nytimes.com/2024/10/14/world/middleeast/israel-gaza-military-human-shields.html | C19: Israeli Army uses Palestinian civilians as human shields in Gaza | D19: צה"ל משתמש באזרחים פלסטינים כמגינים חיים בעזה. | E19: Israeli soldiers have been accused of using Palestinians as human shields in Gaza, forcing them to carry out dangerous tasks, as reported by The New York Times. | F19: חיילי צה"ל לפי דיווח בניו יורק טיימס מאלצים אזרחים פלסטינים לשמש כמגינים חיים ולבצע משימות מסכנות חיים. | G19: October 14, 2024 | J19: The New York Times | K19: Natan Odenheimer; Bilal Shbair; Patrick Kingsley | L19: נתן אודנהיימר, בילאל שבאר, פטריק קינגסלי | O19: English | P19: Gaza Strip | Q19: רצועת עזה | R19: Journalistic report | S19: Text | T19: Ground Operation, Civilians | U19: IDF (Israel Defense Forces) | V19: Gaza Strip
A20: 2402 | B20: https://www.haaretz.co.il/news/magazine/2024-06-28/ty-article-magazine/.premium/00000190-5aa7-de5e-abd0-fbf704260000 | C20: A night with an IDF ghost unit that has been fighting in the Gaza Strip for eight months | D20: לילה עם יחידת רפאים של צה"ל, שנלחמת ברצועה כבר שמונה חודשים | E20: An article about a night with the IDF's Re'phaim unit, which has been fighting in the Gaza Strip for eight months. | F20: לילה עם יחידת רפאים של צה"ל, שמכונה גם היחידה הרב-ממדית, שתפקידה לאתר ולפגוע במחבלים בעומק שטח הלחימה באמצעות יכולות טכנולוגיות מתקדמות | G20: June 28,2024 | H20: June 21, 2024 | J20: Haaretz | K20: Yaniv Kubovich | L20: יניב קובוביץ | O20: Hebrew | P20: Gaza Strip | Q20: רצועת עזה | R20: Journalistic report | S20: Text | T20: Hostages | U20: IDF (Israel Defense Forces) | V20: Gaza Strip
A21: 2403 | B21: https://www.haaretz.co.il/news/politics/2024-10-16/ty-article/.premium/00000192-94aa-d9c2-a7f3-9cae337a0000 | C21: An invitation from Likud for an event in the Gaza border area was distributed under the title 'Preparing to settle in the Gaza region | D21: הזמנה מטעם הליכוד לאירוע בעוטף הופצה תחת הכותרת "נערכים להתיישב בחבל עזה" | E21: The Likud party has issued an invitation for an event in the Gaza envelope titled 'Preparing to settle in the Gaza Strip' with the participation of several Likud Knesset members. | F21: לפי ההזמנה, הליכוד יקים סוכה כחלק מ"עיר סוכות" בעוטף עזה של תנועת "נחלה", שפועלת להקמת מאחזים בלתי חוקיים בגדה. בהזמנה נכתב כי ח"כים מהליכוד צפויים להגיע | G21: October 16,2024 | J21: Haaretz | K21: Noa Spigel | L21: נועה שפיגל | O21: Hebrew | P21: Western Negev (Otef) | Q21: עוטף עזה | R21: Journalistic report | S21: Text | T21: Israeli Society, Settlements | V21: Western Negev (Otef) | W21: Benny Gantz, Benjamin Netanyahu
A22: 2404 | B22: https://www.mekomit.co.il/ps/141796/ | C22: The children of Gaza have started the school year amid destruction, loss, and uncertainty | D22: ילדי עזה החלו את שנת הלימודים בתוך חורבן, אובדן ואי ודאות | E22: Children in Gaza begin the school year amidst destruction and uncertainty, facing challenges in accessing education due to ongoing attacks and war aftermath. | F22: מורים ואנשי חינוך בעזה החרבה מנסים לספק לילדים תוכניות חינוכיות בכיתות, באוהלים או במבנים הרוסים, אך ספק אם התוכניות האלה ישרדו תחת ההתקפות המתמשכות והחורף המתקרב | G22: October 31, 2024 | J22: Mekomit | K22: Rawida Kamal Amar;Ivtisam Mahdi | L22: רווידה כמאל עמאר ואיבתיסאם מהדי | N22: https://www.ochaopt.org/content/reported-impact-snapshot-gaza-strip-29-october-2024 | O22: Hebrew | P22: Gaza Strip | Q22: רצועת עזה | R22: Journalistic report | S22: Text | T22: Scholasticide | V22: Gaza Strip
A23: 2405 | B23: https://www.kan.org.il/content/kan-news/defense/827036/ | C23: With the help of soldiers: This is how the right-wing activist managed to enter Netzarim | D23: תחקיר זמן אמת: בסיוע חיילים הצליחה פעילת הימין להיכנס לנצרים | E23: Israeli Right-wing settler activist Daniella Weiss enlisted the help of military forces stationed in and around the Gaza Strip to enter the territory despite it being declared a closed military zone. Weiss did so in preparation for establishing Jewish settlements in the Gaza Strip. | F23: רכב צבאי הסיע את דניאלה וייס, ממייסדות תנועת ההתיישבות, לתוך שטח צבאי סגור ברצועת עזה. שלטונות הצבא היו מודעים לכך. | G23: November 21, 2024 | H23: November 13, 2024 | J23: Kan 11 | K23: Avi Amit | L23: אבי עמית | O23: Hebrew | P23: Gaza Strip | Q23: רצועת עזה | R23: Journalistic report | S23: Text | T23: Religious Right, Settlements | U23: IDF (Israel Defense Forces) | V23: Gaza Strip
A24: 2406 | B24: https://www.haaretz.co.il/news/politics/2025-01-18/ty-article/00000194-784f-d739-a9b6-78ff31ab0000 | C24: Israel has committed to allowing reconstruction work in the Gaza Strip at the beginning of the first phase of the deal | D24: ישראל התחייבה לאפשר קיום עבודות לשיקום הרצועה בתחילת השלב הראשון של העסקה | E24: Israel committed to allowing infrastructure rehabilitation works in the Gaza Strip at the beginning of the first stage of the agreement, amidst the release of captives and ceasefire negotiations. | F24: במסגרת ההסכם יוקמו ערי קראוונים לתושבי הרצועה במימון בינלאומי. לאחר שהממשלה אישרה הלילה את העסקה, הודיע דובר משרד החוץ הקטארי כי הפסקת האש תיכנס לתוקף מחר ב-8:30. חמאס מחויב לשלוח לישראל היום את שמות שלוש החטופות הראשונות שישוחררו | G24: January 18, 2025 | J24: Haaretz | K24: Yaniv Kubovich, Yehonatan Lis | L24: יניב קובוביץ ויהונתן ליס | O24: Hebrew | P24: North Gaza Strip | Q24: צפון רצועת עזה | R24: Journalistic report | S24: Text | T24: Hostage Deal, Reconstruction, Ceasefire | U24: Qatar | V24: North Gaza
A25: 2407 | B25: https://www.nytimes.com/2024/11/19/world/middleeast/israel-5-million-dollars-hostage.html | C25: Netanyahu Offers $5 Million for Each Hostage Freed in Gaza | D25: נתניהו מציע 5 מיליון דולר עבור כל חטוף שישוחרר | E25: Israeli Prime Minister Netanyahu offers $5 million for each hostage freed in Gaza as part of efforts to secure their release amidst stalled cease-fire talks. | F25: נתניהו מציע פרס כספי עבור שחרור חטופים תוך שהוא דוחה הצעה להפסקת אש ומאיים להעניש מי שיפגע בחטופים. | G25: November 19, 2024 | J25: The New York Times | K25: Efrat Livni | L25: אפרת ליבני | O25: English | Q25: 0 | R25: Journalistic report | S25: Text | T25: Hostage Deal, Hostages | W25: Benjamin Netanyahu, Yoav Gallant
A26: 2408 | B26: https://www.ha-makom.co.il/idf-droppings/ | C26: Silent and suppressed refusal: Active-duty soldiers are no longer willing to keep fighting | D26: סרבנות שקטה ומושתקת: לוחמים בסדיר לא מוכנים יותר להמשיך להילחם | E26: Israeli soldiers in the Nahal Brigade express reluctance to continue fighting in Gaza due to mental and emotional strain, leading to a phenomenon of quiet refusal to engage in combat. | F26: מנח״ל ועד חטיבת הקומנדו, מגבעתי ועד הצנחנים - יותר ויותר לוחמים, מכלל יחידות החי״ר, מעידים שהשחיקה והאטימות של צה"ל לא הותירה להם ברירה אלא לסרב | G26: October 15, 2024 | J26: Ha-Makom | K26: Revital Hovel | L26: רביטל חובל | O26: Hebrew | Q26: 0 | R26: Journalistic report | S26: Text | T26: Israeli Society | U26: IDF (Israel Defense Forces)
A27: 2409 | B27: https://www.haaretz.co.il/news/politics/2024-08-02/ty-article/.premium/00000191-1442-db7e-a99d-1edabb590000 | C27: Senior negotiator: Security officials believe that Netanyahu is not interested in advancing a deal | D27: בכיר בצוות המו"מ: ראשי מערכת הביטחון מעריכים שנתניהו לא מעוניין לקדם עסקה | E27: Senior member of the negotiation team states that security system heads believe Netanyahu is not interested in advancing a deal. | F27: ידיעות על משבר ביחסים בין נתניהו למערכת הביטחון. במערכת הביטחון, וכן בארה"ב בקטאר ובמצרים, מעריכים כבר חודשים ארוכים כי נתניהו אינו מעוניין בעסקה. זאת, בין היתר כדי לשמור על שרידות הממשלה שלו. | G27: August 02, 2024 | J27: Haaretz | K27: Michael Houzertov, Yehonatan Lis, Bar Peleg | L27: מיכאל האוזר טוב, יהונתן ליס ובר פלג | O27: Hebrew | P27: Gaza Strip | Q27: רצועת עזה | R27: Journalistic report | S27: Text | T27: Hostage Deal | U27: Shin Bet | V27: Netzarim Corridor, Philadelphi Corridor | W27: Ronen Bar, Benjamin Netanyahu
A28: 2410 | B28: https://www.haaretz.co.il/news/politics/2025-01-19/ty-article/.premium/00000194-7d23-de1b-a9bd-7d67f9790000 | C28: The IDF and Shin Bet retrieved from the Gaza Strip the body of soldier Oron Shaul, who was killed in Operation Protective Edge in 2014 | D28: צה"ל ושב"כ חילצו מרצועת עזה את גופתו של החייל אורון שאול שנהרג במבצע צוק איתן ב-2014 | E28: IDF and Shin Bet extracted the body of soldier Oron Shaul, who was killed in Operation Protective Edge in 2014, from the Gaza Strip. | F28: גופתו של שאול נחטפה למנהרה בשג'אעייה לאחר שטיל RPG נורה על הנגמ"ש שבו היה עם חבריו. כוחות מיוחדים, בהם לוחמי שייטת 13, השתתפו בהשבתו לישראל. צה"ל: מחויבים להשיב גם את הדר גולדין ושאר החטופים | G28: January 19, 2025 | J28: Haaretz | K28: Michael Houzertov, Adi Hashmonai, Bar Peleg | L28: יניב קובוביץ, עדי חשמונאי ובר פלג | O28: Hebrew | Q28: 0 | R28: Journalistic report | S28: Text | T28: Hostages | U28: IDF (Israel Defense Forces)
A29: 2411 | B29: https://www.haaretz.co.il/gallery/media/2024-08-19/ty-article/.premium/00000191-69da-d12a-a3b5-7dff33f80000 | C29: The Srugim website published an article supporting Jewish terrorism against Palestinians | D29: אתר "סרוגים" פירסם מאמר שתומך בטרור יהודי נגד פלסטינים | E29: The news website Srugim published an article expressing support for Jewish terrorism against Palestinians. | F29: בתגובה למהומות המתנחלים בג'ית שבהן נורה פלסטיני למוות, פרסם סמנכ"ל "חוננו" לשעבר, אורי קירשנבום, באתר החדשות הדתי־לאומי "סרוגים", טור תחת הכותרת "דין ג'ית כדין רפיח": "שמישהו יסביר לי למה מה שנכון בעזה לא נכון בג'נין, בחברון ובשכם" | G29: August 19 2024 | J29: Haaretz | K29: Ido David Cohen | L29: עדו דוד כהן | O29: Hebrew | P29: West Bank | Q29: הגדה המערבית | R29: Journalistic report | S29: Text | T29: Religious Right | V29: West Bank, Zaytun Neighborhood
A30: 2412 | B30: https://www.haaretz.co.il/magazine/2024-10-10/ty-article-magazine/.highlight/00000192-70ab-d292-a392-78bfa8210000?utm_source=App_Share&utm_medium=Android_Native&utm_campaign=Share | C30: Netanyahu's government is not just allowing Jewish terrorism in the West Bank—it is funding it. Investigation | D30: ממשלת נתניהו לא סתם מאפשרת את הטרור היהודי בגדה. היא מממנת אותו. תחקיר | E30: An investigation into the funding of Jewish terrorism in the West Bank by the Netanyahu government. | F30: המתנחלים מדברים על זה במונחים של מהפכה: במקום התנחלויות מגודרות על הגבעות, הוקמו בתוך שבע שנים יותר מ–60 חוות שהשתלטו על מאות אלפי דונם בגדה. הפרויקט הנוסק הזה, שמתבסס על כוח עבודה של בני נוער שנפלטו ממסגרות, הפך למחולל המרכזי של אלימות נגד פלסטינים. והוא ממומן בעשרות מיליונים בידי המדינה | G30: October 10, 2024 | J30: Haaretz | K30: Hilo Glazer, Hafar Sheizaf | L30: הילו גלזר, הגר שיזף | O30: Hebrew | P30: West Bank | Q30: הגדה המערבית | R30: Journalistic report | S30: Text | T30: Religious Right, Settlements | U30: Israeli Government | V30: West Bank
A31: 2413 | B31: https://www.ynet.co.il/news/article/bkldluke1e#autoplay | C31: During a visit to the Civil Administration, Smotrich said he is working to shut it down: 'I spoke with Netanyahu' | D31: בביקור במנהל האזרחי אמר סמוטריץ' כי הוא פועל לסגור אותו: "דיברתי עם נתניהו | E31: Bezalel Smotrich, Minister of Treasury and Minister of Security, is working towards closing the Israeli Civil Administration in the West Bank, as part of a move to annex the territory to Israel de-facto. | F31: שר האוצר רוצה לנצל את מומנטום כניסת ממשל טראמפ, ולקדם את סיפוח יהודה ושומרון והחלת ריבונות על השטח. הכתבה מרחיבה על המשמעויות הדרמטיות של צעד כזה | G31: December 5, 2024 | J31: Ynet | K31: Elisha Ben-kimon | L31: אלישע בן קימון | O31: Hebrew | P31: West Bank | Q31: הגדה המערבית | R31: Journalistic report | S31: Text | T31: Religious Right, Annexation | U31: Israeli Government | V31: West Bank | W31: Bezalel Smotritch
A32: 2414 | B32: https://www.haaretz.co.il/news/politics/2025-01-09/ty-article/.premium/00000194-45b1-db19-abdd-6db7c86d0000 | C32: Ben Gvir demands that the police prioritize the demolition of illegal buildings that house families | D32: בן גביר דורש מהמשטרה לתעדף הריסת מבנים לא חוקיים שמאכלסים משפחות | E32: Minister Itamar Ben Gvir intervenes in the police enforcement policy regarding the demolition of illegal buildings housing families. | F32: השר לביטחון לאומי איתמר בן גביר התערב במדיניות האכיפה של המשטרה בהריסת מבנים לא חוקיים, והורה לבכירים בארגון לתעדף הריסת בתים המאוכלסים על ידי משפחות על אף שאין לו הסמכות לקבוע את מדיניות ההריסה | G32: January 9, 2025 | J32: Haaretz | K32: Josh Breiner | L32: יהושע (ג'וש) בריינר | O32: Hebrew | P32: Negev | Q32: נגב | R32: Journalistic report | S32: Text | T32: Religious Right | U32: Israeli Police | V32: Negev | W32: Itamar Ben-Gvir
A33: 2415 | B33: https://www.haaretz.co.il/news/politics/2024-10-30/ty-article/.premium/00000192-d9c2-d605-a3b2-dfc702430000 | C33: In the Shuafat refugee camp, residents do not believe that the authorities will take over UNRWA's role | D33: במחנה הפליטים שועפט לא מאמינים שהרשויות ייכנסו לנעלי אונר"א | E33: The article discusses the living conditions in the Shuafat refugee camp, managed by the UN agency UNRWA, and the potential legal implications of a recent law passed in the Knesset. | F33: כמו בהחלטות רבות שנוגעות לירושלים מאז 1967, גם החוק לסילוק אונר"א לא הגיע על רקע רצון לפתור בעיה כלשהי, להקל על תושבי ירושלים או לקדם עתיד טוב יותר. גם אם יש בעיות בסוכנות, לא מדובר בארגון טרור, אלא בארגון שמספק שירותים חיוניים למאות אלפי בני אדם | G33: October 30, 2024 | J33: Haaretz | K33: Nir Hasson | L33: ניר חסון | O33: Hebrew | P33: East Jerusalem | Q33: מזרח ירושלים | R33: Opinion | S33: Text | U33: UN (United Nations) | V33: Jerusalem
A34: 2416 | B34: https://www.haaretz.co.il/news/politi/2024-11-13/ty-article/.premium/00000193-24ee-d76b-afd7-a7ff70930000 | C34: Approved in a preliminary vote: The police will be able to access a computer or personal phone without the owner's knowledge | D34: אושר בטרומית: המשטרה תוכל לחדור למחשב או לטלפון אישי בלא ידיעת בעליו | E34: The Knesset approved a controversial bill allowing police officers to access personal computers or phones without the owner's knowledge, sparking opposition concerns about the legality of the process. | F34: מליאת הכנסת אישרה בקריאה טרומית הצעה, לפיה קצין בדרגת ניצב־משנה ומעלה יוכל לבקש אישור מנשיא בית המשפט המחוזי או מסגנו לחדור למחשבים אישיים ולהעתיק מהם חומרים, אם שוכנע שהפעולה נדרשת למניעת "פשע חמור". החוק לא יחול על עבירות שחיתות כגון שוחד, מרמה והפרת אמונים | G34: November 13, 2024 | J34: Haaretz | K34: Noa Shpigel | L34: נעה שפיגל | O34: Hebrew | P34: Israel | Q34: ישראל | R34: Journalistic report | S34: Text | T34: Civilians | U34: Israeli Police | V34: Israel
A35: 2417 | B35: https://www.lemonde.fr/en/les-decodeurs/article/2024/10/13/why-the-gaza-health-ministry-s-death-count-is-considered-reliable_6729264_8.html | C35: Study on MoH death toll being accurate | D35: מדוע נחשבים הנתונים שמספק משרד הבריאות הפלסטיני בעזה לגבי מספר המתים אמינים? | E35: The article discusses the reliability of the death count provided by the Gaza Health Ministry during the Israel-Gaza conflict, detailing the methodology used and the challenges faced in accurately reporting casualties. | F35: המאמר סוקר את חילוקי הדעות לגבי נתונים שמספק משרד הבריאות בעזה. במאמר נטען שהנתונים אמינים ומקובלים. | G35: October 13, 2024 | J35: Le Monde | K35: Assma Maad | L35: אסמה אעד | O35: English | P35: Gaza Strip | Q35: רצועת עזה | R35: Analysis | S35: Text | T35: Civilians | U35: Hamas, Gaza Health Ministry, IDF (Israel Defense Forces) | V35: Gaza Strip
A36: 2418 | B36: https://www.haaretz.co.il/news/law/2024-12-17/ty-article/00000193-d466-d4ec-a5d3-f57f62f00000 | C36: Israeli activists detained for painting a road in Jerusalem a year and a half ago | D36: פעילים ישראלים נעצרו על צביעת כביש בירושלים לפני שנה וחצי | E36: Two activists were detained for investigation on suspicion of painting a road in Jerusalem in protest over police brutality over a year ago. | F36: שני פעילים נעצרו לחקירה בחשד ששלפני יותר משנה צבעו כביש בירושלים במחאה נגד המהפכה המשטרית. | G36: December 17, 2024 | J36: Haaretz | K36: Bar Peleg | L36: בר פלג | O36: Hebrew | P36: Jerusalem | Q36: ירושלים | R36: Journalistic report | S36: Text | T36: Israeli Society, Vandalism, Protest (Israel) | V36: Jerusalem
A37: 2419 | B37: https://www.nytimes.com/2024/07/25/us/politics/harris-biden-netanyahu-meeting-israel.html?campaign_id=9&emc=edit_nn_20240726&instance_id=129819&nl=the-morning&regi_id=70279552&segment_id=173210&smid=url-share&te=1&user_id=2e28080c4831073bd853a843a6df3aec | C37: Harris Offers Support for Israel but Calls Out Palestinians’ Plight After Talk With Netanyahu | D37: הריס מציעה תמיכה לישראל אך מדגישה את מצוקתם של הפלסטינים לאחר שיחה עם נתניהו | E37: Vice President Kamala Harris expresses support for Israel's right to defend itself but also highlights the suffering of Palestinians during a meeting with Prime Minister Benjamin Netanyahu. | F37: סגנית הנשיא קמלה האריס מביעה תמיכה בזכותה של ישראל להגן על עצמה, אך גם מדגישה את הסבל של הפלסטינים במהלך פגישה עם ראש הממשלה בנימין נתניהו. | G37: July 25, 2024 | J37: The New York Times | K37: Peter Baker | L37: פיטר בייקר | O37: English | Q37: 0 | R37: Journalistic report | S37: Text | T37: Civilians, Hostages, Forced Displacement, Starvation | W37: Benjamin Netanyahu, Kamala Harris, Joe Biden
A38: 2420 | B38: https://www.wsj.com/world/middle-east/once-hamass-sworn-enemy-mohammed-dahlan-rises-as-a-postwar-strongman-f64676b1?ref=forever-wars.com | C38: Some U.S., Israeli and Arab officials see Palestinian Mohammed Dahlan as a viable leader of an interim security force | D38: כמה פקידים אמריקאים, ישראלים וערבים רואים את מוחמד דחלאן הפלסטיני כמנהיג אפשרי של כוח ביטחון זמני אחרי המלחמה. | E38: As part of discussions on the so-called "day after" in Gaza, U.S., Arab, and Israeli officials have proposed that Mohammed Dahlan, formerly head of the Palestinian Authority's security forces, be charged with security in the Gaza Strip, once the war is over. | F38: כחלק מהדיונים על מה שמכונה "היום שאחרי" בעזה, פקידים אמריקאים, ערבים וישראלים הציעו שמוחמד דחלאן, שהיה בעבר ראש כוחות הביטחון של הרשות הפלסטינית וחי כיום באבו דאבי, ימונה לאחראי על הביטחון ברצועת עזה, לאחר שהמלחמה תסתיים. | G38: July 25, 2024 | J38: The Wall Street Journal | K38: Summer Said, Fatima AbdulKarim, and Stephen Kalin | L38: סאמר סייד, פאטימה עבדולכרים, וסטיבן קלין | O38: English | Q38: רצועת עזה | R38: Journalistic report | S38: Text | U38: Hamas, United States
A39: 2421 | B39: https://time.com/7008717/benjamin-netanyahu-interview/ | C39: Bibi at war: Benjamin Netanyahu on Israel's historic crisis and his own | D39: ביבי במלחמה: בנימין נתניהו על המשבר ההיסטורי של ישראל ועל מדיניתו | E39: Benjamin Netanyahu's leadership during a time of conflict and criticism, with a focus on Israel's security challenges and international relations. | F39: הנהגת בנימין נתניהו בתקופה של סכסוך וביקורת, עם דגש על אתגרי הביטחון של ישראל ויחסים בינלאומיים. | G39: August 8, 2024 | J39: Time | K39: Eric Cortellessa | L39: אריק קורטלסה | O39: English | Q39: 0 | R39: Journalistic report | S39: Text | T39: Israeli Society, Hostages, Ground Operation, Ceasefire, Protest (International), Protest (Israel) | U39: Hamas, IDF (Israel Defense Forces) | W39: Benjamin Netanyahu, Antony Blinken
A40: 2422 | B40: https://www.theatlantic.com/international/archive/2024/09/israel-gaza-war-biden-netanyahu-peace-negotiations/679581/ | C40: Inside the year-long American effort to release the hostages, end the fighting in Gaza, and bring peace to the Middle East | D40: שנה של מאמץ אמריקאי לשחרר את בני הערובה, לסיים את הלחימה בעזה ולהביא שלום למזרח התיכון | E40: The article discusses the American effort to broker peace in the Middle East, focusing on the Biden administration's involvement during a conflict between Israel and Hamas. | F40: המאמר מספק תיאור כרונולוגי של המאמצים האמריקאיים לתווך שלום במזרח התיכון, תוך התמקדות במעורבות של ממשלת ביידן במהלך הסכסוך בין ישראל לחמאס. | G40: September 25, 2024 | J40: The Atlantic | K40: Franklin Foer | L40: פרנקלין פויר | O40: English | P40: North Gaza | Q40: צפון רצועת עזה | R40: Journalistic report | S40: Text | T40: Hostages, Iron Dome, Air Strike | U40: IDF (Israel Defense Forces) | V40: North Gaza | W40: Benny Gantz, Benjamin Netanyahu, Antony Blinken, Joe Biden, Yoav Gallant, Hassan Nasrallah, Yahya Al-Sinwar, Mohammed bin Salman Al Saud
A41: 2423 | B41: https://www.mekomit.co.il/ps/143011/ | C41: In the besieged Beit Lahia, rotting bodies are scattered among the ruins | D41: בבית לאחיא הנצורה, גופות מרקיבות מפוזרות בין ההריסות | E41: The article describes the dire situation in Beit Lahia, Gaza, where residents face continuous Israeli bombardment, food and water shortages, and deteriorating living conditions. | F41: המאמר מתאר את המצב הקשה בבית לאהיא, עזה, שבו התושבים מתמודדים עם הפצצות ישראליות מתמשכות, מחסור במזון ובמים, ותנאי חיים מתדרדרים. | G41: December 1, 2024 | J41: Mekomit | K41: Ibrahim Mohammad | L41: איברהים מוחמד | O41: Hebrew | P41: Beit Lahiya | Q41: בית לאהיא | R41: Journalistic report | S41: Text | T41: Urbicide, Hospital, Forced Displacement, Air Strike | U41: IDF (Israel Defense Forces) | V41: Beit Lahiya
A42: 2424 | B42: https://www.dropsitenews.com/p/death-march-from-beit-lahia | C42: Death march from Beit Lahia | D42: מצעד המוות מבית לאהיא | E42: Hossam Shabat reports on Israel's mass expulsion campaign in Beit Lahia, Gaza, forcing thousands of Palestinians to flee under heavy artillery shelling and gunfire. | F42: חוסאם שבת מדווח על הגירוש ההמוני מבית לאהיא, עזה, תחת הפגזות ארטילריה כבדות וירי. | G42: December 5, 2024 | J42: Drop Site News | K42: Hossam Shabat | L42: חוסאם שבת | O42: English | P42: Beit Lahiya | Q42: בית לאהיא | R42: Journalistic report | S42: Text | T42: Civilians, Journalists, Forced Displacement, Blockade, Ground Operation, Air Strike | U42: IDF (Israel Defense Forces) | V42: North Gaza, Kamal Adwan Hospital , The Indonesian Hospital, Jabaliya, Beit Lahiya
A43: 2425 | B43: https://www.haaretz.co.il/news/politics/2024-12-24/ty-article/00000193-f900-d10a-a797-fb6bab660000 | C43: IDF attacks on hospitals late Dec | D43: דיווחים פלסטיניים: צה"ל מגביר את התקיפות על בתי חולים בצפון הרצועה ומפנה בכוח מטופלים | E43: Reports from Palestinian sources indicate that the Israeli military is intensifying attacks on hospitals in the northern Gaza Strip, forcibly evacuating patients and causing damage. | F43: דיווחים פלסטיניים מצביעים על כך שהצבא הישראלי מגביר את התקפותיו על בתי חולים בצפון רצועת עזה, מפנה בכוח מטופלים וגורם נזק. | G43: December 24, 2024 | J43: Haaretz | K43: Rawan Suleiman, Jack Khoury | L43: רואן סלימאן, ג'קי חורי | O43: Hebrew | P43: North Gaza | Q43: צפון רצועת עזה | R43: Journalistic report | S43: Text | T43: Hospital, Air Strike | U43: Hamas, IDF (Israel Defense Forces) | V43: Kamal Adwan Hospital, The Indonesian Hospital, Gaza City
A44: 2426 | B44: https://www.israelhayom.com/2025/01/02/knesset-committee-pushes-for-controversial-generals-plan-in-gaza/ | C44: Controversial 'Generals' Plan' in northern Gaza picks up steam | D44: תוכנית ה'גנרלים' השנויה במחלוקת בצפון עזה צוברת תאוצה | E44: Members of the Knesset Foreign Affairs and Defense Committee demand that the Israeli Ministry of Defence implement the so-called "Generals' Plan," which includes the forced evacuation of civilians and the deprivation of energy, food, and water, in northern Gaza. | F44: חברי ועדת החוץ והביטחון של הכנסת דורשים ממשרד הביטחון הישראלי ליישם את מה שמכונה "תוכנית הגנרלים", הכוללת פינוי כפוי של אזרחים ושלילת אנרגיה, מזון ומים בצפון עזה. | G44: January 2, 2025 | J44: Israel Hayom | K44: Shirit Avitan Cohen | L44: שירית אביטן כהן | O44: English | P44: North Gaza | Q44: צפון רצועת עזה | R44: Journalistic report | S44: Text | T44: Civilians, Food, Forced Displacement, Water | U44: Hamas, IDF (Israel Defense Forces) | V44: North Gaza
A45: 2427 | B45: https://www.ynet.co.il/news/article/bkcljlrdyx#autoplay | C45: Harvard and antisemitism - recompensation | D45: פשרת הרווארד ואנטישמיות - פיצוי | E45: Harvard University has reached a settlement with Jewish students and the Brandeis Center for Human Rights over allegations of failing to address campus antisemitism. The agreement includes compensation, adopting IHRA's antisemitism definition, and establishing partnerships with Israeli universities. | F45: אוניברסיטת הרווארד הגיעה להסכם עם סטודנטים יהודים ומרכז ברנדייס לזכויות האדם בעקבות האשמות על כך שלא טיפלה באנטישמיות בקמפוס. ההסכם כולל פיצוי, אימוץ ההגדרה של IHRA לאנטישמיות, והקמת שותפויות עם אוניברסיטאות ישראליות. | G45: January 22, 2025 | J45: Ynet | K45: Daniel Adelson | L45: דניאל אדלסון | O45: Hebrew | P45: United States | Q45: ארה"ב | R45: Journalistic report | S45: Text | T45: Antisemitism, Academia | U45: United States | V45: USA
A46: 2428 | B46: https://www.nytimes.com/2024/12/22/us/gaza-war-campuses-middle-ground.html?unlocked_article_code=1.jU4.Vrl4.tuL9laa9sjOB | C46: College students and faculty members are seeking space for nuanced perspectives on the Israel-Hamas war on deeply divided campuses | D46: סטודנטים ואנשי סגל במכללות מחפשים מרחב לדעות מורכבות על מלחמת ישראל-חמאס בקמפוסים המפולגים עמוקות. | E46: The article discusses efforts by college students and faculty to create space for nuanced perspectives on the Israel-Hamas war amidst campus divisions. | F46: המאמר דן במאמצים של סטודנטים ואנשי סגל במכללות ליצור מרחב לדעות מורכבות על מלחמת ישראל-חמאס על רקע הפיצולים בקמפוסים. | G46: December 22, 2024 | J46: The New York Times | K46: Sharon Otterman | L46: שרון אוטרמן | O46: English | P46: United States | Q46: ארה"ב | R46: Journalistic report | S46: Text | T46: Public Opinion, Academia, Protest (International) | V46: USA
A47: 2429 | B47: https://www.makorrishon.co.il/news/808697/ | C47: Professor from Tel Aviv University accused Israel of war crimes | D47: פרופסור מאוניברסיטת תל אביב האשים את ישראל בפשעי מלחמה | E47: CAMERA On Campus, an organization monitoring speech on university campuses in the US and Israel, clandestinely recorded a student-organized conversation about the situation in Gaza with Israeli Professor Idan Landau at Tel Aviv University and provided the right-wing newspaper Makor Rishon with the recordings, claiming that Prof. Landau baselessly accused Israel of war crimes in Gaza. | F47: CAMERA בקמפוס, ארגון המנטר את השיח בקמפוסים אוניברסיטאיים בארצות הברית ובישראל, הקליט בסתר שיחה מאורגנת על ידי סטודנטים על המצב בעזה עם הפרופסור הישראלי עידן לנדו באוניברסיטת תל אביב וסיפק לעיתון הימני "מקור ראשון" את ההקלטות, וטען כי פרופ' לנדו האשים את ישראל ללא בסיס בפשעי מלחמה בעזה. | G47: January 14, 2025 | H47: December 19, 2024 | I47: December 19, 2024 | J47: Makor Rishon | K47: Avigail Zait | L47: אביגיל זית | O47: Hebrew | Q47: 0 | R47: Journalistic report | S47: Text | T47: Crimes Against Humanity, Academia | U47: Hamas, IDF (Israel Defense Forces)
A48: 2430 | B48: https://13tv.co.il/item/news/domestic/crime-and-justice/c8nmb-904430163/ | C48: 70 people admitted they pretended to be October 7 victims | D48: 70 אנשים הודו שהם העמידו פנים שהם קורבנות של ה-7 באוקטובר | E48: Dozens of suspects are being investigated for falsely claiming to be victims of a massacre at the 'Supernova Sukkot Gathering' (Nova) festival near Kibbutz Re'im and Gaza border communities on October 7th. Investigators suspect fraudulent claims of trauma and are considering filing charges against them. | F48: עשרות חשודים נמצאים בחקירה על כך שטוענים שהם קורבנות הטבח במפגש 'סופרנובה סוכות' (נובה) ליד קיבוץ רעים וקהילות בגבול עזה ב-7 באוקטובר. החוקרים חושדים בטענות שקריות על טראומה כדי לקבל מענק מביטוח לאומי ושוקלים להגיש נגדם כתבי אישום. | G48: January 22, 2025 | J48: Reshet 13 | K48: Eli Senior, Aviad Glickman | L48: אלי סניור, אביעד גליקמן | O48: Hebrew | Q48: 0 | R48: Journalistic report | S48: Text | T48: Israeli Society | U48: Israeli Police
A49: 2431 | B49: https://www.insidehighered.com/news/faculty-issues/academic-freedom/2025/01/05/aha-convention-attendees-oppose-scholasticide-gaza | C49: Historians Condemn ‘Scholasticide’ in Gaza at Conference | D49: כנס היסטוריונים מגנה את השמדת הידע והחינוך בעזה | E49: American Historical Association members at the annual conference vote to oppose 'scholasticide' in Gaza and U.S. funding of Israel's war, calling for a permanent ceasefire and support for Gaza's educational infrastructure. | F49: חברי האגודה ההיסטורית האמריקאית בכנס השנתי הצביעו נהשמדת הידע והחינוך בעזה ומימון המלחמה של ישראל על ידי ארצות הברית, וקוראים להפסקת אש קבועה ולתמיכה בתשתית החינוכית של עזה. | G49: January 5, 2025 | J49: Inside Higher Ed | K49: Ryan Quinn | L49: ראיין קווין | O49: English | Q49: 0 | R49: Journalistic report | S49: Text | T49: Scholasticide, Academia, Education, Schools | U49: UN (United Nations), IDF (Israel Defense Forces)
A50: 2432 | B50: https://www.haaretz.co.il/news/magazine/2024-12-17/ty-article-magazine/.premium/00000193-cf48-dcad-adfb-efeac1eb0000 | C50: An ally of Ben Gvir and a criminal suspect: It turns out that the dominant figure in the police is the Commissioner of the Israel Prison Service | D50: בן גביר וחשוד בפשע: מתברר שהדמות הדומיננטית במשטרה היא המפקח על שירות בתי הסוהר הישראלי קובי יעקבי. | E50: A drama unfolds in the office of the Minister of National Security, Itamar Ben Gvir, involving a refusal by a police commander to accompany him to the Temple Mount, revealing power struggles within the police force. | F50: דרמה במשרדו של שר הביטחון הלאומי, איתמר בן גביר, עם סירובו של מפקד משטרה ללוות אותו להר הבית, חושפת מאבקים על סמכויות בתוך כוחות המשטרה. | G50: December 17, 2024 | J50: Haaretz | K50: Josh Breiner | L50: יהושע (ג'וש) בריינר | O50: Hebrew | P50: Jerusalem | Q50: ירושלים | R50: Journalistic report | S50: Text | U50: Israeli Police, Israeli Prison | V50: Jerusalem | W50: Kobi Yaakobi
A51: 354 | B51: https://x.com/IamIbrahim21/status/1797521016702550496 | C51: Family forced by conditions to move from tent and seek refuge in rental apartment | D51: משפחה שנאלצה בעקבות הנסיבות לעזוב את האוהל ולחפש מקלט בדירה שכורה | E51: Family forced to seek accommodation in a burned rental unit after displacement for 1200 NIS ($330), since they cannot tolerate the conditions in the so-called safe areas. | F51: משפחה נאלצה לעזוב את האוהל ולחפש מגורים בשכירות בדירה שרופה ב-1200 ש"ח (330$), בגלל התנאים הקשים באזורים המוגדרים בטוחים. | G51: June 3, 2024 | H51: June 3, 2024 | I51: June 3, 2024 | J51: X | K51: Ibrahim Massri (@IamIbrahim21) | L51: Ibrahim Massri (@IamIbrahim21) | O51: English | P51: Khan Younis | Q51: חאן יונס | R51: Post | S51: Text, Photo | T51: Forced Displacement, Disease, Testimony | V51: Khan Younis
A52: 355 | B52: https://x.com/JalalAK_jojo/status/1797296916763418747 | C52: Footage of IDF drone attack on Gaza | D52: תיעוד של מתקפת רחפן של צה"ל על עזה | E52: Drone attack on Gaza recorded by IDF soldiers. The drone was downed and its footage was broadcast on Al Jazeera | F52: התקפת רחפן על עזה תועדה על ידי חיילי צה"ל. הרחפן הופל והצילומים שלו שודרו על ידי אל ג'זירה. | G52: June 2, 2024 | H52: May 27, 2024 | I52: May 27, 2024 | J52: X | K52: Jalal (@JalalAK_jojo) | L52: Jalal (@JalalAK_jojo) | O52: English | P52: Gaza Strip | Q52: רצועת עזה | R52: Post | S52: Video, Text | T52: Bombing, Air Strike, Drone / Quadcopter | U52: IDF (Israel Defense Forces) | V52: Gaza Strip
A53: 356 | B53: https://x.com/KhaledYousry22/status/1798729352412319874 | C53: Itamar Ben-Gvir declares intent to resettle Gaza and clear it of Palestinians | D53: איתמר בן-גביר מכריז על כוונה ליישב מחדש את עזה ולפנות אותה מפלסטינים | E53: Itamar Ben-Gvir declares intent to clear Gaza of Palestinians, in order to occupy it and establish settlements. | F53: איתמר בן גביר מכריז על כוונה לפנות את עזה מפלסטינים, במטרה לכבוש אותה ולהקים בה יישובים. | G53: June 6, 2024 | H53: June 6, 2024 | I53: June 6, 2024 | J53: X | K53: Khaled Yousry (@KhaledYousry22) | L53: Khaled Yousry (@KhaledYousry22) | O53: English, Arabic | P53: Israel | Q53: ישראל | R53: Post | S53: Text, Video | T53: Ethnic Cleansing, Incitement to Genocide, Annexation, Forced Displacement, Settlements | U53: Israeli Government | V53: Israel | W53: Itamar Ben-Gvir
A54: 357 | B54: https://x.com/N12News/status/1798769743119167566 | C54: Bezalel Smotrich calls for return to Gush Katif | D54: בצלאל סמוטריץ' קורא לשוב לגוש קטיף | E54: Bezalel Smotrich calls for return to Gush Katif in a ceremony at Merkaz HaTora veHaAretz. | F54: בצלאל סמוטריץ' קורא לשוב לגוש קטיף בטקס במרכז התורה והארץ. | G54: June 6, 2024 | H54: June 6, 2024 | I54: June 6, 2024 | J54: X | K54: N12 news (@N12News) | L54: N12 חדשות (@N12News) | O54: Hebrew | P54: Israel | Q54: ישראל | R54: Post | S54: Video, Text | T54: Religious Right, Ethnic Cleansing, Forced Displacement, Settlements, Annexation | U54: Israeli Government, IDF (Israel Defense Forces) | V54: Israel | W54: Bezalel Smotritch
A55: 358 | B55: https://x.com/YehudaShaul/status/1737112308672016760 | C55: Incitement to racism at events for IDF soldiers | D55: אמנים המופיעים בפני חיילי צה"ל מחזקים מגמות של הסתה, גזענות ופוליטיקה קיצועית | E55: A 19-tweet thread that includes several cases of artists appearing before IDF troops strengthen existing trends of racism and extremism. Increased calls for restablishment of settlements in Gaza. The thread also includes additional examples of racism and dehumanizaiton, as well as hoping to hit innocent people in Gaza. | F55: שרשור של 19 ציוצים שכולל מספר מקרים של אמנים המופיעים בפני חיילי צה"ל ומחזקים מגמות קיימות של גזענות וקיצוניות וקריאות לשוב ולהקים התנחלויות בעזה. השרשור כולל דוגמאות נוספות לגזענות ולדה-הומניזציה, כמו גם תקוות לפגוע באנשים חפים מפשע בעזה. | G55: December 19, 2023 | J55: X | K55: Yehuda Shaul (@YehudaShaul) | L55: יהודה שאול (@YehudaShaul) | O55: English, Hebrew | P55: Gaza Strip | Q55: רצועת עזה | R55: Post | S55: Text, Video | T55: Annexation, Incitement to Genocide, Racism, Abuse, Humiliation, Israeli Soldier Movies, Jewish Settlements in Gaza | U55: IDF (Israel Defense Forces) | V55: Gaza Strip
A56: 359 | B56: https://x.com/abierkhatib/status/1793720981607071831 | C56: IDF soldier filmed vandalizing school property in Gaza | D56: חייל צה"ל תועד משחית רכוש בית ספר בעזה | E56: Israeli soldier filming himself in an elementary school smashing certificates honouring talented students in Gaza, while also declaring the intention to return to Gush Katif and resettle Gaza. | F56: חייל ישראלי מצלם את עצמו בבית ספר יסודי כשהוא הורס תעודות המוקירות תלמידים מוכשרים בעזה, תוך כדי שהוא מכריז על כוונתו לחזור לגוש קטיף וליישב מחדש את עזה. | G56: May 23, 2024 | J56: X | K56: Abier (@abierkhatib) | L56: Abier (@abierkhatib) | O56: English, Hebrew | P56: Gaza Strip | Q56: רצועת עזה | R56: Post | S56: Video, Text | T56: Education, Abuse, Scholasticide, Children, Israeli Soldier Movies, Vandalism, Schools, Jewish Settlements in Gaza | U56: IDF (Israel Defense Forces) | V56: Gaza Strip
A57: 361 | B57: https://x.com/marcowenjones/status/1795063041513402446 | C57: Confusion regarding IDF's messaging on safe zones in Gaza | D57: חוסר בהירות לגבי המסרים של צה"ל על אזורי בטיחות בעזה | E57: IDF maps of "safe zones" in Gaza are imprecise, with animations expanding areas and creating confusion for civilians. Marc Owen Jones highlights inconsistencies and unclear boundaries. | F57: מפות צה"ל של "אזורי בטיחות" בעזה אינן מדויקות, עם אנימציות שמרחיבות אזורים ויוצרות בלבול אצל אזרחים. מארק אוון ג'ונס מדגיש חוסר עקביות וגבולות לא ברורים. | G57: May 22, 2024 | H57: May 22, 2024 | I57: May 22, 2024 | J57: X | K57: Marc Owen Jones (@marcowenjones) | L57: Marc Owen Jones (@marcowenjones) | O57: English, Arabic | P57: Rafah | Q57: רפיח | R57: Post | S57: Video, Text | T57: Forced Displacement, Air Strike, Warning | U57: IDF (Israel Defense Forces) | V57: Rafah | W57: Avichay Adraee
A58: 362 | B58: https://x.com/moshebs11/status/1766830282219372906 | C58: Bringing a torah scroll to Nezarim Corridor | D58: הבאת מגילת תורה למעבר נצרים | E58: IDF soldiers singing and dancing as they bring a Torah scroll to Nezarim Corridor, Gaza. | F58: חיילי צה"ל שרים ורוקדים כשהם מביאים ספר תורה למעבר נצרים, עזה. | G58: March 10, 2024 | J58: X | K58: Moshe ben Shitrit (@moshebs11) | L58: משה בן שטרית (@moshebs11) | O58: Hebrew | P58: Netzarim Corridor | Q58: מסדרון נצרים | R58: Post | S58: Text, Video | T58: Religious Right, Israeli Soldier Movies | U58: IDF (Israel Defense Forces) | V58: Netzarim Corridor
A59: 363 | B59: https://x.com/ytirawi/status/1794113236708573451 | C59: IDF soldier details destruction of Khuza'a (Khirbat Akhzaya) as revenge, as a part of "Oz and Nir" Operation | D59: חייל צה"ל מפרט את הריסת ח'וּזַ֫אעַה (חִ֫'רְבֶּת אֶחְ'זַ֫אעַה) כנקמה, כחלק ממבצע "עוז וניר" | E59: IDF soldier describes his part in destroying the village of Khuza'a (Khirbat Akhzaya) in Gaza, as a revenge for Oct. 7. The post claims to expose genocidal operation "Oz and Nir". | F59: חייל צה"ל מתאר את חלקו בהריסת הכפר ח'וּזַ֫אעַה (חִ֫'רְבֶּת אֶחְ'זַ֫אעַה) בעזה, כנקמה על ה-7 באוקטובר. הפוסט טוען לחשוף את מבצע רצח עם "עוז וניר". | G59: May 25, 2024 | H59: January 8, 2024 | I59: January 8, 2024 | J59: X | K59: Younis Tirawi (@ytirawi) | L59: Younis Tirawi (@ytirawi) | O59: Hebrew | P59: Khuza'a | Q59: ח'וזעה | R59: Post | S59: Photo, Text | T59: Collective Punishment, Domicide, Incitement to Genocide, Urbicide, Genocide, Bombing, Israeli Soldier Testimonies, Destruction | U59: IDF (Israel Defense Forces) | V59: Gaza Strip, Khuza'a
A60: 364 | B60: https://x.com/ytirawi/status/1795129920902873557 | C60: IDF using hospital as mililtary base | D60: צה"ל משתמש בבית חולים בתור בסיס צבאי | E60: IDF soldiers relax on hospital beds at Noura Kaabi Dialysis Hospital in the Jabalia Refugee camp. Smiles and good cheer abound. | F60: חיילי צה"ל נחים על מיטות בבית החולים לדיאליזה נורה קאבי במחנה הפליטים ג'באליה. חיוכים ואווירה טובה שוררים. | G60: May 27, 2024 | J60: X | K60: Younis Tirawi (@ytirawi) | L60: Younis Tirawi (@ytirawi) | O60: English | P60: Jabaliya | Q60: ג'באליה | R60: Post | S60: Photo, Text | T60: Hospital, Israeli Soldier Photos | U60: IDF (Israel Defense Forces) | V60: Jabaliya
A61: 368 | B61: https://twitter.com/Bar_ShemUr/status/1757852992215056477 | C61: Likud spokesman warns hostage families against calling for elections | D61: דובר הליכוד מזהיר את משפחות החטופים מפני קריאה לבחירות | E61: Likud spokesman Guy Levi met with families of Israeli hostages, urging them to oppose new elections and warning that the political fallout would be far worse than before October 7. Several attendees described his remarks as a direct threat. | F61: דובר הליכוד גיא לוי נפגש עם משפחות של חטופים ישראלים ודחק בהן להתנגד לבחירות חדשות והזהיר שההשלכות הפוליטיות יהיו הרבה יותר גרועות מלפני ה-7 באוקטובר. כמה מהנוכחים תיארו את דבריו כאיום ישיר. | G61: February 14, 2024 | H61: January 30, 2024 | I61: January 30, 2024 | J61: X | K61: Bar Shem-Ur (@Bar_ShemUr) | L61: בר שם-אור (@Bar_ShemUr) | M61: Hatzinor | N61: https://x.com/Bar_ShemUr/status/1757863600578777418 | O61: Hebrew | Q61: 0 | R61: Post | S61: Text, Photo | T61: Abuse, Hostages, Hostage Deal, Journalistic Report | U61: Israeli Government, Hostages and Missing Families Forum
A62: 369 | B62: https://twitter.com/Uvda_tweet/status/1778496650798833931 | C62: Testimonies from negotiators on the condition of hostages | D62: עדויות של מנהלי משא ומתן על מצב חטופים | E62: A television documentary presenting accounts from individuals involved in recent negotiations for the return of Israeli hostages. The testimonies provide insight into the deteriorating conditions of the hostages and the urgency surrounding the negotiations. | F62: סרט תיעודי טלוויזיוני מציג דיווחים מאנשים מעורבים לאחרונה במשא ומתן להחזרת החטופים הישראלים. העדויות מספקות תובנה על התנאים המידרדרים של החטופים ועל דחיפות המו"מ. | G62: April 11, 2024 | J62: X | K62: Uvda with Ilana Dayan (@Uvda_tweet) | L62: עובדה עם אילנה דיין (@Uvda_tweet) | O62: Hebrew | Q62: 0 | R62: Post | S62: Video, Text | T62: Captivity Conditions, Civilians, Hostage Deal, Hostages, Journalistic Report, Interview, Israeli Negotiation Team | U62: Hamas, Shin Bet, Mossad
A63: 370 | B63: https://twitter.com/_selftitled_/status/1784272179817041951 | C63: Interview with adviser to Qatari Prime Minister: Hostage deal repeatedly blocked at final stages | D63: ראיון עם יועץ לראש ממשלת קטאר: עסקת בני הערובה נחסמה שוב ושוב בשלבים הסופיים | E63: Qatari official stated that "every time a [hostage] deal was near, it was blocked." | F63: בכיר קטארי הצהיר כי "כל פעם שעסקה [חטופים] הייתה קרובה, היא נחסמה" | G63: April 27, 2024 | H63: April 27, 2024 | I63: April 27, 2024 | J63: X | K63: Sof (@selftitled) | L63: Sof (@selftitled) | M63: Haaretz | O63: Hebrew | Q63: 0 | R63: Post | S63: Photo, Text | T63: Captivity Conditions, Ceasefire | U63: Mossad, Qatar, Shin Bet, Israeli Government
A64: 360 | B64: https://x.com/ireallyhateyou/status/1802435990251848148 | C64: Moshe Feiglin's statement on the need to conquer Gaza | D64: הצהרת משה פייגלין על הצורך לכבוש את עזה | E64: Moshe Feiglin asserts that Israel cannot tolerate the existence of a single "Islamo-Nazi" if it is to survive. "It's us or them" with explicit reference to Hitler's declaration against the Jews. | F64: משה פייגלין טוען שישראל לא יכולה לסבול את קיומו של "איסלאמו-נאצי" אחד, אם היא רוצה לשרוד. "זה אנחנו או הם" עם התייחסות מפורשת להצהרתו של היטלר נגד היהודים. | G64: June 16, 2024 | J64: X | K64: B.M. (@ireallyhateyou) | L64: B.M. (@ireallyhateyou) | M64: Keshet 12 | O64: Hebrew, English | P64: Israel | Q64: ישראל | R64: Post | S64: Video, Text | T64: Religious Right, Incitement to Genocide, Collective Punishment, Interview, Jewish Settlements in Gaza | V64: Israel | W64: Moshe Feiglin
A65: 365 | B65: https://x.com/ytirawi/status/1798462630736396472 | C65: IDF soldier speaks on "Oz and Nir" Operation in Khuza'a (Khirbat Akhzaya) | D65: חייל צה"ל מדבר על מבצע "עוז וניר" בח'וּזַ֫אעַה (חִ֫'רְבֶּת אֶחְ'זַ֫אעַה) | E65: Interview with IDF soldier regarding the destruction of Khuza'a (Khirbat Akhzaya), as a part of "Oz and Nir" Operation. The town of 13,000 Palestinians was completely destroyed. | F65: ראיון עם חייל צה"ל בנוגע להריסת ח'וּזַ֫אעַה (חִ֫'רְבֶּת אֶחְ'זַ֫אעַה), כחלק ממבצע "עוז וניר". העיירה של 13,000 פלסטינים נהרסה לחלוטין. | G65: June 6, 2024 | J65: X | K65: Younis Tirawi (@ytirawi) | L65: Younis Tirawi (@ytirawi) | N65: https://x.com/ytirawi | O65: English | P65: Khuza'a | Q65: ח'וזעה | R65: Post | S65: Text, Audio | T65: Forced Displacement, Domicide, Journalistic Report, Israeli Soldier Testimonies, Urbicide, Interview | U65: IDF (Israel Defense Forces) | V65: Gaza Strip, Khan Younis, Khuza'a
A66: 371 | B66: https://twitter.com/tomashinyu3/status/1747651031737979233 | C66: Confusion regarding cause of death of hostages Sherman, Beizer and Toledano | D66: חוסר בהירות לגבי סיבת המוות של בני הערובה שרמן, בייזר וטולדנו | E66: Survey of possible causes of death of three hostages-soldiers following IDF Spokesperson statement that they may have been suffocated or poisoned. The writer speculates whether the IDF may have intentionally killed the hostages and states as part of a policy of abandoning or killing the remaining hostages and if so, what the implications will be for Israel society. | F66: סקר של סיבות אפשריות למותם של שלושה חיילים-חטופים בעקבות הצהרת דובר צה"ל כי ייתכן שהם נחנקו או הורעלו. הכותב מעלה שאלה האם צה"ל הרג בכוונה את בני הערובה ומציין כחלק ממדיניות של נטישה או הרג של החטופים הנותרים ואם כן, מה יהיו ההשלכות על החברה הישראלית. | G66: January 17, 2024 | H66: January 17, 2024 | I66: January 17, 2024 | J66: X | K66: Tomer Sharon (@tomashinyu3) | L66: תומר שרון (@tomashinyu3) | O66: Hebrew | P66: Gaza Strip | Q66: רצועת עזה | R66: Post | S66: Text | T66: Hostages, Hostage Deal, Hannibal Directive | U66: Israeli Government, Hamas, IDF (Israel Defense Forces) | V66: Gaza Strip
A67: 1450 | B67: https://twitter.com/josh_hammer/status/1711185635229282605 | C67: The events of Saturday, October 7 are indescribable | D67: אין מילים כדי לתאר את אירועי שבת, 7 באוקטובר | E67: The author, Senior Editor-at-large of Newsweek at the time, describes his views about the causes of October 7 essentially arguing that there can be no peaceful solution. Prescribing instead a forced removal of "identifiable" civilian population from Gaza to Egypt, razing of infrastructure, Eradication of all Hamas members and infrastructure, re-annexation, installment of puppet regime. Blaming democratic US administrations and officials. | F67: המחבר, עורך בכיר של ניוזוויק באותה תקופה, מתאר את דעותיו לגבי הסיבות ל-7 באוקטובר, וטוען בעצם שאין פתרון של שלום. הוא ממליץ במקום זאת על גירוש בכוח של אוכלוסייה אזרחית "ניתנת לזיהוי" מעזה למצרים, הריסת תשתיות, חיסול כל חברי חמאס ותשתיותיהם, חזרה לסיפוח רצועת עזה והקמת משטר בובות בה. הוא מאשים את הממשלות והפקידים הדמוקרטיים בארצות הברית. | G67: October 9, 2023 | H67: October 9, 2024 | I67: October 9, 2024 | J67: X | K67: Josh Hammer (@josh_hammer) | L67: Josh Hammer (@josh_hammer) | O67: English | Q67: 0 | R67: Post | S67: Text | T67: Ethnic Cleansing, Religious Right, Annexation, Forced Displacement, Civilians, Collective Punishment, Incitement to Genocide, Hostages, Opinion, Demolition, Infrastructure, Conspiracy theories | U67: Egypt, Mossad, Hamas, Iran, Shin Bet, Hezbollah, United States, Qatar, IDF (Israel Defense Forces) | W67: Joe Biden, Benjamin Netanyahu, Almog Boker
A68: 1451 | B68: https://twitter.com/kann_news/status/1770492431990956343 | C68: Is there starvation in Gaza as claimed by WFO? | D68: האם יש רעב בעזה כפי שטוענת ה-WFO? | E68: Shaul Amsterdamsky in interview with Nurit Yohanan, Palestinian affairs correspondent at Kan who analyzes World Food Organization figures regarding starvation/malnutrition figures in Gaza following the publication of the World Food Programme's Integrated Food Security Phase Classification report. Yohanan judges the WFP figures to be largely accurate. | F68: שאול אמסטרדמסקי בראיון עם נורית יוחנן, כתבת לענייני פלסטינים ב"כאן", שמנתחת את הנתונים של ארגון המזון העולמי לגבי רעב/תת תזונה בעזה בעקבות פרסום דוח סיווג שלב הביטחון התזונתי של תוכנית המזון העולמית. יוחנן מעריכה שהנתונים של WFP מדויקים ברובם. | G68: March 20,2024 | H68: March 18, 2024 | I68: March 18, 2024 | J68: X | K68: Kann News (@kann_news) | L68: חדשות כאן(@kann_news) | N68: https://www.wfp.org/news/famine-imminent-northern-gaza-new-report-warns | O68: Hebrew | P68: Gaza Strip | Q68: רצועת עזה | R68: Post | S68: Video, Text | T68: Starvation, Analysis, Food | U68: World Food Programme, UN (United Nations), UNRWA (The UN Relief and Works Agency for Palestine Refugees) | V68: Gaza Strip
A69: 1453 | B69: https://twitter.com/ofercass/status/1783896320933036133 | C69: Police invade Hadash party HQ in Nazareth before the 1 May demonstration | D69: המשטרה פלשה למטה מפלגת חד"ש בנצרת לפני הפגנת 1 במאי | E69: Police search and vandalize artwork for the May 1st parade in Hadash party's club in Nazareth. Two people detained. | F69: המשטרה עשתה חיפוש במועדון מפלגת חד"ש בנצרת והשחיתה יצירות אמנות לקראת מצעד ה-1 במאי . שני אנשים נעצרו. | G69: April 26, 2024 | H69: April 26, 2024 | I69: April 26, 2024 | J69: X | K69: Ofer Cassif (@ofercass) | L69: עופר כסיף (@ofercass) | O69: Hebrew, English | Q69: 0 | R69: Post | S69: Video, Text | T69: Abuse, Palestinian Citizens of Israel, Vandalism, Limiting Free Speech | U69: Israeli Police
A70: 1454 | B70: https://twitter.com/petersavodnik/status/1778620648551829969 | C70: Pro-Israel campaign to discredit the Gaza Health Ministry's data | D70: קמפיין פרו-ישראלי להפרכת נתוני משרד הבריאות בעזה | E70: A report attempting to cast doubt on the Ministry of Health's claim, arguing that that Israel has killed "only" 22,000 and not 30,000 Gazans by April 2024. Allegedly this would put the ratio of combatants to non-combatants at 1:1. | F70: דו"ח המנסה לערער על טענת משרד הבריאות בעזה, וטוען כי ישראל הרגה "רק" 22,000 ולא 30,000 פלסטינים בעזה עד אפריל 2024. לכאורה, זה היה מציב את היחס בין לוחמים לאזרחים לא מעורבים על 1:1. | G70: April 11, 2024 | H70: April 6, 2024 | I70: April 6, 2024 | J70: X | K70: Peter Savodnik (@petersavodnik) | L70: Peter Savodnik (@petersavodnik) | N70: https://www.fdd.org/analysis/2024/04/09/hamas-run-gaza-health-ministry-admits-to-flaws-in-casualty-data/ | O70: English | P70: Gaza Strip | Q70: רצועת עזה | R70: Post | S70: Photo, Text | T70: Journalistic report, Civilians, Genocide, Doubting the Gaza death toll, Gaza death toll | U70: Gaza Health Ministry, Hamas, Foundation for the Defense of Democracies, IDF (Israel Defense Forces) | V70: Gaza Strip
A71: 428 | B71: https://twitter.com/CensoredMen/status/1765773664325075354 | C71: Popular Israeli Telegram channel mocks Palestinian child who died of starvation. | D71: ערוץ טלגרם ישראלי פופולרי לועג לילד פלסטיני שמת מרעב. | E71: An Israeli Telegram account published a mocking poster, presenting the deceased Palestinian child with cerebral palsy, Yazan al-Kafarneh, as an alien. | F71: חשבון טלגרם ישראלי פרסם פוסטר לועג, המציג את הילד הפלסטיני המנוח עם שיתוק מוחין, יזן אל-כפרנה, כאילו היה חייזר. | G71: March 7, 2024 | H71: March 4, 2024 | I71: March 7, 2024 | J71: X | K71: Censored Men (@CensoredMen) | L71: גברים מצונזרים (@CensoredMen) | O71: English, Hebrew | Q71: 0 | R71: Post | S71: Text, Photo | T71: Dehumanization, Humiliation, Children, Starvation, Social Media
A72: 429 | B72: https://twitter.com/EmilioMorenatti/status/1759669676810904020 | C72: IDF soldiers smile as they take a selfie against a backdrop of the ruins of Gaza. | D72: חיילות צה"ל מחייכות תוך צילום סלפי על רקע חורבות עזה. | E72: IDF female soldiers posed and smiled for a selfie photo among the ruins of destroyed Gazan homes. | F72: חיילות צה"ל מחייכות תוך כדי צילום סלפי על רקע חורבות הבתים ההרוסים בעזה. | G72: February 19, 2024 | J72: X | K72: Emilio Morenatti (@EmilioMorenatti) | L72: Emilio Morenatti (@EmilioMorenatti) | O72: English | P72: Gaza Strip | Q72: רצועת עזה | R72: Post | S72: Text, Photo | T72: Israeli Society, Abuse, Destruction, Dehumanization | U72: IDF (Israel Defense Forces) | V72: Gaza Strip
A73: 430 | B73: https://twitter.com/GLZRadio/status/1773260052683469178 | C73: Ex-IDF official calls to resettle Gaza on Israeli radio. | D73: ראש אכ"א לשעבר לאילנה דיין בגל"צ קורא להתיישבות מחדש בחבל עזה. | E73: Mordechai (Moti) Almoz, former IDF general and head of the Israeli Civil Administration, advocates resettling Gaza, accusing Palestinians of constant aggression and labeling them as "human animals." | F73: מרדכי (מוטי) אלמוז, ראש א"כ לשעבר, תומך בהתיישבות מחדש בעזה, ומאשים את הפלסטינים בתוקפנות מתמדת ומכנה אותם "חיות אדם." | G73: March 28, 2024 | H73: March 28, 2024 | I73: March 28, 2024 | J73: X | K73: GLZRadio (@GLZRadio) | L73: גל"צ (@GLZRadio) | O73: Hebrew | Q73: 0 | R73: Post | S73: Text, Photo | T73: Settlements, War Crimes, Religious Right, Dehumanization, Disengagement (2005) | U73: IDF (Israel Defense Forces)
A74: 431 | B74: https://twitter.com/GLZRadio/status/1779764062433284213 | C74: Smotrich describes Gazan civilians as Nazis and calls for imposing military rule in Gaza. | D74: סמוטריץ' מתאר את אזרחי עזה כנאצים וקורא להטיל שלטון צבאי בעזה. | E74: Finance Minister Bezalel Smotrich asserts that all Gazan civilians ("2 million people") are Nazis "who want to butcher, rape and kill any Jew", arguing that Israel should govern Gaza rather than any local civilian authority. | F74: שר האוצר בצלאל סמוטריץ' טוען שכל האזרחים בעזה ("2 מיליון אנשים") הם נאצים "שרוצים לשחוט, לאנוס ולרצוח כל יהודי", וטוען שישראל צריכה לשלוט בעזה עד שתימצא אזרחית מקומית מתונה. | G74: April 15, 2024 | H74: April 15, 2024 | I74: April 15, 2024 | J74: X | K74: GLZRadio (@GLZRadio) | L74: גל"צ (@GLZRadio) | O74: Hebrew | P74: Israel | Q74: ישראל | R74: Post | S74: Text, Photo | T74: Dehumanization, Annexation, Religious Right | U74: Israeli Government | V74: Israel | W74: Bezalel Smotritch
A75: 438 | B75: https://twitter.com/LensVeritatis/status/1774998396501373207 | C75: Soldiers, mostly shirtless, dance while mocking Gazan detainees and ridiculing Palestinian Dabke. | D75: חיילים, רובם ללא חולצות, רוקדים תוך כדי לעג לעצורים מעזה ולעג לדבקה הפלסטינית. | E75: Dozens of IDF soldiers staged a mocking display, with one standing atop a bulldozer bucket dressed in white overalls as worn by Gazan detainees, while others joined in by imitating and ridiculing the traditional Palestinian Dabke dance. | F75: עשרות חיילי צה"ל ערכו מופע לגלוג, כאשר אחד מהם עמד על דלי של דחפור לבוש במדי עבודה לבנים כמו אלו של עצורים מעזה, בעוד אחרים הצטרפו בחיקוי ולגלוג לריקוד הדבקה המסורתי הפלסטיני. | G75: April 2, 2024 | J75: X | K75: Dr Lens Veritatis (@LensVeritatis) | L75: Dr Lens Veritatis (@LensVeritatis) | O75: English | Q75: 0 | R75: Post | S75: Text, Video | T75: Israeli Society, Humiliation, Dehumanization, Destruction | U75: IDF (Israel Defense Forces)
A76: 440 | B76: https://twitter.com/MacaesBruno/status/1787573947690819907 | C76: Senior Likud official calls for indiscriminate killing of civilians in Rafah. | D76: בכיר בליכוד קורא להרג חסר הבחנה של אזרחים ברפיח. | E76: Shimon Boker, Deputy Chairman of the World Likud, in an interview to Ofira Asayag and Chaim Levinson, Channel 12: "We need to crack down on them(...) We should have entered Rafah already yesterday(...) There are no uninvolved people there. We need to go in and kill, and kill, and kill." | F76: שמעון בוקר, סגן יושב ראש הליכוד העולמי, בראיון לאופירה אסייג וחיים לוינסון, ערוץ 12: "אנחנו צריכים להכות בהם(...) היינו צריכים להיכנס לרפיח כבר אתמול(...) אין שם אנשים לא מעורבים. אנחנו צריכים להיכנס ולقتل, ולقتل, ולقتل." | G76: May 6,2024 | J76: X | K76: Bruno Macaes (@MacaesBruno) | L76: Bruno Macaes (@MacaesBruno) | M76: Keshet 12 | O76: English, Hebrew | P76: Israel | Q76: ישראל | R76: Post | S76: Text, Video | T76: Civilians, Collective Punishment, Dehumanization, Ethnic Cleansing, Incitement to Genocide, Israeli Society, Media | U76: Israeli Government | V76: Rafah, Israel | W76: Shimon Boker
A77: 1455 | B77: https://twitter.com/ytirawi/status/1774836624280473643 | C77: A defamation attempt against Palestinian journalist Younis Tirawi | D77: ניסיון הכפשה נגד העיתונאי הפלסטיני יוניס טיראווי. | E77: Tirawi was approached by a journallist from 13 News claiming that he, Tirawi, does not meet journalistic standards in his posts about IDF soldiers in Gaza. | F77: טיראווי: פנה אליו עיתונאי מחדשות-13 שטוען שהוא, טיראווי, לא עומד בסטנדרטים עיתונאיים בפוסטים שלו על חיילי צה"ל בעזה. | G77: April 1, 2024 | H77: April 1, 2024 | I77: April 1, 2024 | J77: X | K77: Younis Tirawi (@ytirawi) | L77: Younis Tirawi (@ytirawi) | O77: English | P77: Gaza Strip | Q77: רצועת עזה | R77: Post | S77: Text | T77: Journalistic Report, Journalists, Limiting Free Speech, Social Media | U77: IDF (Israel Defense Forces) | V77: Gaza Strip
A78: 1662 | B78: https://x.com/AssalRad/status/1799543857539108962 | C78: World coverage of Israel's rescue of four live hostages does not refer to hundreds of Palestinians killed in the event | D78: הכיסוי העולמי של חילוץ ארבעת חטופים חיים אינו מתייחס למאות הפלסטינים שנהרגו במהלך האירוע. | E78: Quoted reports regarding IDF operation to rescue 4 live hostages; none note the 200+ Palestinians killed during that event. | F78: דיווחים מצוטטים לגבי מבצע צה"ל לשחרור 4 חטופים חיים לא מציינים את 200+ הפלסטינים שנהרגו במהלך האירוע הזה. | G78: June 8, 2024 | H78: June 8, 2024 | I78: June 8, 2024 | J78: X | K78: Assal Rad (@AssalRad) | L78: Assal Rad (@AssalRad) | O78: English | P78: Gaza Strip | Q78: רצועת עזה | R78: Post | S78: Text, Photo | T78: Hostages, Civilians, Ground Operation, Media, Media bias | U78: Hamas, IDF (Israel Defense Forces) | V78: Gaza Strip
A79: 1663 | B79: https://x.com/Morpheus1099/status/1799407973791645979 | C79: Channel 13 journalist: Order exists to withhold Gaza bombing footage from Israeli public | D79: עיתונאית ערוץ 13: ישנה הוראה לא להראות לציבור בישראל צילומי תוצאות ההפצצות בעזה | E79: Hila Elroi on Channel 13 news admits that there exists an order not to expose Israelis to the results of Israel's bombing of Gaza. | F79: הילה אלרואי בחדשות ערוץ 13 מודה שיש הוראה לא לחשוף את הישראלים לתוצאות ההפצצות של ישראל על עזה. | G79: June 8, 2024 | H79: June 8, 2024 | I79: June 8, 2024 | J79: X | K79: Facism has won 2024 (@morpheus1099) | L79: Stop the Genocide (@morpheus1099) | M79: Reshet 13 | O79: Hebrew | P79: Gaza Strip | Q79: רצועת עזה | R79: Post | S79: Text, Video | T79: Media, Communication Blackout, Destruction, Propaganda, Censorship, Limiting Free Speech | U79: Hamas, IDF (Israel Defense Forces) | V79: Gaza Strip
A80: 1666 | B80: https://x.com/rafaelshimunov/status/1795813951940202938 | C80: Arrest of Palestinian Citizen in Israel after social media post expressing solidarity and sorrow following Rafah strike | D80: מעצר של אזרחית פלסטינית בישראל לאחר פוסט ברשתות החברתיות המביע סולידריות ועצב בעקבות הטבח ברפיח | E80: A Palestinian citizen of Israel was arrested following a social media post expressing solidarity with civilians in Gaza after the Rafah tent camp strike. Footage shows police arresting the woman, tying her hands with a ziptie, blindfolding her, and leading her from the police vehicle. | F80: מעצר אזרחית פלסטינית ישראלית בעקבות פוסט ברשתות החברתיות שמביע סולידריות עם אזרחים בעזה לאחר הטבח במחנה האוהלים ברפיח. צילומים מראים את המשטרה עוצרת את האישה, קושרת את ידיה עם אזיקון, מכסה את עיניה ומובילה אותה לרכב המשטרתי. | G80: May 29 2024 | H80: May 29, 2024 | I80: May 29, 2024 | J80: X | K80: Rafael Shimunov (@rafaelshimunov) | L80: רפאל שימונוב (@rafaelshimunov) | O80: Hebrew, Arabic | P80: Majd al-Krum | Q80: מג'ד אל-כרום | R80: Post | S80: Text, Video | T80: Palestinian Citizens of Israel, Social Media, Civilians, Limiting Free Speech, Abuse | U80: Israeli Police | V80: Israel
A81: 2109 | B81: https://x.com/AMokhallalati/status/1849082736402632878 | C81: Testimony from Kamal Adwan Hospital amid heavy bombardment | D81: עדות מבית החולים קמאל אדואן תחת הפצצות כבדות | E81: Orthopedic surgeon Dr. Mohammed Obeid, working with Doctors Without Borders, describes the dire humanitarian and medical crisis at Kamal Adwan Hospital in northern Gaza in a recorded testimony from October 22. He details the ongoing bombardment, overwhelmed facilities, and inability to treat many of the injured. (Dr. Obeid was later arrested by the IDF.) | F81: המנתח האורתופדי ד"ר מוחמד עבאיד, העובד עם רופאים ללא גבולות, מתאר את המשבר ההומניטרי והרפואי החמור בבית החולים קמאל עדואן בצפון עזה בעדות מוקלטת מ-22 באוקטובר. הוא מתאר הפצצות מתמשכות, משאבים מועטים, וחוסר היכולת לטפל בהרבה מהפצועים. (ד"ר עבאיד נעצר מאוחר יותר על ידי צה"ל.) | G81: October 23, 2024 | H81: October 22, 2024 | I81: October 22, 2024 | J81: X | K81: Ahmed El Mokhallati (@AMokhallalati) | L81: Ahmed El Mokhallati (@AMokhallalati) | N81: https://www.youtube.com/watch?v=qEp2wv7wNdU | O81: English | P81: Kamal Adwan Hospital | Q81: בית החולים כמאל עדואן | R81: Post | S81: Photo, Text | T81: Public Health, Healthcare Workers, Hospital, Bombing, Testimony, Air Strike, Blockade | U81: IDF (Israel Defense Forces), MSF - Médecins Sans Frontières (Doctors Without Borders) | V81: Kamal Adwan Hospital, North Gaza, Beit Lahiya | W81: Shimon Boker
A82: 2121 | B82: https://x.com/AbujomaaGaza/status/1846483876014703073 | C82: IDF detonates buildings in Jabaliya camp | D82: צה"ל מפוצץ בניינים במחנה ג'בליה | E82: IDF plants explosives in heart of Jabalyia camp, destroying tens of homes, many of them inhabited. | F82: צה"ל מטמין חומרי נפץ בלב מחנה ג'באליה, הורס עשרות בתים, רבים מהם מאוכלסים. | G82: October 16, 2024 | H82: October 16, 2024 | I82: October 16, 2024 | J82: X | K82: Motasem Dalloul (@abujoummaaGaza) | L82: Motasem Dalloul (@abujoummaaGaza) | O82: English | P82: Jabaliya | Q82: ג'באליה | R82: Post | S82: Text, Video | T82: Civilians, Destruction, Demolition, Explosives | U82: IDF (Israel Defense Forces) | V82: North Gaza, Gaza Strip, Jabaliya
A83: 2122 | B83: https://x.com/AbujomaaGaza/status/1849732808333287510 | C83: Updates on IDF attacks on Gaza October 25, 2024 | D83: עדכונים על התקפות צה"ל על עזה 25 באוקטובר 2024 | E83: Update on attacks throughout Gaza resulting in over 200 deaths of civilians. Paramedics and civil defence personnel required to surrender to IDF. Israeli forces reportedly surrounded Kamal Adwan Hospital and struck its oxygen plant leading to the deaths of patients in critical condition. | F83: עדכון על התקפות ברחבי עזה שגרמו ליותר מ-200 הרוגים אזרחיים. נדרשים פרמדיקים ואנשי הגנה אזרחית להיכנע לצה"ל. כוחות ישראליים דיווחו על כך שהקיפו את בית החולים קמאל אדואן ופגעו במפעל החמצן שלו, מה שהוביל למותם של מטופלים במצב קריטי. | G83: October 25, 2024 | H83: October 24, 2024 | I83: October 25, 2024 | J83: X | K83: Motasem Dalloul (@abujoummaaGaza) | L83: Motasem Dalloul (@abujoummaaGaza) | O83: English | P83: Kamal Adwan Hospital, Beit Lahiya, Jabalia, Khan Yunis | Q83: בית החולים כמאל עדואן, בית לאהיא, ג'באליה, חאן יונס | R83: Post | S83: Text | T83: Hospital, Forced Displacement, Children, Journalistic Report, Air Strike, Public Health, Bombing, Ground Operation | U83: Gaza Health Ministry, IDF (Israel Defense Forces) | V83: North Gaza, Khan Younis, The Indonesian Hospital, Kamal Adwan Hospital, Beit Lahiya, Jabaliya | W83: Dr Hussam Abu Safiya
A84: 2123 | B84: https://x.com/AbujomaaGaza/status/1853847622236418257 | C84: 61 killed in IDF attacks on Gaza since morning | D84: 61 נהרגו בהתקפות צה"ל על עזה מאז הבוקר | E84: Medical sources report that 61 killed in IDF attacks - 46 of them in Jabaliya, Beit Hanoun, and Beit Lahiya in northern Gaza. | F84: מקורות רפואיים מדווחים על 61 הרוגים בהתקפות צה"ל - 46 מהם בג'באליה, בית חנון ובית לאהיה בצפון עזה. | G84: November 5, 2024 | H84: November 5, 2024 | I84: November 5, 2024 | J84: X | K84: Motasem Dalloul (@abujoummaaGaza) | L84: Motasem Dalloul (@abujoummaaGaza) | O84: English | P84: Jabaliya, Beit Hamoun, Beit Lahiya | Q84: ג'באליה, בית חאנון, בית לאהיא | R84: Post | S84: Text, Photo | T84: Air Strike, Bombing, Civilians, Journalistic Report | U84: Gaza Health Ministry, IDF (Israel Defense Forces) | V84: North Gaza, Beit Lahiya, Khan Younis, Jabaliya
A85: 2124 | B85: https://x.com/AbujomaaGaza/status/1854253562190090316 | C85: A Gazan journalist describes how he is living | D85: עיתונאי מעזה מתאר כיצד הוא חי | E85: This the fifth location where the writer has taken shelter with his family and remaining siblings in dire conditions | F85: זה המקום החמישי שבו הסופר מצא מקלט עם משפחתו ואחיו הנותרים בתנאים קשים. | G85: November 6, 2024 | J85: X | K85: Motasem Dalloul (@abujoummaaGaza) | L85: Motasem Dalloul (@abujoummaaGaza) | O85: English | P85: Gaza Strip | Q85: רצועת עזה | R85: Post | S85: Text | T85: Children, Civilians, Water, Food, Forced Displacement, Sanitation, Genocide, Electricity, Humanitarian Crisis, Testimony, Destruction | V85: Gaza Strip
A86: 2126 | B86: https://x.com/AbujomaaGaza/status/1855212378335391870 | C86: Crisis at Kamal Adwan Hospital during the late 2024 military operation in North Gaza | D86: משבר בבית החולים כמאל עדואן במהלך מבצע צבאי בסוף 2024 בצפון עזה | E86: Dr Hussam abu Safieh reports on desperate medical crisis at Kamal Adwan hospital in wake of IDF incursion | F86: ד"ר חוסאם אבו ספיה מדווח על משבר רפואי נואש בבית החולים כמאל עדואן בעקבות חדירת צה"ל | G86: November 9, 2024 | H86: November 9, 2024 | I86: November 9, 2024 | J86: X | K86: Motasem Dalloul (@abujoummaaGaza) | L86: Motasem Dalloul (@abujoummaaGaza) | O86: Arabic | P86: Kamal Adwan Hospital | Q86: בית החולים כמאל עדואן | R86: Post | S86: Video, Text | T86: Civilians, Disease, Public Health, Healthcare Workers, Hospital, Medicine, Testimony | U86: Gaza Health Ministry, IDF (Israel Defense Forces) | V86: Kamal Adwan Hospital | W86: Dr Hussam Abu Safiya
A87: 2127 | B87: https://x.com/AbujomaaGaza/status/1859190079702405379 | C87: Report from Dr Hussam abu Safieh re deaths at Kamal Adwan hospital | D87: דוח מד"ר חוסאם אבו ספיה על מקרי המוות בבית החולים כמאל עדואן | E87: Dr Hussam abu Safieh reports that during the 24 hours between November 19-20 one person died of dehydration and the hospital received 17 cases of dehydration and malnutrition among children. | F87: ד"ר חוסאם אבו ספיה מדווח שבמהלך 24 השעות בין ה-19 ל-20 בנובמבר, אדם אחד מת מהתייבשות ובית החולים קיבל 17 מקרים של התייבשות ותת תזונה בקרב ילדים. | G87: November 20, 2024 | H87: November 19, 2024 | I87: November 20, 2024 | J87: X | K87: Motasem Dalloul (@abujoummaaGaza) | L87: Motasem Dalloul (@abujoummaaGaza) | O87: English | P87: Kamal Adwan Hospital | Q87: בית החולים כמאל עדואן | R87: Post | S87: Text, Video | T87: Public Health, Healthcare Workers, Journalistic report, Children, Civilians, Testimony, Malnutrition, Water | U87: Gaza Health Ministry | V87: Kamal Adwan Hospital, North Gaza | W87: Dr Hussam Abu Safiya
A88: 464 | B88: https://twitter.com/RamAbdu/status/1749971465422745729 | C88: Footage shows Israeli forces killing a Palestinian carrying a white flag. | D88: הצילומים מראים כוחות ישראליים הורגים פלסטיני שנושא דגל לבן. | E88: A Palestinian journalist documented the killing of 51-year-old Ramzi Abu Sahlool in the Mawasi area, on January 22, 2024. The incident occurred after residents were forced to flee from a zone previously declared safe by the Israeli military. Abu Sahlool, holding a white flag, was attempting to evacuate his family when he was shot and killed by Israeli forces. | F88: עיתונאי פלסטיני תיעד את הריגתו של רמזי אבו סהלול בן ה-51 באזור המוואסי, ב-22 בינואר 2024. האירוע התרחש לאחר שהתושבים נאלצו לברוח מאזור שהוכרז קודם לכן כבטוח על ידי הצבא הישראלי. אבו סהלול, שהחזיק בדגל לבן, ניסה לפנות את משפחתו כאשר נורה ונורה למוות על ידי כוחות ישראליים. | G88: January 24, 2024 | H88: January 22, 2024 | I88: January 22, 2024 | J88: X | K88: Ramy Abdu (@RamAbdu) | L88: Ramy Abdu (@RamAbdu) | M88: ITV News | O88: English, Arabic | P88: Al Mawasi | Q88: אל-מוואסי | R88: Post | S88: Text, Video | T88: Civilians, Murder, Rules of Engagement, War Crimes, Journalistic Report, Shooting | U88: IDF (Israel Defense Forces) | V88: Gaza Strip, Al Mawasi
A89: 465 | B89: https://twitter.com/RamAbdu/status/1764759225241129162 | C89: IDF soldiers mock blindfolded Palestinian detainees | D89: חיילי צה"ל לועגים למעוכבים פלסטינים עם כיסוי עיניים | E89: Female IDF soldiers shared a video showing blindfolded Palestinian detainees kneeling, while mocking them and accusing them of being "Islamic Jihad" or "Nukhba" members. They also ridiculed a detainee who urinated in his pants. | F89: חיילות צה"ל שיתפו סרטון המראה עצורים פלסטינים עם כיסוי עיניים, על ברכיהם, תוך כדי שחיילי צה"ל לועגים להם ומאשימים אותם בכך שהם חברים ב"ג'יהאד האסלאמי" או ב"נוחבה". הן גם לגלגו על עצור שהשתין במכנסיו. | G89: March 4, 2024 | J89: X | K89: Ramy Abdu (@RamAbdu) | L89: Ramy Abdu (@RamAbdu) | O89: English, Hebrew | Q89: 0 | R89: Post | S89: Text, Video | T89: Abuse, Captivity Conditions, Civilians, Collective Punishment, Dehumanization, Humiliation, Israeli Society, Torture, Social Media, Detention Center, Detainees | U89: IDF (Israel Defense Forces)
A90: 468 | B90: https://twitter.com/RamAbdu/status/1780281723424547297 | C90: Palestinian child tortured in IDF detention | D90: ילד פלסטיני עונה במעצר של צה"ל | E90: A Palestinian child, recently released from Israeli detention, testifies that he has been beaten with iron bars, stripped naked, subjected to relentless torture, and denied sleep. | F90: ילד פלסטיני, ששוחרר לאחרונה ממעצר ישראלי, מעיד כי הוכה עם מוטות ברזל, הופשט, עונה ללא רחמים, ונמנעה ממנו שינה. | G90: April 16, 2024 | J90: X | K90: Ramy Abdu (@RamAbdu) | L90: Ramy Abdu (@RamAbdu) | O90: English, Arabic | Q90: 0 | R90: Post | S90: Text, Video | T90: Abuse, Captivity Conditions, Children, Civilians, Collective Punishment, Humiliation, Torture, Testimony, Detention Center, War Crimes, Detainees | U90: Israeli Prison
A91: 469 | B91: https://twitter.com/RamAbdu/status/1781018819961454697 | C91: Two Palestinians die in detention; thousands forcibly disappeared. | D91: שניים פלסטינים מתים במעצר; אלפים נלקחו בכוח ונעלמו. | E91: Two detainees from Gaza have died in Israeli detention centers while being interrogated. Thousands of Palestinians have been forcibly disappeared with their fate unknown, amid frequent reports of dozens being killed inside Israeli prisons. | F91: שני עצורים מעזה מתו במרכזי מעצר ישראליים במהלך חקירתם. אלפי פלסטינים נלקחו בכוח ונעלמו, גורלם לא ידוע, על רקע דיווחים תכופים על עשרות שנרצחו בתוך בתי הכלא הישראלים. | G91: April 18, 2024 | J91: X | K91: Ramy Abdu (@RamAbdu) | L91: Ramy Abdu (@RamAbdu) | M91: Kan 11 | N91: https://www.kan.org.il/content/kan-news/defense/739774/#:~:text=%D7%A9%D7%A0%D7%99%20%D7%A2%D7%A6%D7%95%D7%A8%D7%99%D7%9D%20%D7%A2%D7%96%D7%AA%D7%99%D7%9D%20%D7%9E%D7%AA%D7%95%20%D7%91%D7%93%D7%A8%D7%9A%20%D7%9C%D7%9E%D7%AA%D7%A7%D7%9F%20%D7%9B%D7%9C%D7%99%D7%90%D7%94%20%D7%91%D7%99%D7%A9%D7%A8%D7%90%D7%9C%3B%20%D7%9C%D7%95%D7%97%D7%9E%D7%99%D7%9D%20%D7%9E%D7%99%D7%97%D7%99%D7%93%D7%94%20%D7%9E%D7%99%D7%95%D7%97%D7%93%D7%AA%20%D7%A0%D7%97%D7%A7%D7%A8%D7%95,-%D7%A9%D7%A0%D7%99%20%D7%A2%D7%A6%D7%95%D7%A8%D7%99%D7%9D%20%D7%A2%D7%96%D7%AA%D7%99%D7%9D&text=%D7%94%D7%9E%D7%A9%D7%98%D7%A8%D7%94%20%D7%94%D7%A6%D7%91%D7%90%D7%99%D7%AA%20%D7%94%D7%97%D7%95%D7%A7%D7%A8%D7%AA%20%D7%94%D7%97%D7%9C%D7%94%20%D7%91%D7%99%D7%9E%D7%99%D7%9D,%D7%97%D7%9E%D7%99%D7%A9%D7%99)%20%D7%91%D7%97%D7%93%D7%A9%D7%95%D7%AA%20%D7%94%D7%A2%D7%A8%D7%91%20%D7%91%D7%9B%D7%90%D7%9F%2011. | O91: English, Hebrew | Q91: 0 | R91: Post | S91: Text | T91: Captivity Conditions, Detention Center, Detainees | U91: IDF (Israel Defense Forces)
A92: 470 | B92: https://twitter.com/RamAbdu/status/1785074198844453223 | C92: Israeli soldiers take photographs while wearing Palestinian women's clothes in Gaza home | D92: חיילי צה"ל מצטלמים בזמן שהם לובשים בגדי נשים פלסטיניות בבית בעזה | E92: While over 10,000 women are reported killed, IDF soldiers dress in displaced Palestinian women's clothing and take photos. | F92: בעת שדווח על הריגת יותר מ-10,000 נשים, חיילי צה"ל מתלבשים בבגדי נשים פלסטיניות עקורות ומצלמים תמונות. | G92: April 30, 2024 | J92: X | K92: Ramy Abdu (@RamAbdu) | L92: Ramy Abdu (@RamAbdu) | O92: English | P92: Gaza Strip | Q92: רצועת עזה | R92: Post | S92: Text, Photo | T92: Women, War Crimes, Social Media, Sexual Violence, Humiliation, Civilians | U92: IDF (Israel Defense Forces) | V92: Gaza Strip
A93: 471 | B93: https://twitter.com/RamAbdu/status/1785941575157067916 | C93: Palestinian detainee recounts physical and mental abuse by IDF | D93: עציר פלסטיני מתאר התעללות פיזית ונפשית על ידי צה"ל | E93: Jamal al-Eissawi, a Palestinian recently released from IDF detention, recounts enduring relentless abuse, including humiliation, the stripping of dignity, beatings with iron rods, dog attacks, and various other forms of extreme torture and harassment. | F93: ג'מאל אל-עיסאווי, פלסטיני ששוחרר לאחרונה ממעצר צה"ל, מתאר חוויות של התעללות מתמשכת, כולל השפלה, שלילת כבוד, מכות עם מוטות ברזל, התקפות כלבים וצורות אחרות של עינויים והטרדות קשות. | G93: May 2, 2024 | J93: X | K93: Ramy Abdu (@RamAbdu) | L93: Ramy Abdu (@RamAbdu) | O93: English, Arabic | Q93: 0 | R93: Post | S93: Text, Video | T93: Abuse, Captivity Conditions, Civilians, Humiliation, Torture, Testimony, Detention Center, Detainees | U93: IDF (Israel Defense Forces)
A94: 425 | B94: https://twitter.com/AlonLeeGreen/status/1787892635186712737 | C94: IDF tank drives into Gaza signs and fires indiscriminately at the Rafah Crossing to Egypt | D94: טנק של צה"ל נכנס לרצועת עזה, חוצה את מעבר רפיח למצרים ויורה באקראי. | E94: IDF soldiers drive a tank into the Gaza sign near the arrivals building in the Rafah Crossing from Egypt, drive into a "I ❤️ Gaza" sign nearby, and record themselves firing indiscriminately from a tank at civilian structures in Gaza City. | F94: חיילי צה"ל נוהגים טנק לעבר שלט "עזה" ליד בניין ההגעה במעבר רפיח ממצרים, פוגעים בשלט "אני ❤️ עזה" הסמוך, ומקליטים את עצמם יורים באקראי מטנק לעבר מבנים אזרחיים בעיר עזה. | G94: March 7, 2024 | J94: X | K94: Alon-Lee Green (@AlonLeeGreen) | L94: אלון-לי גרין (@AlonLeeGreen) | O94: Hebrew | P94: Rafah | Q94: רפיח | R94: Post | S94: Text, Video | T94: Collective Punishment, Vandalism, Abuse, Infrastructure, Indiscriminate Shooting, Destruction, Israeli Soldier Movies | U94: IDF (Israel Defense Forces) | V94: Rafah
A95: 522 | B95: https://twitter.com/ireallyhateyou/status/1780222143445205191 | C95: A man wears a "May your village burn" t-shirt in Mishmar HaSharon | D95: גבר לובש חולצת טי עם הכיתוב "שיישרף לכם הכפר" במושב משמר השרון | E95: A picture taken by Haaretz journalist Niv Hadas documents a young man wearing a t-shirt bearing the slogan "may your village burn" in Mishmar HaSharon, at a place where many Arabs work. The man appears to belong to the religious right. | F95: תמונה שצולמה על ידי העיתונאי ניב הדס מהארץ מתעדת צעיר שלובש חולצה עם הסלוגן "שישרף לכם הכפר" במושב משמר השרון, במקום שבו עובדים רבים ערבים. נראה כי האיש שייך לזרם הדתי-ימני. | G95: April 16, 2024 | H95: April 16, 2024 | I95: April 16, 2024 | J95: X | K95: B.M. (@ireallyhateyou) | L95: B.M. (@ireallyhateyou) | N95: https://x.com/NivHadas/status/1780156825351905721 | O95: Hebrew, English | P95: Mishmar HaSharon | Q95: משמר השרון | R95: Post | S95: Photo | T95: Israeli Society, Incitement to Violence, Religious Right | V95: Israel
A96: 523 | B96: https://twitter.com/ireallyhateyou/status/1781995666593456397 | C96: Israel's Finance Minister Bezalel Smotrich interviews on Galatz stating that all Gazans are Nazis | D96: שר האוצר של ישראל, בצלאל סמוטריץ', מתראיין בגלצ ואומר שכל תושבי עזה נאצים. | E96: Israel's Finance Minister Bezalel Smotrich claims that all 2 million Gazans are Nazis "who want to slaughter, rape and murder every Jew". He adds that Israel must occupy Gaza until Hamas is defeated and replaced. | F96: שר האוצר של ישראל, בצלאל סמוטריץ', טוען שכל 2 מיליון תושבי עזה הם נאצים "שרוצים לשחוט, לאנוס ולרצוח כל יהודי". הוא מוסיף שישראל חייבת לכבוש את עזה עד שחמאס יובס ויוחלף. | G96: April 21, 2024 | H96: April 21, 2024 | I96: April 21, 2024 | J96: X | K96: B.M. (@ireallyhateyou) | L96: B.M. (@ireallyhateyou) | M96: Galey Tzahal | O96: Hebrew, English | P96: Israel | Q96: ישראל | R96: Post | S96: Audio | T96: Interview, Opinion, Collective Punishment, Dehumanization, Media | U96: Israeli Government | V96: Gaza Strip, Israel | W96: Bezalel Smotritch
A97: 883 | B97: https://twitter.com/tparsi/status/1774872023098888465 | C97: A survey of Israel's systematic violations of international humanitarian law | D97: סקר על ההפרות השיטתיות של ישראל את החוק ההומניטרי הבינלאומי | E97: Israel is breaking long-standing rules of war by attacking protected places like embassies and hospitals, blocking aid deliveries, and allegedly using starvation as a weapon - actions that may count as war crimes. These aren't accidental violations, but seem to be part of a deliberate attempt to ignore or change international laws, which is also backed by the US government. | F97: ישראל מפרה חוקי מלחמה ארוכי שנים על ידי תקיפת מקומות מוגנים כמו שגרירויות ובתי חולים, חסימת משלוחי סיוע, וככל הנראה שימוש ברעב כנשק - פעולות שעשויות להיחשב כפשעי מלחמה. אלו לא הפרות מקריות, אלא נראות כחלק מניסיון מכוון להתעלם או לשנות חוקים בינלאומיים, דבר שגם נתמך על ידי ממשלת ארצות הברית. | G97: April 1, 2024 | J97: X | K97: Trita Parsi (@tparsi) | L97: Trita Parsi (@tparsi) | O97: English | Q97: 0 | R97: Post | S97: Text, Photo | T97: Humanitarian Law, War Crimes, Analysis | U97: United States, Israeli Government | W97: Joe Biden, Benjamin Netanyahu
A98: 1020 | B98: https://x.com/AssalRad/status/1850360530730709105 | C98: Different UN officials warn of Gaza's annihilation but U.S. looks away | D98: פקידים שונים באומות המאוחדות מזהירים מפני השמדת עזה, אך ארצות הברית מסיטה את מבטה. | E98: UN agencies warn of catastrophic humanitarian crisis in Gaza, with reports of mass starvation, indiscriminate attacks, and potential ethnic erasure—while the U.S. ignores their pleas, undermining its own claims to uphold international law. | F98: סוכנויות האומות המאוחדות מזהירות על משבר הומניטרי קטסטרופלי בעזה, עם דיווחים על רעב המוני, התקפות אקראיות ופוטנציאל למחיקה אתנית—בעוד שהארצות הברית מתעלמת מהפניות שלהן, ומערערת את טענתה שהיא שומרת על החוק הבינלאומי. | G98: October 27, 2024 | J98: X | K98: Assal Rad (@AssalRad) | L98: Assal Rad (@AssalRad) | O98: English | P98: Gaza Strip | Q98: רצועת עזה | R98: Post | S98: Text | T98: Ceasefire, Humanitarian Law, War Crimes | U98: United States, Israeli Government, UN (United Nations), UNICEF (United Nations Children's Fund), OCHA (UN Office for the Coordination of Humanitarian Affairs) | V98: Gaza Strip
